Workbook

Sheet Netplay
A1: Attraction DSR OF JUNE 26 | N1: =TODAY()-1 -> 46290 | O1: =TODAY() -> 46291
A2: DATE | C2: DAY | D2: Net Play | P2: MTD ACH
D3: Target | E3: Actual Sale | F3: Ach% | G3: Bills target | H3: Bills | I3: Ach % | J3: MTD TARGET | K3: MTD ACH | L3: MTD ACH % | M3: Qty | Q3: Target | R3: Actual Sale | S3: Ach%
A4: 46266 | B4: 1 | C4: TUE | D4: 4597.4185 | E4: 0 | F4: =E4/D4 -> 0 | G4: =D4/250 -> 18.389674 | H4: 0 | I4: =H4/G4 -> 0 | J4: =+D4 -> 4597.4185 | K4: =+E4 -> 0 | L4: =+K4/J4 -> 0 | M4: 0 | P4: Today | Q4: =+VLOOKUP(O1,A4:D34,4,0) -> 11996.078 | R4: =+VLOOKUP(O1,A4:E34,5,0) -> 0 | S4: =R4/Q4 -> 0
A5: =+A4+1 -> 46267 | B5: 2 | C5: WED | D5: 4760.6694 | E5: 0 | F5: =E5/D5 -> 0 | G5: =D5/250 -> 19.042677 | H5: 0 | I5: =H5/G5 -> 0 | J5: =+D5+J4 -> 9358.0879 | K5: =+E5+K4 -> 0 | L5: =+K5/J5 -> 0 | M5: 0 | P5: MTD | Q5: =+VLOOKUP(O1,A4:J35,10,0) -> 181800.24 | R5: =+VLOOKUP(O1,A4:K35,11,0) -> 47200 | S5: =R5/Q5 -> 0.25962562
A6: =+A5+1 -> 46268 | B6: 3 | C6: THU | D6: 5336.5905 | E6: 2000 | F6: =E6/D6 -> 0.37477112 | G6: =D6/250 -> 21.346362 | H6: 5 | I6: =H6/G6 -> 0.23423195 | J6: =+D6+J5 -> 14694.678 | K6: =+E6+K5 -> 2000 | L6: =+K6/J6 -> 0.13610369 | M6: 8
A7: =+A6+1 -> 46269 | B7: 4 | C7: FRI | D7: 8061.591 | E7: 3000 | F7: =E7/D7 -> 0.37213498 | G7: =D7/250 -> 32.246364 | H7: 9 | I7: =H7/G7 -> 0.27910124 | J7: =+D7+J6 -> 22756.269 | K7: =+E7+K6 -> 5000 | L7: =+K7/J7 -> 0.21971967 | M7: 12
A8: =+A7+1 -> 46270 | B8: 5 | C8: SAT | D8: 10551.494 | E8: 2750 | F8: =E8/D8 -> 0.2606266 | G8: =D8/250 -> 42.205976 | H8: 10 | I8: =H8/G8 -> 0.23693327 | J8: =+D8+J7 -> 33307.763 | K8: =+E8+K7 -> 7750 | L8: =+K8/J8 -> 0.23267849 | M8: 11
A9: =+A8+1 -> 46271 | B9: 6 | C9: SUN | D9: 11801.484 | E9: 0 | F9: =E9/D9 -> 0 | G9: =D9/250 -> 47.205936 | H9: 0 | I9: =H9/G9 -> 0 | J9: =+D9+J8 -> 45109.247 | K9: =+E9+K8 -> 7750 | L9: =+K9/J9 -> 0.17180513 | M9: 0
A10: =+A9+1 -> 46272 | B10: 7 | C10: MON | D10: 4504.142 | E10: 750 | F10: =E10/D10 -> 0.1665134 | G10: =D10/250 -> 18.016568 | H10: 3 | I10: =H10/G10 -> 0.1665134 | J10: =+D10+J9 -> 49613.389 | K10: =+E10+K9 -> 8500 | L10: =+K10/J10 -> 0.17132472 | M10: 3
A11: =+A10+1 -> 46273 | B11: 8 | C11: TUE | D11: 4713.2701 | E11: 500 | F11: =E11/D11 -> 0.10608346 | G11: =D11/250 -> 18.85308 | H11: 2 | I11: =H11/G11 -> 0.10608346 | J11: =+D11+J10 -> 54326.659 | K11: =+E11+K10 -> 9000 | L11: =+K11/J11 -> 0.16566452 | M11: 2
A12: =+A11+1 -> 46274 | B12: 9 | C12: WED | D12: 4730.4354 | E12: 250 | F12: =E12/D12 -> 0.052849258 | G12: =D12/250 -> 18.921741 | H12: 1 | I12: =H12/G12 -> 0.052849258 | J12: =+D12+J11 -> 59057.095 | K12: =+E12+K11 -> 9250 | L12: =+K12/J12 -> 0.15662809 | M12: 1
A13: =+A12+1 -> 46275 | B13: 10 | C13: THU | D13: 5265.6039 | E13: 1750 | F13: =E13/D13 -> 0.33234555 | G13: =D13/250 -> 21.062416 | H13: 4 | I13: =H13/G13 -> 0.18991174 | J13: =+D13+J12 -> 64322.699 | K13: =+E13+K12 -> 11000 | L13: =+K13/J13 -> 0.17101273 | M13: 7
A14: =+A13+1 -> 46276 | B14: 11 | C14: FRI | D14: 6387.6675 | E14: 1850 | F14: =E14/D14 -> 0.28962059 | G14: =D14/250 -> 25.55067 | H14: 7 | I14: =H14/G14 -> 0.27396542 | J14: =+D14+J13 -> 70710.366 | K14: =+E14+K13 -> 12850 | L14: =+K14/J14 -> 0.18172724 | M14: 8
A15: =+A14+1 -> 46277 | B15: 12 | C15: SAT | D15: 11555.449 | E15: 7500 | F15: =E15/D15 -> 0.64904444 | G15: =D15/250 -> 46.221796 | H15: 22 | I15: =H15/G15 -> 0.47596592 | J15: =+D15+J14 -> 82265.815 | K15: =+E15+K14 -> 20350 | L15: =+K15/J15 -> 0.24736885 | M15: 30
A16: =+A15+1 -> 46278 | B16: 13 | C16: SUN | D16: 11783.432 | E16: 5250 | F16: =E16/D16 -> 0.44554082 | G16: =D16/250 -> 47.133728 | H16: 17 | I16: =H16/G16 -> 0.36067591 | J16: =+D16+J15 -> 94049.247 | K16: =+E16+K15 -> 25600 | L16: =+K16/J16 -> 0.27219782 | M16: 21
A17: =+A16+1 -> 46279 | B17: 14 | C17: MON | D17: 5196.8316 | E17: 1000 | F17: =E17/D17 -> 0.19242494 | G17: =D17/250 -> 20.787326 | H17: 4 | I17: =H17/G17 -> 0.19242494 | J17: =+D17+J16 -> 99246.079 | K17: =+E17+K16 -> 26600 | L17: =+K17/J17 -> 0.26802066 | M17: 4
... A28: =+A27+1 -> 46290 | B28: 25 | C28: FRI | D28: 6239.3847 | E28: 750 | F28: =E28/D28 -> 0.12020416 | G28: =D28/250 -> 24.957539 | H28: 3 | I28: =H28/G28 -> 0.12020416 | J28: =+D28+J27 -> 169804.17 | K28: =+E28+K27 -> 47200 | L28: =+K28/J28 -> 0.27796727 | M28: 3
A29: =+A28+1 -> 46291 | B29: 26 | C29: SAT | D29: 11996.078 | F29: =E29/D29 -> 0 | G29: =D29/250 -> 47.984312 | I29: =H29/G29 -> 0 | J29: =+D29+J28 -> 181800.24 | K29: =+E29+K28 -> 47200 | L29: =+K29/J29 -> 0.25962562
A30: =+A29+1 -> 46292 | B30: 27 | C30: SUN | D30: 11530.929 | F30: =E30/D30 -> 0 | G30: =D30/250 -> 46.123716 | I30: =H30/G30 -> 0 | J30: =+D30+J29 -> 193331.17 | K30: =+E30+K29 -> 47200 | L30: =+K30/J30 -> 0.24414066
A31: =+A30+1 -> 46293 | B31: 28 | C31: MON | D31: 4504.142 | F31: =E31/D31 -> 0 | G31: =D31/250 -> 18.016568 | I31: =H31/G31 -> 0 | J31: =+D31+J30 -> 197835.31 | K31: =+E31+K30 -> 47200 | L31: =+K31/J31 -> 0.23858228
A32: =+A31+1 -> 46294 | B32: 29 | C32: TUE | D32: 4713.2701 | F32: =E32/D32 -> 0 | G32: =D32/250 -> 18.85308 | I32: =H32/G32 -> 0 | J32: =+D32+J31 -> 202548.58 | K32: =+E32+K31 -> 47200 | L32: =+K32/J32 -> 0.23303051
A33: =+A32+1 -> 46295 | B33: 30 | C33: WED | D33: 4802.5022 | F33: =E33/D33 -> 0 | G33: =D33/250 -> 19.210009 | I33: =H33/G33 -> 0 | J33: =+D33+J32 -> 207351.09 | K33: =+E33+K32 -> 47200 | L33: =+K33/J33 -> 0.22763324
A34: =+A33+1 -> 46296 | B34: 31 | C34: THU | F34: =E34/D34 -> #DIV/0! | G34: =D34/250 -> 0 | I34: =H34/G34 -> #DIV/0! | J34: =+D34+J33 -> 207351.09 | K34: =+E34+K33 -> 47200 | L34: =+K34/J34 -> 0.22763324
A35: Total | D35: =SUM(D4:D34) -> 207351.09 | E35: =SUM(E4:E34) -> 47200 | F35: =E35/D35 -> 0.22763324 | G35: =+SUM(G4:G34) -> 829.40435 | H35: =SUM(H4:H34) -> 154 | I35: =H35/G35 -> 0.18567542 | J35: =J34 -> 207351.09 | K35: =K34 -> 47200 | L35: =+K35/J35 -> 0.22763324 | M35: =SUM(M4:M34) -> 190
W36: =37/40 -> 0.925
A37: Last
A38: Week1
A39: Week2
A40: Week3
A41: Week4
A42: Week5
A43: Week6
V61: d

Sheet DSR
A1: DAILY NET SALES (Gross Of Vat; Net Of Discount) | S1: Hamleys India
E2: YTD | F2: =17179447+E54 -> 19583633 | J2: achieved till date | K2: =#REF!/#REF! -> #REF! | S2: Hamleys Store: | U2: Vegas | AW2: =8095+7733 -> 15828
S3: Store Area: | U3: 4500
D4: Daily Net Sales | K4: Month to Date Net Sales | Q4: Key Performance Indicators
E5: ACTUAL | F5: Discount Given | G5: Disc % | I5: ACTUAL | J5: ACTUAL | K5: MONTH | L5: MONTH | M5: MONTH | N5: ACTUAL | O5: ACTUAL | Q5: Units Sold | R5: Number of Transact | S5: Number of visitors | T5: Batteries Sold | U5: ATV Drivers Sold | V5: Loyalty | W5: Red Card | X5: Bubble Stick | AC5: Battery Attachment% | AD5: ATV Attachment% | AE5: Red Card% | AF5: Loyalty% | AG5: Bubble Stick% | AH5: ATV Drivers Value | AI5: ATV CONTRI % | AJ5: BAttery Value | AK5: BATTERY CONTRI % | AL5: Core Value | AN5: CORE CONTRI % | AO5: SELF VALUE | AQ5: SELF CONTRI % | AR5: HOTSPOT VALUE | AT5: HOTSPOT CONTRI % | AU5: MII Sale | AW5: MII Contri% | AX5: MULTI BILLS | AY5: MULTI BILLS CONTRI % | AZ5: TELECALLING TGT | BA5: TELECALLING CALLS | BB5: TELECALLING BILLS | BC5: TELECALLING SALE | BD5: TELECALLING CONRI% | BE5: Liquidation | BF5: Liquidation% | BG5: Tote Bag | BH5: Tote Bag%
A6: Week | B6: Weekdy | C6: Day | D6: TARGET | H6: LY | I6: vs | J6: vs | K6: to date | L6: to date | M6: to date | N6: vs | O6: vs | Y6: AUV | Z6: ATV | AA6: UPT | AB6: Conv%
I7: TARGET | J7: LY | K7: TARGET | L7: ACTUAL | M7: LY | N7: TARGET | O7: LY
AL8: Qty | AM8: Sale | AO8: Qty | AP8: Sale | AR8: Qty | AS8: Sale | AU8: Qty | AV8: Sale
A9: WEEK 1 | B9: Sat | C9: 46263 | G9: =IF(ISERROR(F9/E9),"",F9/E9) | I9: =IF(ISERROR(E9/D9),"",E9/D9) | J9: =IF(ISERROR(E9/H9),"",(E9/H9))-1 -> #VALUE! | K9: =IF(ISERROR(K8+D9),0,K8+D9) -> 0 | L9: =IF(ISERROR(L8+E9),0,L8+E9) -> 0 | M9: =IF(ISERROR(M8+H9),0,M8+H9) -> 0 | N9: =IF(ISERROR(L9/K9),"",L9/K9) | O9: =IF(ISERROR(L9/M9),"",L9/M9)-100% -> #VALUE! | Y9: =IF(ISERROR(E9/Q9),"",E9/Q9) | Z9: =IF(ISERROR(E9/R9),"",E9/R9) | AA9: =IF(ISERROR(Q9/R9),"",Q9/R9) | AB9: =IF(ISERROR(R9/S9),"",R9/S9) | AC9: =IF(ISERROR(T9/R9),"",T9/R9) | AD9: =IF(ISERROR(U9/R9),"",U9/R9) | AE9: =IF(ISERROR(W9/R9),"",W9/R9) | AF9: =+V9/R9 -> #DIV/0! | AG9: =+X9/R9 -> #DIV/0! | AI9: =AH9/E9 -> #DIV/0! | AK9: =+AJ9/E9 -> #DIV/0! | AN9: =AM9/E9 -> #DIV/0! | AQ9: =AP9/E9 -> #DIV/0! | AT9: =AS9/E9 -> #DIV/0! | AW9: =AV9/E9 -> #DIV/0! | AY9: =AX9/R9 -> #DIV/0! | BD9: =+BC9/E9 -> #DIV/0! | BF9: =BE9/R9 -> #DIV/0! | BH9: =BG9/R9 -> #DIV/0!
B10: Sun | C10: =C9+1 -> 46264 | G10: =IF(ISERROR(F10/E10),"",F10/E10) | I10: =IF(ISERROR(E10/D10),"",E10/D10) | J10: =IF(ISERROR(E10/H10),"",(E10/H10))-1 -> #VALUE! | K10: =IF(ISERROR(K9+D10),0,K9+D10) -> 0 | L10: =IF(ISERROR(L9+E10),0,L9+E10) -> 0 | M10: =IF(ISERROR(M9+H10),0,M9+H10) -> 0 | N10: =IF(ISERROR(L10/K10),"",L10/K10) | O10: =IF(ISERROR(L10/M10),"",L10/M10)-100% -> #VALUE! | Y10: =IF(ISERROR(E10/Q10),"",E10/Q10) | Z10: =IF(ISERROR(E10/R10),"",E10/R10) | AA10: =IF(ISERROR(Q10/R10),"",Q10/R10) | AB10: =IF(ISERROR(R10/S10),"",R10/S10) | AC10: =IF(ISERROR(T10/R10),"",T10/R10) | AD10: =IF(ISERROR(U10/R10),"",U10/R10) | AE10: =IF(ISERROR(W10/R10),"",W10/R10) | AF10: =+V10/R10 -> #DIV/0! | AG10: =+X10/R10 -> #DIV/0! | AI10: =AH10/E10 -> #DIV/0! | AK10: =+AJ10/E10 -> #DIV/0! | AN10: =AM10/E10 -> #DIV/0! | AQ10: =AP10/E10 -> #DIV/0! | AT10: =AS10/E10 -> #DIV/0! | AW10: =AV10/E10 -> #DIV/0! | AY10: =AX10/R10 -> #DIV/0! | BD10: =+BC10/E10 -> #DIV/0! | BF10: =BE10/R10 -> #DIV/0! | BH10: =BG10/R10 -> #DIV/0!
B11: Total | D11: =SUM(D9:D10) -> 0 | E11: =SUM(E9:E10) -> 0 | F11: =SUM(F9:F10) -> 0 | G11: =IF(ISERROR(F11/E11),"",F11/E11) | H11: =SUM(H9:H10) -> 0 | I11: =IF(ISERROR(E11/D11),"",E11/D11) | J11: =IF(ISERROR(E11/H11),"",(E11/H11))-1 -> #VALUE! | Q11: =SUM(Q9:Q10) -> 0 | R11: =SUM(R9:R10) -> 0 | S11: =SUM(S9:S10) -> 0 | T11: =SUM(T9:T10) -> 0 | U11: =SUM(U9:U10) -> 0 | V11: =SUM(V9:V10) -> 0 | W11: =SUM(W9:W10) -> 0 | X11: =SUM(X9:X10) -> 0 | Y11: =IF(ISERROR(E11/Q11),"",E11/Q11) | Z11: =IF(ISERROR(E11/R11),"",E11/R11) | AA11: =IF(ISERROR(Q11/R11),"",Q11/R11) | AB11: =IF(ISERROR(R11/S11),"",R11/S11) | AC11: =IF(ISERROR(T11/R11),"",T11/R11) | AD11: =IF(ISERROR(U11/R11),"",U11/R11) | AE11: =IF(ISERROR(W11/R11),"",W11/R11) | AF11: =+V11/R11 -> #DIV/0! | AG11: =+X11/R11 -> #DIV/0! | AH11: =SUM(AH9:AH10) -> 0 | AI11: =AH11/E11 -> #DIV/0! | AJ11: =SUM(AJ9:AJ10) -> 0 | AK11: =+AJ11/E11 -> #DIV/0! | AL11: =SUM(AL9:AL10) -> 0 | AM11: =SUM(AM9:AM10) -> 0 | AN11: =AM11/E11 -> #DIV/0! | AO11: =+SUM(AO9:AO10) -> 0 | AP11: =+SUM(AP9:AP10) -> 0 | AQ11: =AP11/E11 -> #DIV/0! | AR11: =+SUM(AR9:AR10) -> 0 | AS11: =+SUM(AS9:AS10) -> 0 | AT11: =AS11/E11 -> #DIV/0! | AU11: =+SUM(AU9:AU10) -> 0 | AV11: =+SUM(AV9:AV10) -> 0 | AW11: =AV11/E11 -> #DIV/0! | AX11: =SUM(AX9:AX10) -> 0 | AY11: =AX11/R11 -> #DIV/0! | AZ11: =SUM(AZ9:AZ10) -> 0 | BA11: =SUM(BA9:BA10) -> 0 | BB11: =SUM(BB9:BB10) -> 0 | BC11: =SUM(BC9:BC10) -> 0 | BD11: =+BC11/E11 -> #DIV/0! | BE11: =SUM(BE9:BE10) -> 0 | BF11: =BE11/R11 -> #DIV/0! | BG11: =SUM(BG9:BG10) -> 0 | BH11: =BG11/R11 -> #DIV/0!
A12: WEEK 1 | B12: Mon | C12: =C10+1 -> 46265 | G12: =IF(ISERROR(F12/E12),"",F12/E12) | I12: =IF(ISERROR(E12/D12),"",E12/D12) | J12: =IF(ISERROR(E12/H12),"",(E12/H12))-1 -> #VALUE! | K12: =IF(ISERROR(K10+D12),0,K10+D12) -> 0 | L12: =IF(ISERROR(L10+E12),0,L10+E12) -> 0 | M12: =IF(ISERROR(M10+H12),0,M10+H12) -> 0 | N12: =IF(ISERROR(L12/K12),"",L12/K12) | O12: =IF(ISERROR(L12/M12),"",L12/M12)-100% -> #VALUE! | Y12: =IF(ISERROR(E12/Q12),"",E12/Q12) | Z12: =IF(ISERROR(E12/R12),"",E12/R12) | AA12: =IF(ISERROR(Q12/R12),"",Q12/R12) | AB12: =IF(ISERROR(R12/S12),"",R12/S12) | AC12: =IF(ISERROR(T12/R12),"",T12/R12) | AD12: =IF(ISERROR(U12/R12),"",U12/R12) | AE12: =IF(ISERROR(W12/R12),"",W12/R12) | AF12: =+V12/R12 -> #DIV/0! | AG12: =+X12/R12 -> #DIV/0! | AI12: =AH12/E12 -> #DIV/0! | AK12: =+AJ12/E12 -> #DIV/0! | AN12: =AM12/E12 -> #DIV/0! | AQ12: =AP12/E12 -> #DIV/0! | AT12: =AS12/E12 -> #DIV/0! | AW12: =AV12/E12 -> #DIV/0! | AY12: =AX12/R12 -> #DIV/0! | BD12: =+BC12/E12 -> #DIV/0! | BF12: =BE12/R12 -> #DIV/0! | BH12: =BG12/R12 -> #DIV/0!
B13: Tues | C13: =C12+1 -> 46266 | D13: 73656.886 | E13: 64929 | G13: =IF(ISERROR(F13/E13),"",F13/E13) -> 0 | H13: 65771 | I13: =IF(ISERROR(E13/D13),"",E13/D13) -> 0.88150618 | J13: =IF(ISERROR(E13/H13),"",(E13/H13))-1 -> -0.012801995 | K13: =IF(ISERROR(K12+D13),0,K12+D13) -> 73656.886 | L13: =IF(ISERROR(L12+E13),0,L12+E13) -> 64929 | M13: =IF(ISERROR(M12+H13),0,M12+H13) -> 65771 | N13: =IF(ISERROR(L13/K13),"",L13/K13) -> 0.88150618 | O13: =IF(ISERROR(L13/M13),"",L13/M13)-100% -> -0.012801995 | Q13: 54 | R13: 27 | S13: 186 | T13: 4 | U13: 0 | V13: 4 | W13: 0 | X13: 0 | Y13: =IF(ISERROR(E13/Q13),"",E13/Q13) -> 1202.3889 | Z13: =IF(ISERROR(E13/R13),"",E13/R13) -> 2404.7778 | AA13: =IF(ISERROR(Q13/R13),"",Q13/R13) -> 2 | AB13: =IF(ISERROR(R13/S13),"",R13/S13) -> 0.14516129 | AC13: =IF(ISERROR(T13/R13),"",T13/R13) -> 0.14814815 | AD13: =IF(ISERROR(U13/R13),"",U13/R13) -> 0 | AE13: =IF(ISERROR(W13/R13),"",W13/R13) -> 0 | AF13: =+V13/R13 -> 0.14814815 | AG13: =+X13/R13 -> 0 | AH13: 0 | AI13: =AH13/E13 -> 0 | AJ13: 440 | AK13: =+AJ13/E13 -> 0.0067766329 | AL13: 0 | AM13: 0 | AN13: =AM13/E13 -> 0 | AO13: 3 | AP13: 3573 | AQ13: =AP13/E13 -> 0.05502934 | AR13: 1 | AS13: 1699 | AT13: =AS13/E13 -> 0.026167044 | AU13: 4 | AV13: 7172 | AW13: =AV13/E13 -> 0.11045912 | AX13: 13 | AY13: =AX13/R13 -> 0.48148148 | AZ13: 100 | BA13: 80 | BB13: 0 | BC13: 0 | BD13: =+BC13/E13 -> 0 | BE13: 0 | BF13: =BE13/R13 -> 0 | BG13: 0 | BH13: =BG13/R13 -> 0
B14: Wed | C14: =C13+1 -> 46267 | D14: 76859.359 | E14: 119760 | G14: =IF(ISERROR(F14/E14),"",F14/E14) -> 0 | H14: 66849 | I14: =IF(ISERROR(E14/D14),"",E14/D14) -> 1.5581707 | J14: =IF(ISERROR(E14/H14),"",(E14/H14))-1 -> 0.79150025 | K14: =IF(ISERROR(K13+D14),0,K13+D14) -> 150516.25 | L14: =IF(ISERROR(L13+E14),0,L13+E14) -> 184689 | M14: =IF(ISERROR(M13+H14),0,M13+H14) -> 132620 | N14: =IF(ISERROR(L14/K14),"",L14/K14) -> 1.227037 | O14: =IF(ISERROR(L14/M14),"",L14/M14)-100% -> 0.39261801 | Q14: 58 | R14: 29 | S14: 206 | T14: 7 | U14: 0 | V14: 1 | W14: 0 | X14: 0 | Y14: =IF(ISERROR(E14/Q14),"",E14/Q14) -> 2064.8276 | Z14: =IF(ISERROR(E14/R14),"",E14/R14) -> 4129.6552 | AA14: =IF(ISERROR(Q14/R14),"",Q14/R14) -> 2 | AB14: =IF(ISERROR(R14/S14),"",R14/S14) -> 0.1407767 | AC14: =IF(ISERROR(T14/R14),"",T14/R14) -> 0.24137931 | AD14: =IF(ISERROR(U14/R14),"",U14/R14) -> 0 | AE14: =IF(ISERROR(W14/R14),"",W14/R14) -> 0 | AF14: =+V14/R14 -> 0.034482759 | AG14: =+X14/R14 -> 0 | AH14: 2499 | AI14: =AH14/E14 -> 0.020866733 | AJ14: 760 | AK14: =+AJ14/E14 -> 0.0063460254 | AL14: 1 | AM14: 32997 | AN14: =AM14/E14 -> 0.27552605 | AO14: 0 | AP14: 0 | AQ14: =AP14/E14 -> 0 | AR14: 1 | AS14: 32997 | AT14: =AS14/E14 -> 0.27552605 | AU14: 4 | AV14: 7071 | AW14: =AV14/E14 -> 0.059043086 | AX14: 15 | AY14: =AX14/R14 -> 0.51724138 | AZ14: 100 | BA14: 100 | BB14: 0 | BC14: 0 | BD14: =+BC14/E14 -> 0 | BE14: 0 | BF14: =BE14/R14 -> 0 | BG14: 0 | BH14: =BG14/R14 -> 0
B15: Thurs | C15: =C14+1 -> 46268 | D15: 89669.252 | E15: 70583 | G15: =IF(ISERROR(F15/E15),"",F15/E15) -> 0 | H15: 69939 | I15: =IF(ISERROR(E15/D15),"",E15/D15) -> 0.7871483 | J15: =IF(ISERROR(E15/H15),"",(E15/H15))-1 -> 0.0092080241 | K15: =IF(ISERROR(K14+D15),0,K14+D15) -> 240185.5 | L15: =IF(ISERROR(L14+E15),0,L14+E15) -> 255272 | M15: =IF(ISERROR(M14+H15),0,M14+H15) -> 202559 | N15: =IF(ISERROR(L15/K15),"",L15/K15) -> 1.0628119 | O15: =IF(ISERROR(L15/M15),"",L15/M15)-100% -> 0.26023529 | Q15: 75 | R15: 37 | S15: 231 | T15: 6 | U15: 0 | V15: 4 | W15: 0 | X15: 0 | Y15: =IF(ISERROR(E15/Q15),"",E15/Q15) -> 941.10667 | Z15: =IF(ISERROR(E15/R15),"",E15/R15) -> 1907.6486 | AA15: =IF(ISERROR(Q15/R15),"",Q15/R15) -> 2.027027 | AB15: =IF(ISERROR(R15/S15),"",R15/S15) -> 0.16017316 | AC15: =IF(ISERROR(T15/R15),"",T15/R15) -> 0.16216216 | AD15: =IF(ISERROR(U15/R15),"",U15/R15) -> 0 | AE15: =IF(ISERROR(W15/R15),"",W15/R15) -> 0 | AF15: =+V15/R15 -> 0.10810811 | AG15: =+X15/R15 -> 0 | AH15: 0 | AI15: =AH15/E15 -> 0 | AJ15: 630 | AK15: =+AJ15/E15 -> 0.008925662 | AL15: 0 | AM15: 0 | AN15: =AM15/E15 -> 0 | AO15: 1 | AP15: 1299 | AQ15: =AP15/E15 -> 0.018403865 | AR15: 0 | AS15: 0 | AT15: =AS15/E15 -> 0 | AU15: 2 | AV15: 648 | AW15: =AV15/E15 -> 0.0091806809 | AX15: 20 | AY15: =AX15/R15 -> 0.54054054 | AZ15: 100 | BA15: 110 | BB15: 1 | BC15: 7794 | BD15: =+BC15/E15 -> 0.11042319 | BE15: 0 | BF15: =BE15/R15 -> 0 | BG15: 0 | BH15: =BG15/R15 -> 0
B16: Fri | C16: =C15+1 -> 46269 | D16: 128098.93 | E16: 51966 | G16: =IF(ISERROR(F16/E16),"",F16/E16) -> 0 | H16: 81017 | I16: =IF(ISERROR(E16/D16),"",E16/D16) -> 0.40567083 | J16: =IF(ISERROR(E16/H16),"",(E16/H16))-1 -> -0.35857906 | K16: =IF(ISERROR(K15+D16),0,K15+D16) -> 368284.43 | L16: =IF(ISERROR(L15+E16),0,L15+E16) -> 307238 | M16: =IF(ISERROR(M15+H16),0,M15+H16) -> 283576 | N16: =IF(ISERROR(L16/K16),"",L16/K16) -> 0.83424108 | O16: =IF(ISERROR(L16/M16),"",L16/M16)-100% -> 0.083441476 | Q16: 75 | R16: 34 | S16: 233 | T16: 3 | U16: 1 | V16: 3 | W16: 0 | X16: 1 | Y16: =IF(ISERROR(E16/Q16),"",E16/Q16) -> 692.88 | Z16: =IF(ISERROR(E16/R16),"",E16/R16) -> 1528.4118 | AA16: =IF(ISERROR(Q16/R16),"",Q16/R16) -> 2.2058824 | AB16: =IF(ISERROR(R16/S16),"",R16/S16) -> 0.14592275 | AC16: =IF(ISERROR(T16/R16),"",T16/R16) -> 0.088235294 | AD16: =IF(ISERROR(U16/R16),"",U16/R16) -> 0.029411765 | AE16: =IF(ISERROR(W16/R16),"",W16/R16) -> 0 | AF16: =+V16/R16 -> 0.088235294 | AG16: =+X16/R16 -> 0.029411765 | AH16: 1499 | AI16: =AH16/E16 -> 0.028845784 | AJ16: 320 | AK16: =+AJ16/E16 -> 0.0061578725 | AL16: 1 | AM16: 954 | AN16: =AM16/E16 -> 0.018358157 | AO16: 4 | AP16: 5546 | AQ16: =AP16/E16 -> 0.10672363 | AR16: 2 | AS16: 2748 | AT16: =AS16/E16 -> 0.05288073 | AU16: 9 | AV16: 12702 | AW16: =AV16/E16 -> 0.24442905 | AX16: 17 | AY16: =AX16/R16 -> 0.5 | AZ16: 100 | BA16: 50 | BB16: 0 | BC16: 0 | BD16: =+BC16/E16 -> 0 | BE16: 0 | BF16: =BE16/R16 -> 0 | BG16: 0 | BH16: =BG16/R16 -> 0
B17: Sat | C17: =C16+1 -> 46270 | D17: 166528.61 | E17: 153776 | G17: =IF(ISERROR(F17/E17),"",F17/E17) -> 0 | H17: 190445 | I17: =IF(ISERROR(E17/D17),"",E17/D17) -> 0.9234209 | J17: =IF(ISERROR(E17/H17),"",(E17/H17))-1 -> -0.19254378 | K17: =IF(ISERROR(K16+D17),0,K16+D17) -> 534813.04 | L17: =IF(ISERROR(L16+E17),0,L16+E17) -> 461014 | M17: =IF(ISERROR(M16+H17),0,M16+H17) -> 474021 | N17: =IF(ISERROR(L17/K17),"",L17/K17) -> 0.86200964 | O17: =IF(ISERROR(L17/M17),"",L17/M17)-100% -> -0.027439713 | Q17: 178 | R17: 66 | S17: 437 | T17: 3 | U17: 1 | V17: 9 | W17: 0 | X17: 0 | Y17: =IF(ISERROR(E17/Q17),"",E17/Q17) -> 863.91011 | Z17: =IF(ISERROR(E17/R17),"",E17/R17) -> 2329.9394 | AA17: =IF(ISERROR(Q17/R17),"",Q17/R17) -> 2.6969697 | AB17: =IF(ISERROR(R17/S17),"",R17/S17) -> 0.15102975 | AC17: =IF(ISERROR(T17/R17),"",T17/R17) -> 0.045454545 | AD17: =IF(ISERROR(U17/R17),"",U17/R17) -> 0.015151515 | AE17: =IF(ISERROR(W17/R17),"",W17/R17) -> 0 | AF17: =+V17/R17 -> 0.13636364 | AG17: =+X17/R17 -> 0 | AH17: 1199 | AI17: =AH17/E17 -> 0.0077970555 | AJ17: 288 | AK17: =+AJ17/E17 -> 0.001872854 | AL17: 1 | AM17: 799 | AN17: =AM17/E17 -> 0.0051958693 | AO17: 2 | AP17: 949 | AQ17: =AP17/E17 -> 0.0061713141 | AR17: 0 | AS17: 0 | AT17: =AS17/E17 -> 0 | AU17: 9 | AV17: 6043 | AW17: =AV17/E17 -> 0.03929742 | AX17: 31 | AY17: =AX17/R17 -> 0.46969697 | AZ17: 100 | BA17: 100 | BB17: 0 | BC17: 0 | BD17: =+BC17/E17 -> 0 | BE17: 0 | BF17: =BE17/R17 -> 0 | BG17: 0 | BH17: =BG17/R17 -> 0
B18: Sun | C18: =C17+1 -> 46271 | G18: =IF(ISERROR(F18/E18),"",F18/E18) | H18: 130963 | I18: =IF(ISERROR(E18/D18),"",E18/D18) | J18: =IF(ISERROR(E18/H18),"",(E18/H18))-1 -> -1 | K18: =IF(ISERROR(K17+D18),0,K17+D18) -> 534813.04 | L18: =IF(ISERROR(L17+E18),0,L17+E18) -> 461014 | M18: =IF(ISERROR(M17+H18),0,M17+H18) -> 604984 | N18: =IF(ISERROR(L18/K18),"",L18/K18) -> 0.86200964 | O18: =IF(ISERROR(L18/M18),"",L18/M18)-100% -> -0.23797324 | Y18: =IF(ISERROR(E18/Q18),"",E18/Q18) | Z18: =IF(ISERROR(E18/R18),"",E18/R18) | AA18: =IF(ISERROR(Q18/R18),"",Q18/R18) | AB18: =IF(ISERROR(R18/S18),"",R18/S18) | AC18: =IF(ISERROR(T18/R18),"",T18/R18) | AD18: =IF(ISERROR(U18/R18),"",U18/R18) | AE18: =IF(ISERROR(W18/R18),"",W18/R18) | AF18: =+V18/R18 -> #DIV/0! | AG18: =+X18/R18 -> #DIV/0! | AI18: =AH18/E18 -> #DIV/0! | AK18: =+AJ18/E18 -> #DIV/0! | AN18: =AM18/E18 -> #DIV/0! | AQ18: =AP18/E18 -> #DIV/0! | AT18: =AS18/E18 -> #DIV/0! | AW18: =AV18/E18 -> #DIV/0! | AY18: =AX18/R18 -> #DIV/0! | BD18: =+BC18/E18 -> #DIV/0! | BF18: =BE18/R18 -> #DIV/0! | BG18: 0 | BH18: =BG18/R18 -> #DIV/0!
B19: Total | D19: =SUM(D12:D18) -> 534813.04 | E19: =SUM(E12:E18) -> 461014 | F19: =SUM(F12:F18) -> 0 | G19: =IF(ISERROR(F19/E19),"",F19/E19) -> 0 | H19: =SUM(H12:H18) -> 604984 | I19: =IF(ISERROR(E19/D19),"",E19/D19) -> 0.86200964 | J19: =IF(ISERROR(E19/H19),"",(E19/H19))-1 -> -0.23797324 | Q19: =SUM(Q12:Q18) -> 440 | R19: =SUM(R12:R18) -> 193 | S19: =SUM(S12:S18) -> 1293 | T19: =SUM(T12:T18) -> 23 | U19: =SUM(U12:U18) -> 2 | V19: =SUM(V12:V18) -> 21 | W19: =SUM(W12:W18) -> 0 | X19: =SUM(X12:X18) -> 1 | Y19: =IF(ISERROR(E19/Q19),"",E19/Q19) -> 1047.7591 | Z19: =IF(ISERROR(E19/R19),"",E19/R19) -> 2388.6736 | AA19: =IF(ISERROR(Q19/R19),"",Q19/R19) -> 2.2797927 | AB19: =IF(ISERROR(R19/S19),"",R19/S19) -> 0.14926527 | AC19: =IF(ISERROR(T19/R19),"",T19/R19) -> 0.11917098 | AD19: =IF(ISERROR(U19/R19),"",U19/R19) -> 0.010362694 | AE19: =IF(ISERROR(W19/R19),"",W19/R19) -> 0 | AF19: =+V19/R19 -> 0.10880829 | AG19: =+X19/R19 -> 0.0051813472 | AH19: =SUM(AH12:AH18) -> 5197 | AI19: =AH19/E19 -> 0.011272977 | AJ19: =SUM(AJ12:AJ18) -> 2438 | AK19: =+AJ19/E19 -> 0.0052883427 | AL19: =SUM(AL12:AL18) -> 3 | AM19: =SUM(AM12:AM18) -> 34750 | AN19: =AM19/E19 -> 0.07537732 | AO19: =+SUM(AO12:AO18) -> 10 | AP19: =+SUM(AP12:AP18) -> 11367 | AQ19: =AP19/E19 -> 0.024656518 | AR19: =+SUM(AR12:AR18) -> 4 | AS19: =+SUM(AS12:AS18) -> 37444 | AT19: =AS19/E19 -> 0.081220961 | AU19: =+SUM(AU12:AU18) -> 28 | AV19: =+SUM(AV12:AV18) -> 33636 | AW19: =AV19/E19 -> 0.072960908 | AX19: =SUM(AX12:AX18) -> 96 | AY19: =AX19/R19 -> 0.49740933 | AZ19: =SUM(AZ12:AZ18) -> 500 | BA19: =SUM(BA12:BA18) -> 440 | BB19: =SUM(BB12:BB18) -> 1 | BC19: =SUM(BC12:BC18) -> 7794 | BD19: =+BC19/E19 -> 0.016906211 | BE19: =SUM(BE12:BE18) -> 0 | BF19: =BE19/R19 -> 0 | BG19: =SUM(BG12:BG18) -> 0 | BH19: =BG19/R19 -> 0
A20: WEEK 2 | B20: Mon | C20: =C18+1 -> 46272 | D20: 73656.886 | E20: 38921 | G20: =IF(ISERROR(F20/E20),"",F20/E20) -> 0 | H20: 166519 | I20: =IF(ISERROR(E20/D20),"",E20/D20) -> 0.52840952 | J20: =IF(ISERROR(E20/H20),"",(E20/H20))-1 -> -0.76626691 | K20: =IF(ISERROR(K18+D20),0,K18+D20) -> 608469.93 | L20: =IF(ISERROR(L18+E20),0,L18+E20) -> 499935 | M20: =IF(ISERROR(M18+H20),0,M18+H20) -> 771503 | N20: =IF(ISERROR(L20/K20),"",L20/K20) -> 0.82162647 | O20: =IF(ISERROR(L20/M20),"",L20/M20)-100% -> -0.35199863 | Q20: 35 | R20: 24 | S20: 140 | T20: 2 | U20: 0 | V20: 3 | W20: 0 | X20: 0 | Y20: =IF(ISERROR(E20/Q20),"",E20/Q20) -> 1112.0286 | Z20: =IF(ISERROR(E20/R20),"",E20/R20) -> 1621.7083 | AA20: =IF(ISERROR(Q20/R20),"",Q20/R20) -> 1.4583333 | AB20: =IF(ISERROR(R20/S20),"",R20/S20) -> 0.17142857 | AC20: =IF(ISERROR(T20/R20),"",T20/R20) -> 0.083333333 | AD20: =IF(ISERROR(U20/R20),"",U20/R20) -> 0 | AE20: =IF(ISERROR(V20/S20),"",V20/S20) -> 0.021428571 | AF20: =+V20/R20 -> 0.125 | AG20: =+X20/R20 -> 0 | AH20: 0 | AI20: =AH20/E20 -> 0 | AJ20: 300 | AK20: =+AJ20/E20 -> 0.0077079212 | AL20: 0 | AM20: 0 | AN20: =AM20/E20 -> 0 | AO20: 1 | AP20: 479 | AQ20: =AP20/E20 -> 0.012306981 | AR20: 0 | AS20: 0 | AT20: =AS20/E20 -> 0 | AU20: 3 | AV20: 1318 | AW20: =AV20/E20 -> 0.033863467 | AX20: 9 | AY20: =AX20/R20 -> 0.375 | AZ20: 100 | BA20: 50 | BB20: 0 | BC20: 0 | BD20: =+BC20/E20 -> 0 | BE20: 0 | BF20: =BE20/R20 -> 0 | BG20: 0 | BH20: =BG20/R20 -> 0
B21: Tues | C21: =C20+1 -> 46273 | D21: 76859.359 | E21: 46337 | G21: =IF(ISERROR(F21/E21),"",F21/E21) -> 0 | H21: 47302 | I21: =IF(ISERROR(E21/D21),"",E21/D21) -> 0.60288038 | J21: =IF(ISERROR(E21/H21),"",(E21/H21))-1 -> -0.020400829 | K21: =IF(ISERROR(K20+D21),0,K20+D21) -> 685329.29 | L21: =IF(ISERROR(L20+E21),0,L20+E21) -> 546272 | M21: =IF(ISERROR(M20+H21),0,M20+H21) -> 818805 | N21: =IF(ISERROR(L21/K21),"",L21/K21) -> 0.7970942 | O21: =IF(ISERROR(L21/M21),"",L21/M21)-100% -> -0.33284237 | Q21: 36 | R21: 22 | S21: 142 | T21: 0 | U21: 1 | V21: 1 | W21: 0 | X21: 0 | Y21: =IF(ISERROR(E21/Q21),"",E21/Q21) -> 1287.1389 | Z21: =IF(ISERROR(E21/R21),"",E21/R21) -> 2106.2273 | AA21: =IF(ISERROR(Q21/R21),"",Q21/R21) -> 1.6363636 | AB21: =IF(ISERROR(R21/S21),"",R21/S21) -> 0.15492958 | AC21: =IF(ISERROR(T21/R21),"",T21/R21) -> 0 | AD21: =IF(ISERROR(U21/R21),"",U21/R21) -> 0.045454545 | AE21: =IF(ISERROR(V21/S21),"",V21/S21) -> 0.0070422535 | AF21: =+V21/R21 -> 0.045454545 | AG21: =+X21/R21 -> 0 | AH21: 2563 | AI21: =AH21/E21 -> 0.05531217 | AJ21: 0 | AK21: =+AJ21/E21 -> 0 | AL21: 3 | AM21: =9999+3362 -> 13361 | AN21: =AM21/E21 -> 0.28834409 | AO21: 0 | AP21: 0 | AQ21: =AP21/E21 -> 0 | AR21: 0 | AS21: 0 | AT21: =AS21/E21 -> 0 | AU21: 3 | AV21: 2361 | AW21: =AV21/E21 -> 0.050952802 | AX21: 12 | AY21: =AX21/R21 -> 0.54545455 | AZ21: 100 | BA21: 100 | BB21: 0 | BC21: 0 | BD21: =+BC21/E21 -> 0 | BE21: 0 | BF21: =BE21/R21 -> 0 | BG21: 0 | BH21: =BG21/R21 -> 0
B22: Wed | C22: =C21+1 -> 46274 | D22: 76859.359 | E22: 86046 | G22: =IF(ISERROR(F22/E22),"",F22/E22) -> 0 | H22: 47469 | I22: =IF(ISERROR(E22/D22),"",E22/D22) -> 1.1195253 | J22: =IF(ISERROR(E22/H22),"",(E22/H22))-1 -> 0.81267775 | K22: =IF(ISERROR(K21+D22),0,K21+D22) -> 762188.65 | L22: =IF(ISERROR(L21+E22),0,L21+E22) -> 632318 | M22: =IF(ISERROR(M21+H22),0,M21+H22) -> 866274 | N22: =IF(ISERROR(L22/K22),"",L22/K22) -> 0.82960826 | O22: =IF(ISERROR(L22/M22),"",L22/M22)-100% -> -0.27007159 | Q22: 57 | R22: 29 | S22: 192 | T22: 1 | U22: 1 | V22: 3 | W22: 0 | X22: 0 | Y22: =IF(ISERROR(E22/Q22),"",E22/Q22) -> 1509.5789 | Z22: =IF(ISERROR(E22/R22),"",E22/R22) -> 2967.1034 | AA22: =IF(ISERROR(Q22/R22),"",Q22/R22) -> 1.9655172 | AB22: =IF(ISERROR(R22/S22),"",R22/S22) -> 0.15104167 | AC22: =IF(ISERROR(T22/R22),"",T22/R22) -> 0.034482759 | AD22: =IF(ISERROR(U22/R22),"",U22/R22) -> 0.034482759 | AE22: =IF(ISERROR(V22/S22),"",V22/S22) -> 0.015625 | AF22: =+V22/R22 -> 0.10344828 | AG22: =+X22/R22 -> 0 | AH22: 1499 | AI22: =AH22/E22 -> 0.017420914 | AJ22: 100 | AK22: =+AJ22/E22 -> 0.0011621691 | AL22: 2 | AM22: 21198 | AN22: =AM22/E22 -> 0.2463566 | AO22: 1 | AP22: 1799 | AQ22: =AP22/E22 -> 0.020907422 | AR22: 1 | AS22: 1799 | AT22: =AS22/E22 -> 0.020907422 | AU22: 13 | AV22: 15779 | AW22: =AV22/E22 -> 0.18337866 | AX22: 12 | AY22: =AX22/R22 -> 0.4137931 | AZ22: 100 | BA22: 100 | BB22: 1 | BC22: 32360 | BD22: =+BC22/E22 -> 0.37607791 | BE22: 0 | BF22: =BE22/R22 -> 0 | BG22: 0 | BH22: =BG22/R22 -> 0
B23: Thurs | C23: =C22+1 -> 46275 | D23: 86466.779 | E23: 47076 | G23: =IF(ISERROR(F23/E23),"",F23/E23) -> 0 | H23: 55947 | I23: =IF(ISERROR(E23/D23),"",E23/D23) -> 0.54444031 | J23: =IF(ISERROR(E23/H23),"",(E23/H23))-1 -> -0.15856078 | K23: =IF(ISERROR(K22+D23),0,K22+D23) -> 848655.43 | L23: =IF(ISERROR(L22+E23),0,L22+E23) -> 679394 | M23: =IF(ISERROR(M22+H23),0,M22+H23) -> 922221 | N23: =IF(ISERROR(L23/K23),"",L23/K23) -> 0.80055342 | O23: =IF(ISERROR(L23/M23),"",L23/M23)-100% -> -0.26330673 | Q23: 56 | R23: 37 | S23: 210 | T23: 0 | U23: 0 | V23: 2 | W23: 0 | X23: 0 | Y23: =IF(ISERROR(E23/Q23),"",E23/Q23) -> 840.64286 | Z23: =IF(ISERROR(E23/R23),"",E23/R23) -> 1272.3243 | AA23: =IF(ISERROR(Q23/R23),"",Q23/R23) -> 1.5135135 | AB23: =IF(ISERROR(R23/S23),"",R23/S23) -> 0.17619048 | AC23: =IF(ISERROR(T23/R23),"",T23/R23) -> 0 | AD23: =IF(ISERROR(U23/R23),"",U23/R23) -> 0 | AE23: =IF(ISERROR(V23/S23),"",V23/S23) -> 0.0095238095 | AF23: =+V23/R23 -> 0.054054054 | AG23: =+X23/R23 -> 0 | AH23: 0 | AI23: =AH23/E23 -> 0 | AJ23: 0 | AK23: =+AJ23/E23 -> 0 | AL23: 0 | AM23: 0 | AN23: =AM23/E23 -> 0 | AO23: 1 | AP23: 1799 | AQ23: =AP23/E23 -> 0.038214802 | AR23: 1 | AS23: 1799 | AT23: =AS23/E23 -> 0.038214802 | AU23: 3 | AV23: 458 | AW23: =AV23/E23 -> 0.0097289489 | AX23: 20 | AY23: =AX23/R23 -> 0.54054054 | AZ23: 100 | BA23: 50 | BB23: 0 | BC23: 0 | BD23: =+BC23/E23 -> 0 | BE23: 2 | BF23: =BE23/R23 -> 0.054054054 | BG23: 0 | BH23: =BG23/R23 -> 0
B24: Fri | C24: =C23+1 -> 46276 | D24: 96074.199 | E24: 109677 | G24: =IF(ISERROR(F24/E24),"",F24/E24) -> 0 | H24: 74095 | I24: =IF(ISERROR(E24/D24),"",E24/D24) -> 1.1415864 | J24: =IF(ISERROR(E24/H24),"",(E24/H24))-1 -> 0.48022134 | K24: =IF(ISERROR(K23+D24),0,K23+D24) -> 944729.62 | L24: =IF(ISERROR(L23+E24),0,L23+E24) -> 789071 | M24: =IF(ISERROR(M23+H24),0,M23+H24) -> 996316 | N24: =IF(ISERROR(L24/K24),"",L24/K24) -> 0.83523474 | O24: =IF(ISERROR(L24/M24),"",L24/M24)-100% -> -0.20801131 | Q24: 105 | R24: 47 | S24: 253 | T24: 6 | U24: 0 | V24: 7 | W24: 0 | X24: 0 | Y24: =IF(ISERROR(E24/Q24),"",E24/Q24) -> 1044.5429 | Z24: =IF(ISERROR(E24/R24),"",E24/R24) -> 2333.5532 | AA24: =IF(ISERROR(Q24/R24),"",Q24/R24) -> 2.2340426 | AB24: =IF(ISERROR(R24/S24),"",R24/S24) -> 0.18577075 | AC24: =IF(ISERROR(T24/R24),"",T24/R24) -> 0.12765957 | AD24: =IF(ISERROR(U24/R24),"",U24/R24) -> 0 | AE24: =IF(ISERROR(V24/S24),"",V24/S24) -> 0.027667984 | AF24: =+V24/R24 -> 0.14893617 | AG24: =+X24/R24 -> 0 | AH24: 0 | AI24: =AH24/E24 -> 0 | AJ24: 780 | AK24: =+AJ24/E24 -> 0.0071117919 | AL24: 0 | AM24: 0 | AN24: =AM24/E24 -> 0 | AO24: 1 | AP24: 1799 | AQ24: =AP24/E24 -> 0.01640271 | AR24: 2 | AS24: 2798 | AT24: =AS24/E24 -> 0.025511274 | AU24: 7 | AV24: 6354 | AW24: =AV24/E24 -> 0.057933751 | AX24: 24 | AY24: =AX24/R24 -> 0.5106383 | AZ24: 100 | BA24: 100 | BB24: 1 | BC24: 2341 | BD24: =+BC24/E24 -> 0.021344493 | BE24: 1 | BF24: =BE24/R24 -> 0.021276596 | BG24: 0 | BH24: =BG24/R24 -> 0
B25: Sat | C25: =C24+1 -> 46277 | D25: 169731.09 | E25: 229487 | G25: =IF(ISERROR(F25/E25),"",F25/E25) -> 0 | H25: 89983 | I25: =IF(ISERROR(E25/D25),"",E25/D25) -> 1.3520623 | J25: =IF(ISERROR(E25/H25),"",(E25/H25))-1 -> 1.5503373 | K25: =IF(ISERROR(K24+D25),0,K24+D25) -> 1114460.7 | L25: =IF(ISERROR(L24+E25),0,L24+E25) -> 1018558 | M25: =IF(ISERROR(M24+H25),0,M24+H25) -> 1086299 | N25: =IF(ISERROR(L25/K25),"",L25/K25) -> 0.91394698 | O25: =IF(ISERROR(L25/M25),"",L25/M25)-100% -> -0.062359442 | Q25: 220 | R25: 82 | S25: 512 | T25: 4 | U25: 1 | V25: 10 | W25: 0 | X25: 0 | Y25: =IF(ISERROR(E25/Q25),"",E25/Q25) -> 1043.1227 | Z25: =IF(ISERROR(E25/R25),"",E25/R25) -> 2798.622 | AA25: =IF(ISERROR(Q25/R25),"",Q25/R25) -> 2.6829268 | AB25: =IF(ISERROR(R25/S25),"",R25/S25) -> 0.16015625 | AC25: =IF(ISERROR(T25/R25),"",T25/R25) -> 0.048780488 | AD25: =IF(ISERROR(U25/R25),"",U25/R25) -> 0.012195122 | AE25: =IF(ISERROR(V25/S25),"",V25/S25) -> 0.01953125 | AF25: =+V25/R25 -> 0.12195122 | AG25: =+X25/R25 -> 0 | AH25: 2466 | AI25: =AH25/E25 -> 0.010745707 | AJ25: 510 | AK25: =+AJ25/E25 -> 0.0022223481 | AL25: 3 | AM25: 4989 | AN25: =AM25/E25 -> 0.021739794 | AO25: 3 | AP25: 2337 | AQ25: =AP25/E25 -> 0.010183583 | AR25: 1 | AS25: 325 | AT25: =AS25/E25 -> 0.0014162022 | AU25: 11 | AV25: 12617 | AW25: =AV25/E25 -> 0.054979149 | AX25: 41 | AY25: =AX25/R25 -> 0.5 | AZ25: 100 | BA25: 100 | BB25: 1 | BC25: 2143 | BD25: =+BC25/E25 -> 0.0093382196 | BE25: 0 | BF25: =BE25/R25 -> 0 | BG25: 0 | BH25: =BG25/R25 -> 0
B26: Sun | C26: =C25+1 -> 46278 | D26: 169731.09 | E26: 183475 | G26: =IF(ISERROR(F26/E26),"",F26/E26) -> 0 | H26: 139375 | I26: =IF(ISERROR(E26/D26),"",E26/D26) -> 1.0809746 | J26: =IF(ISERROR(E26/H26),"",(E26/H26))-1 -> 0.31641256 | K26: =IF(ISERROR(K25+D26),0,K25+D26) -> 1284191.8 | L26: =IF(ISERROR(L25+E26),0,L25+E26) -> 1202033 | M26: =IF(ISERROR(M25+H26),0,M25+H26) -> 1225674 | N26: =IF(ISERROR(L26/K26),"",L26/K26) -> 0.93602296 | O26: =IF(ISERROR(L26/M26),"",L26/M26)-100% -> -0.019288163 | Q26: 187 | R26: 75 | S26: 500 | T26: 17 | U26: 0 | V26: 7 | W26: 0 | X26: 0 | Y26: =IF(ISERROR(E26/Q26),"",E26/Q26) -> 981.14973 | Z26: =IF(ISERROR(E26/R26),"",E26/R26) -> 2446.3333 | AA26: =IF(ISERROR(Q26/R26),"",Q26/R26) -> 2.4933333 | AB26: =IF(ISERROR(R26/S26),"",R26/S26) -> 0.15 | AC26: =IF(ISERROR(T26/R26),"",T26/R26) -> 0.22666667 | AD26: =IF(ISERROR(U26/R26),"",U26/R26) -> 0 | AE26: =IF(ISERROR(V26/S26),"",V26/S26) -> 0.014 | AF26: =+V26/R26 -> 0.093333333 | AG26: =+X26/R26 -> 0 | AH26: 0 | AI26: =AH26/E26 -> 0 | AJ26: 1924 | AK26: =+AJ26/E26 -> 0.010486442 | AL26: 1 | AM26: 2124 | AN26: =AM26/E26 -> 0.011576509 | AO26: 2 | AP26: 2814 | AQ26: =AP26/E26 -> 0.015337239 | AR26: 1 | AS26: 2124 | AT26: =AS26/E26 -> 0.011576509 | AU26: 7 | AV26: 7924 | AW26: =AV26/E26 -> 0.043188445 | AX26: 35 | AY26: =AX26/R26 -> 0.46666667 | AZ26: 100 | BA26: 50 | BB26: 0 | BC26: 0 | BD26: =+BC26/E26 -> 0 | BE26: 0 | BF26: =BE26/R26 -> 0 | BG26: 0 | BH26: =BG26/R26 -> 0
B27: Total | D27: =SUM(D20:D26) -> 749378.75 | E27: =SUM(E20:E26) -> 741019 | F27: =SUM(F20:F26) -> 0 | G27: =IF(ISERROR(F27/E27),"",F27/E27) -> 0 | H27: =SUM(H20:H26) -> 620690 | I27: =IF(ISERROR(E27/D27),"",E27/D27) -> 0.98884442 | J27: =IF(ISERROR(E27/H27),"",(E27/H27))-1 -> 0.19386328 | Q27: =SUM(Q20:Q26) -> 696 | R27: =SUM(R20:R26) -> 316 | S27: =SUM(S20:S26) -> 1949 | T27: =SUM(T20:T26) -> 30 | U27: =+SUM(U26,U25,U24,U23,U22,U21,U20) -> 3 | V27: =+SUM(V26,V25,V24,V23,V22,V21,V20) -> 33 | W27: =+SUM(W26,W25,W24,W23,W22,W21,W20) -> 0 | X27: =+SUM(X26,X25,X24,X23,X22,X21,X20) -> 0 | Y27: =IF(ISERROR(E27/Q27),"",E27/Q27) -> 1064.6825 | Z27: =IF(ISERROR(E27/R27),"",E27/R27) -> 2344.9968 | AA27: =IF(ISERROR(Q27/R27),"",Q27/R27) -> 2.2025316 | AB27: =IF(ISERROR(R27/S27),"",R27/S27) -> 0.16213443 | AC27: =IF(ISERROR(T27/R27),"",T27/R27) -> 0.094936709 | AD27: =IF(ISERROR(U27/R27),"",U27/R27) -> 0.0094936709 | AE27: =IF(ISERROR(V27/S27),"",V27/S27) -> 0.01693176 | AF27: =+V27/R27 -> 0.10443038 | AG27: =+X27/R27 -> 0 | AH27: =SUM(AH20:AH26) -> 6528 | AI27: =AH27/E27 -> 0.0088094907 | AJ27: =SUM(AJ20:AJ26) -> 3614 | AK27: =+AJ27/E27 -> 0.0048770679 | AL27: =SUM(AL20:AL26) -> 9 | AM27: =SUM(AM20:AM26) -> 41672 | AN27: =AM27/E27 -> 0.056236075 | AO27: =SUM(AO20:AO26) -> 9 | AP27: =SUM(AP20:AP26) -> 11027 | AQ27: =AP27/E27 -> 0.01488086 | AR27: =SUM(AR20:AR26) -> 6 | AS27: =SUM(AS20:AS26) -> 8845 | AT27: =AS27/E27 -> 0.011936266 | AU27: =+SUM(AU20:AU26) -> 47 | AV27: =+SUM(AV20:AV26) -> 46811 | AW27: =AV27/E27 -> 0.06317112 | AX27: =SUM(AX20:AX26) -> 153 | AY27: =AX27/R27 -> 0.48417722 | AZ27: =SUM(AZ20:AZ26) -> 700 | BA27: =SUM(BA20:BA26) -> 550 | BB27: =SUM(BB20:BB26) -> 3 | BC27: =SUM(BC20:BC26) -> 36844 | BD27: =+BC27/E27 -> 0.049720722 | BE27: =SUM(BE20:BE26) -> 3 | BF27: =BE27/R27 -> 0.0094936709 | BG27: =SUM(BG20:BG26) -> 0 | BH27: =BG27/R27 -> 0
A28: WEEK 3 | B28: Mon | C28: =C26+1 -> 46279 | D28: 73656.886 | E28: 63336 | G28: =IF(ISERROR(F28/E28),"",F28/E28) -> 0 | H28: 153549 | I28: =IF(ISERROR(E28/D28),"",E28/D28) -> 0.85987887 | J28: =IF(ISERROR(E28/H28),"",(E28/H28))-1 -> -0.58751929 | K28: =IF(ISERROR(K26+D28),0,K26+D28) -> 1357848.7 | L28: =IF(ISERROR(L26+E28),0,L26+E28) -> 1265369 | M28: =IF(ISERROR(M26+H28),0,M26+H28) -> 1379223 | N28: =IF(ISERROR(L28/K28),"",L28/K28) -> 0.9318925 | O28: =IF(ISERROR(L28/M28),"",L28/M28)-100% -> -0.082549377 | Q28: 63 | R28: 21 | S28: 149 | T28: 2 | U28: 0 | V28: 2 | W28: 0 | X28: 0 | Y28: =IF(ISERROR(E28/Q28),"",E28/Q28) -> 1005.3333 | Z28: =IF(ISERROR(E28/R28),"",E28/R28) -> 3016 | AA28: =IF(ISERROR(Q28/R28),"",Q28/R28) -> 3 | AB28: =IF(ISERROR(R28/S28),"",R28/S28) -> 0.1409396 | AC28: =IF(ISERROR(T28/R28),"",T28/R28) -> 0.095238095 | AD28: =IF(ISERROR(U28/R28),"",U28/R28) -> 0 | AE28: =IF(ISERROR(W28/R28),"",W28/R28) -> 0 | AF28: =+V28/R28 -> 0.095238095 | AG28: =+X28/R28 -> 0 | AH28: 0 | AI28: =AH28/E28 -> 0 | AJ28: 220 | AK28: =+AJ28/E28 -> 0.003473538 | AL28: 0 | AM28: 0 | AN28: =AM28/E28 -> 0 | AO28: 3 | AP28: 4080 | AQ28: =AP28/E28 -> 0.06441834 | AR28: 2 | AS28: 4687 | AT28: =AS28/E28 -> 0.074002147 | AU28: 7 | AV28: 9843 | AW28: =AV28/E28 -> 0.15540925 | AX28: 12 | AY28: =AX28/R28 -> 0.57142857 | AZ28: 100 | BA28: 50 | BB28: 0 | BC28: 0 | BD28: =+BC28/E28 -> 0 | BE28: 0 | BF28: =BE28/R28 -> 0 | BG28: 0 | BH28: =BG28/R28 -> 0
B29: Tues | C29: =C28+1 -> 46280 | D29: 76859.359 | E29: 60616 | G29: =IF(ISERROR(F29/E29),"",F29/E29) -> 0 | H29: 55073 | I29: =IF(ISERROR(E29/D29),"",E29/D29) -> 0.78866127 | J29: =IF(ISERROR(E29/H29),"",(E29/H29))-1 -> 0.10064823 | K29: =IF(ISERROR(K28+D29),0,K28+D29) -> 1434708 | L29: =IF(ISERROR(L28+E29),0,L28+E29) -> 1325985 | M29: =IF(ISERROR(M28+H29),0,M28+H29) -> 1434296 | N29: =IF(ISERROR(L29/K29),"",L29/K29) -> 0.9242194 | O29: =IF(ISERROR(L29/M29),"",L29/M29)-100% -> -0.075515096 | Q29: 47 | R29: 20 | S29: 159 | T29: 5 | U29: 0 | V29: 3 | W29: 0 | X29: 0 | Y29: =IF(ISERROR(E29/Q29),"",E29/Q29) -> 1289.7021 | Z29: =IF(ISERROR(E29/R29),"",E29/R29) -> 3030.8 | AA29: =IF(ISERROR(Q29/R29),"",Q29/R29) -> 2.35 | AB29: =IF(ISERROR(R29/S29),"",R29/S29) -> 0.12578616 | AC29: =IF(ISERROR(T29/R29),"",T29/R29) -> 0.25 | AD29: =IF(ISERROR(U29/R29),"",U29/R29) -> 0 | AE29: =IF(ISERROR(W29/R29),"",W29/R29) -> 0 | AF29: =+V29/R29 -> 0.15 | AG29: =+X29/R29 -> 0 | AH29: 0 | AI29: =AH29/E29 -> 0 | AJ29: 552 | AK29: =+AJ29/E29 -> 0.0091065065 | AL29: 0 | AM29: 0 | AN29: =AM29/E29 -> 0 | AO29: 2 | AP29: 6898 | AQ29: =AP29/E29 -> 0.11379834 | AR29: 1 | AS29: 3059 | AT29: =AS29/E29 -> 0.050465224 | AU29: 4 | AV29: 10437 | AW29: =AV29/E29 -> 0.17218226 | AX29: 15 | AY29: =AX29/R29 -> 0.75 | AZ29: 100 | BA29: 50 | BB29: 0 | BC29: 0 | BD29: =+BC29/E29 -> 0 | BE29: 0 | BF29: =BE29/R29 -> 0 | BG29: 0 | BH29: =BG29/R29 -> 0
B30: Wed | C30: =C29+1 -> 46281 | D30: 76859.359 | E30: 45330 | G30: =IF(ISERROR(F30/E30),"",F30/E30) -> 0 | H30: 55540 | I30: =IF(ISERROR(E30/D30),"",E30/D30) -> 0.58977853 | J30: =IF(ISERROR(E30/H30),"",(E30/H30))-1 -> -0.18383147 | K30: =IF(ISERROR(K29+D30),0,K29+D30) -> 1511567.4 | L30: =IF(ISERROR(L29+E30),0,L29+E30) -> 1371315 | M30: =IF(ISERROR(M29+H30),0,M29+H30) -> 1489836 | N30: =IF(ISERROR(L30/K30),"",L30/K30) -> 0.90721393 | O30: =IF(ISERROR(L30/M30),"",L30/M30)-100% -> -0.079553051 | Q30: 47 | R30: 20 | S30: 151 | T30: 2 | U30: 0 | V30: 5 | W30: 0 | X30: 3 | Y30: =IF(ISERROR(E30/Q30),"",E30/Q30) -> 964.46809 | Z30: =IF(ISERROR(E30/R30),"",E30/R30) -> 2266.5 | AA30: =IF(ISERROR(Q30/R30),"",Q30/R30) -> 2.35 | AB30: =IF(ISERROR(R30/S30),"",R30/S30) -> 0.13245033 | AC30: =IF(ISERROR(T30/R30),"",T30/R30) -> 0.1 | AD30: =IF(ISERROR(U30/R30),"",U30/R30) -> 0 | AE30: =IF(ISERROR(W30/R30),"",W30/R30) -> 0 | AF30: =+V30/R30 -> 0.25 | AG30: =+X30/R30 -> 0.15 | AH30: 0 | AI30: =AH30/E30 -> 0 | AJ30: 220 | AK30: =+AJ30/E30 -> 0.004853298 | AL30: 0 | AM30: 0 | AN30: =AM30/E30 -> 0 | AO30: 1 | AP30: 2804 | AQ30: =AP30/E30 -> 0.06185749 | AR30: 0 | AS30: 0 | AT30: =AS30/E30 -> 0 | AU30: 1 | AV30: 2804 | AW30: =AV30/E30 -> 0.06185749 | AX30: 10 | AY30: =AX30/R30 -> 0.5 | AZ30: 100 | BA30: 50 | BB30: 0 | BC30: 0 | BD30: =+BC30/E30 -> 0 | BE30: 0 | BF30: =BE30/R30 -> 0 | BG30: 0 | BH30: =BG30/R30 -> 0
B31: Thurs | C31: =C30+1 -> 46282 | D31: 89669.252 | E31: 43767 | G31: =IF(ISERROR(F31/E31),"",F31/E31) -> 0 | H31: 46315 | I31: =IF(ISERROR(E31/D31),"",E31/D31) -> 0.48809373 | J31: =IF(ISERROR(E31/H31),"",(E31/H31))-1 -> -0.055014574 | K31: =IF(ISERROR(K30+D31),0,K30+D31) -> 1601236.7 | L31: =IF(ISERROR(L30+E31),0,L30+E31) -> 1415082 | M31: =IF(ISERROR(M30+H31),0,M30+H31) -> 1536151 | N31: =IF(ISERROR(L31/K31),"",L31/K31) -> 0.8837432 | O31: =IF(ISERROR(L31/M31),"",L31/M31)-100% -> -0.078813216 | Q31: 52 | R31: 25 | S31: 169 | T31: 7 | U31: 0 | V31: 2 | W31: 1 | X31: 3 | Y31: =IF(ISERROR(E31/Q31),"",E31/Q31) -> 841.67308 | Z31: =IF(ISERROR(E31/R31),"",E31/R31) -> 1750.68 | AA31: =IF(ISERROR(Q31/R31),"",Q31/R31) -> 2.08 | AB31: =IF(ISERROR(R31/S31),"",R31/S31) -> 0.14792899 | AC31: =IF(ISERROR(T31/R31),"",T31/R31) -> 0.28 | AD31: =IF(ISERROR(U31/R31),"",U31/R31) -> 0 | AE31: =IF(ISERROR(W31/R31),"",W31/R31) -> 0.04 | AF31: =+V31/R31 -> 0.08 | AG31: =+X31/R31 -> 0.12 | AH31: 0 | AI31: =AH31/E31 -> 0 | AJ31: 848 | AK31: =+AJ31/E31 -> 0.019375328 | AL31: 0 | AM31: 0 | AN31: =AM31/E31 -> 0 | AO31: 1 | AP31: 1359 | AQ31: =AP31/E31 -> 0.031050792 | AR31: 1 | AS31: 1359 | AT31: =AS31/E31 -> 0.031050792 | AU31: 6 | AV31: 6645 | AW31: =AV31/E31 -> 0.15182672 | AX31: 15 | AY31: =AX31/R31 -> 0.6 | AZ31: 100 | BA31: 50 | BB31: 0 | BC31: 0 | BD31: =+BC31/E31 -> 0 | BE31: 0 | BF31: =BE31/R31 -> 0 | BG31: 0 | BH31: =BG31/R31 -> 0
B32: Fri | C32: =C31+1 -> 46283 | D32: 96074.199 | E32: 103358 | G32: =IF(ISERROR(F32/E32),"",F32/E32) -> 0 | H32: 76551 | I32: =IF(ISERROR(E32/D32),"",E32/D32) -> 1.0758143 | J32: =IF(ISERROR(E32/H32),"",(E32/H32))-1 -> 0.35018484 | K32: =IF(ISERROR(K31+D32),0,K31+D32) -> 1697310.9 | L32: =IF(ISERROR(L31+E32),0,L31+E32) -> 1518440 | M32: =IF(ISERROR(M31+H32),0,M31+H32) -> 1612702 | N32: =IF(ISERROR(L32/K32),"",L32/K32) -> 0.89461515 | O32: =IF(ISERROR(L32/M32),"",L32/M32)-100% -> -0.058449732 | Q32: 94 | R32: 42 | S32: 247 | T32: 1 | U32: 0 | V32: 5 | W32: 0 | X32: 1 | Y32: =IF(ISERROR(E32/Q32),"",E32/Q32) -> 1099.5532 | Z32: =IF(ISERROR(E32/R32),"",E32/R32) -> 2460.9048 | AA32: =IF(ISERROR(Q32/R32),"",Q32/R32) -> 2.2380952 | AB32: =IF(ISERROR(R32/S32),"",R32/S32) -> 0.17004049 | AC32: =IF(ISERROR(T32/R32),"",T32/R32) -> 0.023809524 | AD32: =IF(ISERROR(U32/R32),"",U32/R32) -> 0 | AE32: =IF(ISERROR(W32/R32),"",W32/R32) -> 0 | AF32: =+V32/R32 -> 0.11904762 | AG32: =+X32/R32 -> 0.023809524 | AH32: 0 | AI32: =AH32/E32 -> 0 | AJ32: 110 | AK32: =+AJ32/E32 -> 0.0010642621 | AL32: 1 | AM32: 1199 | AN32: =AM32/E32 -> 0.011600457 | AO32: 3 | AP32: 8797 | AQ32: =AP32/E32 -> 0.085111941 | AR32: 0 | AS32: 0 | AT32: =AS32/E32 -> 0 | AU32: 7 | AV32: 12343 | AW32: =AV32/E32 -> 0.11941988 | AX32: 27 | AY32: =AX32/R32 -> 0.64285714 | AZ32: 100 | BA32: 60 | BB32: 2 | BC32: 2196 | BD32: =+BC32/E32 -> 0.021246541 | BE32: 0 | BF32: =BE32/R32 -> 0 | BG32: 0 | BH32: =BG32/R32 -> 0
B33: Sat | C33: =C32+1 -> 46284 | D33: 169731.09 | E33: 192912 | G33: =IF(ISERROR(F33/E33),"",F33/E33) -> 0 | H33: 89503 | I33: =IF(ISERROR(E33/D33),"",E33/D33) -> 1.1365744 | J33: =IF(ISERROR(E33/H33),"",(E33/H33))-1 -> 1.1553691 | K33: =IF(ISERROR(K32+D33),0,K32+D33) -> 1867041.9 | L33: =IF(ISERROR(L32+E33),0,L32+E33) -> 1711352 | M33: =IF(ISERROR(M32+H33),0,M32+H33) -> 1702205 | N33: =IF(ISERROR(L33/K33),"",L33/K33) -> 0.91661144 | O33: =IF(ISERROR(L33/M33),"",L33/M33)-100% -> 0.0053736183 | Q33: 180 | R33: 81 | S33: 500 | T33: 6 | U33: 1 | V33: 15 | W33: 0 | X33: 0 | Y33: =IF(ISERROR(E33/Q33),"",E33/Q33) -> 1071.7333 | Z33: =IF(ISERROR(E33/R33),"",E33/R33) -> 2381.6296 | AA33: =IF(ISERROR(Q33/R33),"",Q33/R33) -> 2.2222222 | AB33: =IF(ISERROR(R33/S33),"",R33/S33) -> 0.162 | AC33: =IF(ISERROR(T33/R33),"",T33/R33) -> 0.074074074 | AD33: =IF(ISERROR(U33/R33),"",U33/R33) -> 0.012345679 | AE33: =IF(ISERROR(W33/R33),"",W33/R33) -> 0 | AF33: =+V33/R33 -> 0.18518519 | AG33: =+X33/R33 -> 0 | AH33: 1099 | AI33: =AH33/E33 -> 0.0056968981 | AJ33: 680 | AK33: =+AJ33/E33 -> 0.0035249233 | AL33: 4 | AM33: 9721 | AN33: =AM33/E33 -> 0.050390852 | AO33: 5 | AP33: 5495 | AQ33: =AP33/E33 -> 0.02848449 | AR33: 3 | AS33: 11082 | AT33: =AS33/E33 -> 0.057445882 | AU33: 14 | AV33: 18722 | AW33: =AV33/E33 -> 0.097049432 | AX33: 45 | AY33: =AX33/R33 -> 0.55555556 | AZ33: 100 | BA33: 50 | BB33: 0 | BC33: 0 | BD33: =+BC33/E33 -> 0 | BE33: 0 | BF33: =BE33/R33 -> 0 | BG33: 0 | BH33: =BG33/R33 -> 0
B34: Sun | C34: =C33+1 -> 46285 | D34: 169731.09 | E34: 239136 | G34: =IF(ISERROR(F34/E34),"",F34/E34) -> 0 | H34: 122958 | I34: =IF(ISERROR(E34/D34),"",E34/D34) -> 1.408911 | J34: =IF(ISERROR(E34/H34),"",(E34/H34))-1 -> 0.94485922 | K34: =IF(ISERROR(K33+D34),0,K33+D34) -> 2036773 | L34: =IF(ISERROR(L33+E34),0,L33+E34) -> 1950488 | M34: =IF(ISERROR(M33+H34),0,M33+H34) -> 1825163 | N34: =IF(ISERROR(L34/K34),"",L34/K34) -> 0.95763641 | O34: =IF(ISERROR(L34/M34),"",L34/M34)-100% -> 0.0686651 | Q34: 221 | R34: 84 | S34: 538 | T34: 11 | U34: 1 | V34: 17 | W34: 0 | X34: 6 | Y34: =IF(ISERROR(E34/Q34),"",E34/Q34) -> 1082.0633 | Z34: =IF(ISERROR(E34/R34),"",E34/R34) -> 2846.8571 | AA34: =IF(ISERROR(Q34/R34),"",Q34/R34) -> 2.6309524 | AB34: =IF(ISERROR(R34/S34),"",R34/S34) -> 0.15613383 | AC34: =IF(ISERROR(T34/R34),"",T34/R34) -> 0.13095238 | AD34: =IF(ISERROR(U34/R34),"",U34/R34) -> 0.011904762 | AE34: =IF(ISERROR(W34/R34),"",W34/R34) -> 0 | AF34: =+V34/R34 -> 0.20238095 | AG34: =+X34/R34 -> 0.071428571 | AH34: 1440 | AI34: =AH34/E34 -> 0.006021678 | AJ34: 1266 | AK34: =+AJ34/E34 -> 0.0052940586 | AL34: 5 | AM34: 5195 | AN34: =AM34/E34 -> 0.02172404 | AO34: 5 | AP34: 8357 | AQ34: =AP34/E34 -> 0.034946641 | AR34: 6 | AS34: 13464 | AT34: =AS34/E34 -> 0.05630269 | AU34: 20 | AV34: 26548 | AW34: =AV34/E34 -> 0.11101633 | AX34: 48 | AY34: =AX34/R34 -> 0.57142857 | AZ34: 100 | BA34: 50 | BB34: 0 | BC34: 0 | BD34: =+BC34/E34 -> 0 | BE34: 0 | BF34: =BE34/R34 -> 0 | BG34: 0 | BH34: =BG34/R34 -> 0
B35: Total | D35: =SUM(D28:D34) -> 752581.23 | E35: =SUM(E28:E34) -> 748455 | F35: =SUM(F28:F34) -> 0 | G35: =IF(ISERROR(F35/E35),"",F35/E35) -> 0 | H35: =SUM(H28:H34) -> 599489 | I35: =IF(ISERROR(E35/D35),"",E35/D35) -> 0.99451723 | J35: =IF(ISERROR(E35/H35),"",(E35/H35))-1 -> 0.2484883 | Q35: =SUM(Q28:Q34) -> 704 | R35: =SUM(R28:R34) -> 293 | S35: =SUM(S28:S34) -> 1913 | T35: =SUM(T28:T34) -> 34 | U35: =SUM(U28:U34) -> 2 | V35: =SUM(V28:V34) -> 49 | W35: =SUM(W28:W34) -> 1 | X35: =SUM(X28:X34) -> 13 | Y35: =IF(ISERROR(E35/Q35),"",E35/Q35) -> 1063.1463 | Z35: =IF(ISERROR(E35/R35),"",E35/R35) -> 2554.4539 | AA35: =IF(ISERROR(Q35/R35),"",Q35/R35) -> 2.4027304 | AB35: =IF(ISERROR(R35/S35),"",R35/S35) -> 0.15316257 | AC35: =IF(ISERROR(T35/R35),"",T35/R35) -> 0.11604096 | AD35: =IF(ISERROR(U35/R35),"",U35/R35) -> 0.0068259386 | AE35: =IF(ISERROR(W35/R35),"",W35/R35) -> 0.0034129693 | AF35: =+V35/R35 -> 0.16723549 | AG35: =+X35/R35 -> 0.044368601 | AH35: =SUM(AH28:AH34) -> 2539 | AI35: =AH35/E35 -> 0.0033923215 | AJ35: =SUM(AJ28:AJ34) -> 3896 | AK35: =SUM(AK28:AK34) -> 0.046691915 | AL35: =SUM(AL28:AL34) -> 10 | AM35: =SUM(AM28:AM34) -> 16115 | AN35: =AM35/E35 -> 0.021531021 | AO35: =SUM(AO28:AO34) -> 20 | AP35: =SUM(AP28:AP34) -> 37790 | AQ35: =AP35/E35 -> 0.050490677 | AR35: =SUM(AR28:AR34) -> 13 | AS35: =SUM(AS28:AS34) -> 33651 | AT35: =AS35/E35 -> 0.044960619 | AU35: =+SUM(AU28:AU34) -> 59 | AV35: =+SUM(AV28:AV34) -> 87342 | AW35: =AV35/E35 -> 0.11669639 | AX35: =SUM(AX28:AX34) -> 172 | AY35: =SUM(AY28:AY34) -> 4.1912698 | AZ35: =SUM(AZ28:AZ34) -> 700 | BA35: =SUM(BA28:BA34) -> 360 | BB35: =SUM(BB28:BB34) -> 2 | BC35: =SUM(BC28:BC34) -> 2196 | BD35: =+BC35/E35 -> 0.0029340441 | BE35: =SUM(BE28:BE34) -> 0 | BF35: =BE35/R35 -> 0 | BG35: =SUM(BG28:BG34) -> 0 | BH35: =BG35/R35 -> 0
A36: WEEK 4 | B36: Mon | C36: =C34+1 -> 46286 | D36: 73656.886 | E36: 61212 | G36: =IF(ISERROR(F36/E36),"",F36/E36) -> 0 | H36: 151580 | I36: =IF(ISERROR(E36/D36),"",E36/D36) -> 0.83104246 | J36: =IF(ISERROR(E36/H36),"",(E36/H36))-1 -> -0.59617364 | K36: =IF($C36="","",IF(ISERROR(K34+D36),0,K34+D36)) -> 2110429.9 | L36: =IF(ISERROR(L34+E36),0,L34+E36) -> 2011700 | M36: =IF(ISERROR(M34+H36),0,M34+H36) -> 1976743 | N36: =IF(ISERROR(L36/K36),"",L36/K36) -> 0.95321811 | O36: =IF(ISERROR(L36/M36),"",L36/M36)-100% -> 0.01768414 | Q36: 54 | R36: 30 | S36: 216 | T36: 4 | U36: 0 | V36: 1 | W36: 0 | X36: 0 | Y36: =IF(ISERROR(E36/Q36),"",E36/Q36) -> 1133.5556 | Z36: =IF(ISERROR(E36/R36),"",E36/R36) -> 2040.4 | AA36: =IF(ISERROR(Q36/R36),"",Q36/R36) -> 1.8 | AB36: =IF(ISERROR(R36/S36),"",R36/S36) -> 0.13888889 | AC36: =IF(ISERROR(T36/R36),"",T36/R36) -> 0.13333333 | AD36: =IF(ISERROR(U36/R36),"",U36/R36) -> 0 | AE36: =IF(ISERROR(W36/R36),"",W36/R36) -> 0 | AF36: =+V36/R36 -> 0.033333333 | AG36: =+X36/R36 -> 0 | AH36: 0 | AI36: =AH36/E36 -> 0 | AJ36: 440 | AK36: =+AJ36/E36 -> 0.007188133 | AL36: 1 | AM36: 1099 | AN36: =AM36/E36 -> 0.017953996 | AO36: 1 | AP36: 999 | AQ36: =AP36/E36 -> 0.016320329 | AR36: 0 | AS36: 0 | AT36: =AS36/E36 -> 0 | AU36: 3 | AV36: 1947 | AW36: =AV36/E36 -> 0.031807489 | AX36: 14 | AY36: =AX36/R36 -> 0.46666667 | AZ36: 100 | BA36: 50 | BB36: 0 | BC36: 0 | BD36: =+BC36/E36 -> 0 | BE36: 0 | BF36: =BE36/R36 -> 0 | BG36: 0 | BH36: =BG36/R36 -> 0
B37: Tue | C37: =C36+1 -> 46287 | D37: 76859.359 | E37: 110446 | G37: =IF(ISERROR(F37/E37),"",F37/E37) -> 0 | H37: 64149 | I37: =IF(ISERROR(E37/D37),"",E37/D37) -> 1.4369883 | J37: =IF(ISERROR(E37/H37),"",(E37/H37))-1 -> 0.72171039 | K37: =IF(C37="","",IF(ISERROR(K36+D37),0,K36+D37)) -> 2187289.3 | L37: =IF(ISERROR(L36+E37),0,L36+E37) -> 2122146 | M37: =IF(ISERROR(M36+H37),0,M36+H37) -> 2040892 | N37: =IF(ISERROR(L37/K37),"",L37/K37) -> 0.97021735 | O37: =IF(ISERROR(L37/M37),"",L37/M37)-100% -> 0.039812984 | Q37: 102 | R37: 42 | S37: 281 | T37: 16 | U37: 1 | V37: 2 | W37: 0 | X37: 0 | Y37: =IF(ISERROR(E37/Q37),"",E37/Q37) -> 1082.8039 | Z37: =IF(ISERROR(E37/R37),"",E37/R37) -> 2629.6667 | AA37: =IF(ISERROR(Q37/R37),"",Q37/R37) -> 2.4285714 | AB37: =IF(ISERROR(R37/S37),"",R37/S37) -> 0.14946619 | AC37: =IF(ISERROR(T37/R37),"",T37/R37) -> 0.38095238 | AD37: =IF(ISERROR(U37/R37),"",U37/R37) -> 0.023809524 | AE37: =IF(ISERROR(W37/R37),"",W37/R37) -> 0 | AF37: =+V37/R37 -> 0.047619048 | AG37: =+X37/R37 -> 0 | AH37: 1499 | AI37: =AH37/E37 -> 0.013572243 | AJ37: 1880 | AK37: =+AJ37/E37 -> 0.017021893 | AL37: 2 | AM37: 2398 | AN37: =AM37/E37 -> 0.021711968 | AO37: 2 | AP37: 5208 | AQ37: =AP37/E37 -> 0.047154265 | AR37: 0 | AS37: 0 | AT37: =AS37/E37 -> 0 | AU37: 7 | AV37: 11789 | AW37: =AV37/E37 -> 0.10673995 | AX37: 26 | AY37: =AX37/R37 -> 0.61904762 | AZ37: 100 | BA37: 0 | BB37: 0 | BC37: 0 | BD37: =+BC37/E37 -> 0 | BE37: 0 | BF37: =BE37/R37 -> 0 | BG37: 0 | BH37: =BG37/R37 -> 0
B38: Wed | C38: =C37+1 -> 46288 | D38: 76859.359 | E38: 74250 | G38: =IF(ISERROR(F38/E38),"",F38/E38) -> 0 | H38: 155133 | I38: =IF(ISERROR(E38/D38),"",E38/D38) -> 0.96605021 | J38: =IF(ISERROR(E38/H38),"",(E38/H38))-1 -> -0.52137843 | K38: =IF(C38="","",IF(ISERROR(K37+D38),0,K37+D38)) -> 2264148.6 | L38: =IF($C38="","",IF(ISERROR(L37+E38),0,L37+E38)) -> 2196396 | M38: =IF($C38="","",IF(ISERROR(M37+H38),0,M37+H38)) -> 2196025 | N38: =IF(ISERROR(L38/K38),"",L38/K38) -> 0.97007589 | O38: =IF(ISERROR(L38/M38),"",L38/M38)-100% -> 0.00016894161 | Q38: 69 | R38: 39 | S38: 214 | T38: 1 | U38: 0 | V38: 5 | W38: 0 | X38: 2 | Y38: =IF(ISERROR(E38/Q38),"",E38/Q38) -> 1076.087 | Z38: =IF(ISERROR(E38/R38),"",E38/R38) -> 1903.8462 | AA38: =IF(ISERROR(Q38/R38),"",Q38/R38) -> 1.7692308 | AB38: =IF(ISERROR(R38/S38),"",R38/S38) -> 0.18224299 | AC38: =IF(ISERROR(T38/R38),"",T38/R38) -> 0.025641026 | AD38: =IF(ISERROR(U38/R38),"",U38/R38) -> 0 | AE38: =IF(ISERROR(W38/R38),"",W38/R38) -> 0 | AF38: =+V38/R38 -> 0.12820513 | AG38: =+X38/R38 -> 0.051282051 | AH38: 0 | AI38: =AH38/E38 -> 0 | AJ38: 120 | AK38: =+AJ38/E38 -> 0.0016161616 | AL38: 0 | AM38: 0 | AN38: =AM38/E38 -> 0 | AO38: 4 | AP38: 11468 | AQ38: =AP38/E38 -> 0.15445118 | AR38: 1 | AS38: 5099 | AT38: =AS38/E38 -> 0.068673401 | AU38: 9 | AV38: 15178 | AW38: =AV38/E38 -> 0.20441751 | AX38: 20 | AY38: =AX38/R38 -> 0.51282051 | AZ38: 100 | BA38: 0 | BB38: 0 | BC38: 0 | BD38: =+BC38/E38 -> 0 | BE38: 0 | BF38: =BE38/R38 -> 0 | BG38: 0 | BH38: =BG38/R38 -> 0
B39: Thu | C39: =C38+1 -> 46289 | D39: 89669.252 | E39: 111052 | G39: =IF(ISERROR(F39/E39),"",F39/E39) -> 0 | H39: 68405 | I39: =IF(ISERROR(E39/D39),"",E39/D39) -> 1.2384624 | J39: =IF(ISERROR(E39/H39),"",(E39/H39))-1 -> 0.62344858 | K39: =IF(C39="","",IF(ISERROR(K38+D39),0,K38+D39)) -> 2353817.9 | L39: =IF($C39="","",IF(ISERROR(L38+E39),0,L38+E39)) -> 2307448 | M39: =IF($C39="","",IF(ISERROR(M38+H39),0,M38+H39)) -> 2264430 | N39: =IF(ISERROR(L39/K39),"",L39/K39) -> 0.98030014 | O39: =IF(ISERROR(L39/M39),"",L39/M39)-100% -> 0.018997275 | Q39: 127 | R39: 60 | S39: 287 | T39: 7 | U39: 0 | V39: 5 | W39: 0 | X39: 5 | Y39: =IF(ISERROR(E39/Q39),"",E39/Q39) -> 874.4252 | Z39: =IF(ISERROR(E39/R39),"",E39/R39) -> 1850.8667 | AA39: =IF(ISERROR(Q39/R39),"",Q39/R39) -> 2.1166667 | AB39: =IF(ISERROR(R39/S39),"",R39/S39) -> 0.20905923 | AC39: =IF(ISERROR(T39/R39),"",T39/R39) -> 0.11666667 | AD39: =IF(ISERROR(U39/R39),"",U39/R39) -> 0 | AE39: =IF(ISERROR(W39/R39),"",W39/R39) -> 0 | AF39: =+V39/R39 -> 0.083333333 | AG39: =+X39/R39 -> 0.083333333 | AH39: 0 | AI39: =AH39/E39 -> 0 | AJ39: 698 | AK39: =+AJ39/E39 -> 0.0062853438 | AL39: 3 | AM39: 4623 | AN39: =AM39/E39 -> 0.041629147 | AO39: 2 | AP39: 4139 | AQ39: =AP39/E39 -> 0.037270828 | AR39: 5 | AS39: 10936 | AT39: =AS39/E39 -> 0.098476389 | AU39: 8 | AV39: 13930 | AW39: =AV39/E39 -> 0.12543673 | AX39: 30 | AY39: =AX39/R39 -> 0.5 | AZ39: 100 | BA39: 50 | BB39: 0 | BC39: 0 | BD39: =+BC39/E39 -> 0 | BE39: 2 | BF39: =BE39/R39 -> 0.033333333 | BG39: 0 | BH39: =BG39/R39 -> 0
B40: Fri | C40: =C39+1 -> 46290 | D40: 96074.199 | E40: 96738 | G40: =IF(ISERROR(F40/E40),"",F40/E40) -> 0 | H40: 89900 | I40: =IF(ISERROR(E40/D40),"",E40/D40) -> 1.0069093 | J40: =IF(ISERROR(E40/H40),"",(E40/H40))-1 -> 0.076062291 | K40: =IF(C40="","",IF(ISERROR(K39+D40),0,K39+D40)) -> 2449892.1 | L40: =IF($C40="","",IF(ISERROR(L39+E40),0,L39+E40)) -> 2404186 | M40: =IF($C40="","",IF(ISERROR(M39+H40),0,M39+H40)) -> 2354330 | N40: =IF(ISERROR(L40/K40),"",L40/K40) -> 0.98134364 | O40: =IF(ISERROR(L40/M40),"",L40/M40)-100% -> 0.021176301 | Q40: 100 | R40: 48 | S40: 265 | T40: 11 | U40: 0 | V40: 5 | W40: 0 | X40: 0 | Y40: =IF(ISERROR(E40/Q40),"",E40/Q40) -> 967.38 | Z40: =IF(ISERROR(E40/R40),"",E40/R40) -> 2015.375 | AA40: =IF(ISERROR(Q40/R40),"",Q40/R40) -> 2.0833333 | AB40: =IF(ISERROR(R40/S40),"",R40/S40) -> 0.18113208 | AC40: =IF(ISERROR(T40/R40),"",T40/R40) -> 0.22916667 | AD40: =IF(ISERROR(U40/R40),"",U40/R40) -> 0 | AE40: =IF(ISERROR(W40/R40),"",W40/R40) -> 0 | AF40: =+V40/R40 -> 0.10416667 | AG40: =+X40/R40 -> 0 | AH40: 0 | AI40: =AH40/E40 -> 0 | AJ40: 1142 | AK40: =+AJ40/E40 -> 0.011805082 | AL40: 2 | AM40: 1860 | AN40: =AM40/E40 -> 0.019227191 | AO40: 4 | AP40: 5309 | AQ40: =AP40/E40 -> 0.054880192 | AR40: 1 | AS40: 1799 | AT40: =AS40/E40 -> 0.018596622 | AU40: 7 | AV40: 8581 | AW40: =AV40/E40 -> 0.088703508 | AX40: 31 | AY40: =AX40/R40 -> 0.64583333 | AZ40: 100 | BA40: 50 | BB40: 0 | BC40: 0 | BD40: =+BC40/E40 -> 0 | BE40: 0 | BF40: =BE40/R40 -> 0 | BG40: 0 | BH40: =BG40/R40 -> 0
B41: Sat | C41: =C40+1 -> 46291 | D41: 176136.03 | G41: =IF(ISERROR(F41/E41),"",F41/E41) | H41: 71229 | I41: =IF(ISERROR(E41/D41),"",E41/D41) -> 0 | J41: =IF(ISERROR(E41/H41),"",(E41/H41))-1 -> -1 | K41: =IF(C41="","",IF(ISERROR(K40+D41),0,K40+D41)) -> 2626028.1 | L41: =IF($C41="","",IF(ISERROR(L40+E41),0,L40+E41)) -> 2404186 | M41: =IF($C41="","",IF(ISERROR(M40+H41),0,M40+H41)) -> 2425559 | N41: =IF(ISERROR(L41/K41),"",L41/K41) -> 0.91552181 | O41: =IF(ISERROR(L41/M41),"",L41/M41)-100% -> -0.008811577 | Y41: =IF(ISERROR(E41/Q41),"",E41/Q41) | Z41: =IF(ISERROR(E41/R41),"",E41/R41) | AA41: =IF(ISERROR(Q41/R41),"",Q41/R41) | AB41: =IF(ISERROR(R41/S41),"",R41/S41) | AC41: =IF(ISERROR(T41/R41),"",T41/R41) | AD41: =IF(ISERROR(U41/R41),"",U41/R41) | AE41: =IF(ISERROR(W41/R41),"",W41/R41) | AF41: =+V41/R41 -> #DIV/0! | AG41: =+X41/R41 -> #DIV/0! | AI41: =AH41/E41 -> #DIV/0! | AK41: 0.03 | AN41: =AM41/E41 -> #DIV/0! | AQ41: =AP41/E41 -> #DIV/0! | AT41: =AS41/E41 -> #DIV/0! | AW41: =AV41/E41 -> #DIV/0! | AY41: =AX41/R41 -> #DIV/0! | BD41: =+BC41/E41 -> #DIV/0! | BF41: =BE41/R41 -> #DIV/0! | BH41: =BG41/R41 -> #DIV/0!
B42: Sun | C42: =C41+1 -> 46292 | D42: 176136.03 | G42: =IF(ISERROR(F42/E42),"",F42/E42) | H42: 162085 | I42: =IF(ISERROR(E42/D42),"",E42/D42) -> 0 | J42: =IF(ISERROR(E42/H42),"",(E42/H42))-1 -> -1 | K42: =IF(C42="","",IF(ISERROR(K41+D42),0,K41+D42)) -> 2802164.1 | L42: =IF($C42="","",IF(ISERROR(L41+E42),0,L41+E42)) -> 2404186 | M42: =IF($C42="","",IF(ISERROR(M41+H42),0,M41+H42)) -> 2587644 | N42: =IF(ISERROR(L42/K42),"",L42/K42) -> 0.85797472 | O42: =IF(ISERROR(L42/M42),"",L42/M42)-100% -> -0.070897697 | Y42: =IF(ISERROR(E42/Q42),"",E42/Q42) | Z42: =IF(ISERROR(E42/R42),"",E42/R42) | AA42: =IF(ISERROR(Q42/R42),"",Q42/R42) | AB42: =IF(ISERROR(R42/S42),"",R42/S42) | AC42: =IF(ISERROR(T42/R42),"",T42/R42) | AD42: =IF(ISERROR(U42/R42),"",U42/R42) | AE42: =IF(ISERROR(W42/R42),"",W42/R42) | AF42: =+V42/R42 -> #DIV/0! | AG42: =+X42/R42 -> #DIV/0! | AI42: =AH42/E42 -> #DIV/0! | AK42: =+AJ42/E42 -> #DIV/0! | AN42: =AM42/E42 -> #DIV/0! | AQ42: =AP42/E42 -> #DIV/0! | AT42: =AS42/E42 -> #DIV/0! | AW42: =AV42/E42 -> #DIV/0! | AY42: =AX42/R42 -> #DIV/0! | BD42: =+BC42/E42 -> #DIV/0! | BF42: =BE42/R42 -> #DIV/0! | BH42: =BG42/R42 -> #DIV/0!
B43: Total | D43: =SUM(D36:D42) -> 765391.12 | E43: =SUM(E36:E42) -> 453698 | F43: =SUM(F36:F42) -> 0 | G43: =IF(ISERROR(F43/E43),"",F43/E43) -> 0 | H43: =SUM(H36:H42) -> 762481 | I43: =IF(ISERROR(E43/D43),"",E43/D43) -> 0.59276622 | J43: =IF(ISERROR(E43/H43),"",(E43/H43))-1 -> -0.4049714 | N43: =IF(ISERROR(I43/L43),"",(I43/L43)) | Q43: =SUM(Q36:Q42) -> 452 | R43: =SUM(R36:R42) -> 219 | S43: =SUM(S36:S42) -> 1263 | T43: =SUM(T36:T42) -> 39 | U43: =SUM(U36:U42) -> 1 | V43: =SUM(V36:V42) -> 18 | W43: =SUM(W36:W42) -> 0 | X43: =SUM(X36:X42) -> 7 | Y43: =IF(ISERROR(E43/Q43),"",E43/Q43) -> 1003.7566 | Z43: =IF(ISERROR(E43/R43),"",E43/R43) -> 2071.6804 | AA43: =IF(ISERROR(Q43/R43),"",Q43/R43) -> 2.0639269 | AB43: =IF(ISERROR(R43/S43),"",R43/S43) -> 0.17339667 | AC43: =IF(ISERROR(T43/R43),"",T43/R43) -> 0.17808219 | AD43: =IF(ISERROR(U43/R43),"",U43/R43) -> 0.00456621 | AE43: =IF(ISERROR(W43/R43),"",W43/R43) -> 0 | AF43: =+V43/R43 -> 0.082191781 | AG43: =+X43/R43 -> 0.03196347 | AH43: =SUM(AH36:AH42) -> 1499 | AI43: =AH43/E43 -> 0.0033039599 | AJ43: =SUM(AJ36:AJ42) -> 4280 | AK43: =SUM(AK36:AK42) -> #DIV/0! | AL43: =SUM(AL36:AL42) -> 8 | AM43: =SUM(AM36:AM42) -> 9980 | AN43: =AM43/E43 -> 0.021997011 | AO43: =SUM(AO36:AO42) -> 13 | AP43: =SUM(AP36:AP42) -> 27123 | AQ43: =AP43/E43 -> 0.059782058 | AR43: =SUM(AR36:AR42) -> 7 | AS43: =SUM(AS36:AS42) -> 17834 | AT43: =AS43/E43 -> 0.039308086 | AU43: =+SUM(AU36:AU42) -> 34 | AV43: =+SUM(AV36:AV42) -> 51425 | AW43: =AV43/E43 -> 0.11334632 | AX43: =SUM(AX36:AX42) -> 121 | AY43: =SUM(AY36:AY42) -> #DIV/0! | AZ43: =SUM(AZ36:AZ42) -> 500 | BA43: =SUM(BA36:BA42) -> 150 | BB43: =SUM(BB36:BB42) -> 0 | BC43: =SUM(BC36:BC42) -> 0 | BD43: =+BC43/E43 -> 0 | BF43: =BE43/R43 -> 0 | BG43: =SUM(BG36:BG42) -> 0 | BH43: =BG43/R43 -> 0
A44: WEEK 5 | B44: Mon | C44: =C42+1 -> 46293 | D44: 73656.886 | G44: =IF(ISERROR(F44/E44),"",F44/E44) | H44: 136774 | I44: =IF(ISERROR(E44/D44),"",E44/D44) -> 0 | J44: =IF(ISERROR(E44/H44),"",(E44/H44))-1 -> -1 | K44: =IF($C44="","",IF(ISERROR(K42+D44),0,K42+D44)) -> 2875821 | L44: =IF(ISERROR(L42+E44),0,L42+E44) -> 2404186 | M44: =IF(ISERROR(M42+H44),0,M42+H44) -> 2724418 | N44: =IF(ISERROR(L44/K44),"",L44/K44) -> 0.83599987 | O44: =IF(ISERROR(L44/M44),"",L44/M44)-100% -> -0.11754143 | Y44: =IF(ISERROR(E44/Q44),"",E44/Q44) | Z44: =IF(ISERROR(E44/R44),"",E44/R44) | AA44: =IF(ISERROR(Q44/R44),"",Q44/R44) | AB44: =IF(ISERROR(R44/S44),"",R44/S44) | AC44: =IF(ISERROR(T44/R44),"",T44/R44) | AD44: =IF(ISERROR(U44/R44),"",U44/R44) | AE44: =IF(ISERROR(W44/R44),"",W44/R44) | AF44: =+V44/R44 -> #DIV/0! | AG44: =+X44/R44 -> #DIV/0! | AI44: =AH44/E44 -> #DIV/0! | AK44: =+AJ44/E44 -> #DIV/0! | AN44: =AM44/E44 -> #DIV/0! | AQ44: =AP44/E44 -> #DIV/0! | AT44: =AS44/E44 -> #DIV/0! | AW44: =AV44/E44 -> #DIV/0! | AY44: =AX44/R44 -> #DIV/0! | BD44: =+BC44/E44 -> #DIV/0! | BF44: =BE44/R44 -> #DIV/0! | BH44: =BG44/R44 -> #DIV/0!
B45: Tues | C45: =C44+1 -> 46294 | D45: 76859.359 | G45: =IF(ISERROR(F45/E45),"",F45/E45) | H45: 40077 | I45: =IF(ISERROR(E45/D45),"",E45/D45) -> 0 | J45: =IF(ISERROR(E45/H45),"",(E45/H45))-1 -> -1 | K45: =IF(C45="","",IF(ISERROR(K44+D45),0,K44+D45)) -> 2952680.4 | L45: =IF($C45="","",IF(ISERROR(L44+E45),0,L44+E45)) -> 2404186 | M45: =IF($C45="","",IF(ISERROR(M44+H45),0,M44+H45)) -> 2764495 | N45: =IF(ISERROR(L45/K45),"",L45/K45) -> 0.81423848 | O45: =IF(ISERROR(L45/M45),"",L45/M45)-100% -> -0.13033447 | Y45: =IF(ISERROR(E45/Q45),"",E45/Q45) | Z45: =IF(ISERROR(E45/R45),"",E45/R45) | AA45: =IF(ISERROR(Q45/R45),"",Q45/R45) | AB45: =IF(ISERROR(R45/S45),"",R45/S45) | AC45: =IF(ISERROR(T45/R45),"",T45/R45) | AD45: =IF(ISERROR(U45/R45),"",U45/R45) | AE45: =IF(ISERROR(W45/R45),"",W45/R45) | AF45: =+V45/R45 -> #DIV/0! | AG45: =+X45/R45 -> #DIV/0! | AI45: =AH45/E45 -> #DIV/0! | AK45: =+AJ45/E45 -> #DIV/0! | AN45: =AM45/E45 -> #DIV/0! | AQ45: =AP45/E45 -> #DIV/0! | AT45: =AS45/E45 -> #DIV/0! | AW45: =AV45/E45 -> #DIV/0! | AY45: =AX45/R45 -> #DIV/0! | BD45: =+BC45/E45 -> #DIV/0! | BF45: =BE45/R45 -> #DIV/0! | BH45: =BG45/R45 -> #DIV/0!
B46: Wed | C46: =C45+1 -> 46295 | D46: 76859.359 | G46: =IF(ISERROR(F46/E46),"",F46/E46) | H46: 95890 | I46: =IF(ISERROR(E46/D46),"",E46/D46) -> 0 | J46: =IF(ISERROR(E46/H46),"",(E46/H46))-1 -> -1 | K46: =IF(C46="","",IF(ISERROR(K45+D46),0,K45+D46)) -> 3029539.7 | L46: =IF($C46="","",IF(ISERROR(L45+E46),0,L45+E46)) -> 2404186 | M46: =IF($C46="","",IF(ISERROR(M45+H46),0,M45+H46)) -> 2860385 | N46: =IF(ISERROR(L46/K46),"",L46/K46) -> 0.79358127 | O46: =IF(ISERROR(L46/M46),"",L46/M46)-100% -> -0.15948867 | Y46: =IF(ISERROR(E46/Q46),"",E46/Q46) | Z46: =IF(ISERROR(E46/R46),"",E46/R46) | AA46: =IF(ISERROR(Q46/R46),"",Q46/R46) | AB46: =IF(ISERROR(R46/S46),"",R46/S46) | AC46: =IF(ISERROR(T46/R46),"",T46/R46) | AD46: =IF(ISERROR(U46/R46),"",U46/R46) | AE46: =IF(ISERROR(W46/R46),"",W46/R46) | AF46: =+V46/R46 -> #DIV/0! | AG46: =+X46/R46 -> #DIV/0! | AI46: =AH46/E46 -> #DIV/0! | AK46: =+AJ46/E46 -> #DIV/0! | AN46: =AM46/E46 -> #DIV/0! | AQ46: =AP46/E46 -> #DIV/0! | AT46: =AS46/E46 -> #DIV/0! | AW46: =AV46/E46 -> #DIV/0! | AY46: =AX46/R46 -> #DIV/0! | BD46: =+BC46/E46 -> #DIV/0! | BF46: =BE46/R46 -> #DIV/0! | BH46: =BG46/R46 -> #DIV/0!
B47: Thurs | C47: =C46+1 -> 46296 | G47: =IF(ISERROR(F47/E47),"",F47/E47) | I47: =IF(ISERROR(E47/D47),"",E47/D47) | J47: =IF(ISERROR(E47/H47),"",(E47/H47))-1 -> #VALUE! | K47: =IF(C47="","",IF(ISERROR(K46+D47),0,K46+D47)) -> 3029539.7 | L47: =IF($C47="","",IF(ISERROR(L46+E47),0,L46+E47)) -> 2404186 | M47: =IF($C47="","",IF(ISERROR(M46+H47),0,M46+H47)) -> 2860385 | N47: =IF(ISERROR(L47/K47),"",L47/K47) -> 0.79358127 | O47: =IF(ISERROR(L47/M47),"",L47/M47)-100% -> -0.15948867 | Y47: =IF(ISERROR(E47/Q47),"",E47/Q47) | Z47: =IF(ISERROR(E47/R47),"",E47/R47) | AA47: =IF(ISERROR(Q47/R47),"",Q47/R47) | AB47: =IF(ISERROR(R47/S47),"",R47/S47) | AC47: =IF(ISERROR(T47/R47),"",T47/R47) | AD47: =IF(ISERROR(U47/R47),"",U47/R47) | AE47: =IF(ISERROR(W47/R47),"",W47/R47) | AF47: =+V47/R47 -> #DIV/0! | AG47: 0 | AI47: =AH47/E47 -> #DIV/0! | AK47: =+AJ47/E47 -> #DIV/0! | AN47: =AM47/E47 -> #DIV/0! | AQ47: =AP47/E47 -> #DIV/0! | AT47: =AS47/E47 -> #DIV/0! | AW47: =AV47/E47 -> #DIV/0! | AY47: =AX47/R47 -> #DIV/0! | BD47: =+BC47/E47 -> #DIV/0! | BF47: =BE47/R47 -> #DIV/0! | BH47: =BG47/R47 -> #DIV/0!
B48: Fri | C48: =C47+1 -> 46297 | G48: =IF(ISERROR(F48/E48),"",F48/E48) | I48: =IF(ISERROR(E48/D48),"",E48/D48) | J48: =IF(ISERROR(E48/H48),"",(E48/H48))-1 -> #VALUE! | K48: =IF(C48="","",IF(ISERROR(K47+D48),0,K47+D48)) -> 3029539.7 | L48: =IF($C48="","",IF(ISERROR(L47+E48),0,L47+E48)) -> 2404186 | M48: =IF($C48="","",IF(ISERROR(M47+H48),0,M47+H48)) -> 2860385 | N48: =IF(ISERROR(L48/K48),"",L48/K48) -> 0.79358127 | O48: =IF(ISERROR(L48/M48),"",L48/M48)-100% -> -0.15948867 | Y48: =IF(ISERROR(E48/Q48),"",E48/Q48) | Z48: =IF(ISERROR(E48/R48),"",E48/R48) | AA48: =IF(ISERROR(Q48/R48),"",Q48/R48) | AB48: =IF(ISERROR(R48/S48),"",R48/S48) | AC48: =IF(ISERROR(T48/R48),"",T48/R48) | AD48: =IF(ISERROR(U48/R48),"",U48/R48) | AE48: =IF(ISERROR(W48/R48),"",W48/R48) | AF48: =+V48/R48 -> #DIV/0! | AG48: =+X48/R48 -> #DIV/0! | AI48: =AH48/E48 -> #DIV/0! | AK48: =+AJ48/E48 -> #DIV/0! | AN48: =AM48/E48 -> #DIV/0! | AQ48: =AP48/E48 -> #DIV/0! | AT48: =AS48/E48 -> #DIV/0! | AW48: =AV48/E48 -> #DIV/0! | AY48: =AX48/R48 -> #DIV/0! | BD48: =+BC48/E48 -> #DIV/0! | BF48: =BE48/R48 -> #DIV/0! | BH48: =BG48/R48 -> #DIV/0!
B49: Sat | C49: =C48+1 -> 46298 | G49: =IF(ISERROR(F49/E49),"",F49/E49) | I49: =IF(ISERROR(E49/D49),"",E49/D49) | J49: =IF(ISERROR(E49/H49),"",(E49/H49))-1 -> #VALUE! | K49: =IF(C49="","",IF(ISERROR(K48+D49),0,K48+D49)) -> 3029539.7 | L49: =IF($C49="","",IF(ISERROR(L48+E49),0,L48+E49)) -> 2404186 | M49: =IF($C49="","",IF(ISERROR(M48+H49),0,M48+H49)) -> 2860385 | N49: =IF(ISERROR(L49/K49),"",L49/K49) -> 0.79358127 | O49: =IF(ISERROR(L49/M49),"",L49/M49) -> 0.84051133 | Y49: =IF(ISERROR(E49/Q49),"",E49/Q49) | Z49: =IF(ISERROR(E49/R49),"",E49/R49) | AA49: =IF(ISERROR(Q49/R49),"",Q49/R49) | AB49: =IF(ISERROR(R49/S49),"",R49/S49) | AC49: =IF(ISERROR(T49/R49),"",T49/R49) | AD49: =IF(ISERROR(U49/R49),"",U49/R49) | AE49: =IF(ISERROR(W49/R49),"",W49/R49) | AF49: =+V49/R49 -> #DIV/0! | AG49: =+X49/R49 -> #DIV/0! | AI49: =AH49/E49 -> #DIV/0! | AK49: =+AJ49/E49 -> #DIV/0! | AN49: =AM49/E49 -> #DIV/0! | AQ49: =AP49/E49 -> #DIV/0! | AT49: =AS49/E49 -> #DIV/0! | AW49: =AV49/E49 -> #DIV/0! | AY49: =AX49/R49 -> #DIV/0! | BD49: =+BC49/E49 -> #DIV/0! | BF49: =BE49/R49 -> #DIV/0! | BH49: =BG49/R49 -> #DIV/0!
B50: Sun | C50: =C49+1 -> 46299 | G50: =IF(ISERROR(F50/E50),"",F50/E50) | I50: =IF(ISERROR(E50/D50),"",E50/D50) | J50: =IF(ISERROR(E50/H50),"",(E50/H50))-1 -> #VALUE! | K50: =IF(C50="","",IF(ISERROR(K49+D50),0,K49+D50)) -> 3029539.7 | L50: =IF($C50="","",IF(ISERROR(L49+E50),0,L49+E50)) -> 2404186 | M50: =IF($C50="","",IF(ISERROR(M49+H50),0,M49+H50)) -> 2860385 | N50: =IF(ISERROR(L50/K50),"",L50/K50) -> 0.79358127 | O50: =IF(ISERROR(L50/M50),"",L50/M50) -> 0.84051133 | Y50: =IF(ISERROR(E50/Q50),"",E50/Q50) | Z50: =IF(ISERROR(E50/R50),"",E50/R50) | AA50: =IF(ISERROR(Q50/R50),"",Q50/R50) | AB50: =IF(ISERROR(R50/S50),"",R50/S50) | AC50: =IF(ISERROR(T50/R50),"",T50/R50) | AD50: =IF(ISERROR(U50/R50),"",U50/R50) | AE50: =IF(ISERROR(W50/R50),"",W50/R50) | AF50: =+V50/R50 -> #DIV/0! | AG50: =+X50/R50 -> #DIV/0! | AI50: =AH50/E50 -> #DIV/0! | AK50: =+AJ50/E50 -> #DIV/0! | AN50: =AM50/E50 -> #DIV/0! | AQ50: =AP50/E50 -> #DIV/0! | AT50: =AS50/E50 -> #DIV/0! | AW50: =AV50/E50 -> #DIV/0! | AY50: =AX50/R50 -> #DIV/0! | BD50: =+BC50/E50 -> #DIV/0! | BF50: =BE50/R50 -> #DIV/0! | BH50: =BG50/R50 -> #DIV/0!
B51: Total | D51: =SUM(D44:D50) -> 227375.6 | E51: =SUM(E44:E50) -> 0 | F51: =SUM(F44:F50) -> 0 | G51: =IF(ISERROR(F51/E51),"",F51/E51) | H51: =SUM(H44:H50) -> 272741 | I51: =IF(ISERROR(E51/D51),"",E51/D51) -> 0 | J51: =IF(ISERROR(E51/H51),"",(E51/H51))-1 -> -1 | N51: =IF(ISERROR(L51/K51),"",L51/K51) | O51: =IF(ISERROR(L51/M51),"",L51/M51) | Q51: =SUM(Q44:Q50) -> 0 | R51: =SUM(R44:R50) -> 0 | S51: =SUM(S44:S50) -> 0 | T51: =SUM(T44:T50) -> 0 | U51: =SUM(U44:U50) -> 0 | V51: =SUM(V44:V50) -> 0 | W51: =SUM(W44:W50) -> 0 | X51: =SUM(X44:X50) -> 0 | Y51: =IF(ISERROR(E51/Q51),"",E51/Q51) | Z51: =IF(ISERROR(E51/R51),"",E51/R51) | AA51: =IF(ISERROR(Q51/R51),"",Q51/R51) | AB51: =IF(ISERROR(R51/S51),"",R51/S51) | AC51: =IF(ISERROR(T51/R51),"",T51/R51) | AD51: =IF(ISERROR(U51/R51),"",U51/R51) | AE51: =IF(ISERROR(W51/R51),"",W51/R51) | AF51: =+V51/R51 -> #DIV/0! | AG51: =+X51/R51 -> #DIV/0! | AH51: =SUM(AH44,AH45,AH46,AH47) -> 0 | AI51: =SUM(AI44,AI45,AI46,AI47) -> #DIV/0! | AJ51: =SUM(AJ44:AJ50) -> 0 | AK51: =SUM(AK44:AK50) -> #DIV/0! | AM51: =SUM(AM44:AM50) -> 0 | AN51: =SUM(AN44,AN45,AN46,AN47) -> #DIV/0! | AP51: =SUM(AP44:AP50) -> 0 | AS51: =SUM(AS44:AS50) -> 0 | AT51: =AS51/E51 -> #DIV/0! | AV51: =SUM(AV44:AV50) -> 0 | AW51: =AV51/E51 -> #DIV/0! | AX51: =SUM(AX44:AX50) -> 0 | AY51: =SUM(AY44:AY50) -> #DIV/0! | AZ51: =SUM(AZ44:AZ50) -> 0 | BA51: =SUM(BA44:BA50) -> 0 | BB51: =SUM(BB44:BB50) -> 0 | BC51: =SUM(BC44:BC50) -> 0 | BD51: =SUM(BD44:BD50) -> #DIV/0!
B52: Mon | I52: =IF(ISERROR(E52/D52),"",E52/D52) | J52: =IF(ISERROR(E52/H52),"",(E52/H52))-1 -> #VALUE! | K52: =K42+D52 -> 2802164.1 | L52: =L42+E52 -> 2404186 | M52: =M42+H52 -> 2587644 | N52: =IF(ISERROR(L52/K52),"",L52/K52) -> 0.85797472 | O52: =IF(ISERROR(L52/M52),"",L52/M52)-100% -> -0.070897697 | Y52: =IF(ISERROR(E52/Q52),"",E52/Q52) | Z52: =IF(ISERROR(E52/R52),"",E52/R52) | AA52: =IF(ISERROR(Q52/R52),"",Q52/R52) | AB52: =IF(ISERROR(R52/S52),"",R52/S52) | AC52: =IF(ISERROR(T52/R52),"",T52/R52) | AD52: =IF(ISERROR(U52/R52),"",U52/R52) | AE52: =IF(ISERROR(W52/R52),"",W52/R52) | AF52: =+V52/R52 -> #DIV/0! | AG52: =+X52/R52 -> #DIV/0! | AI52: =AH52/E52 -> #DIV/0! | AK52: =+AJ52/E52 -> #DIV/0! | AN52: =AM52/E52 -> #DIV/0! | AQ52: =AP52/E52 -> #DIV/0! | AT52: =AS52/E52 -> #DIV/0! | AW52: =AV52/E52 -> #DIV/0! | AY52: =AX52/R52 -> #DIV/0! | BD52: =+BC52/E52 -> #DIV/0! | BF52: =BE52/R52 -> #DIV/0! | BH52: =BG52/R52 -> #DIV/0!
B53: Total | D53: =D52 -> 0 | E53: =E52 -> 0 | F53: =F52 -> 0 | H53: =H52 -> 0 | Q53: =Q52 -> 0 | R53: =R52 -> 0 | S53: =S52 -> 0 | T53: =T52 -> 0 | U53: =U52 -> 0 | V53: =V52 -> 0 | W53: =W52 -> 0 | X53: =X52 -> 0 | ... AE53: =AE52 | AH53: =AH52 -> 0 | AJ53: =AJ52 -> 0 | AL53: =AL52 -> 0 | AM53: =AM52 -> 0 | AO53: =AO52 -> 0 | AP53: =AP52 -> 0 | AR53: =AR52 -> 0 | AS53: =AS52 -> 0 | AT53: =AS53/E53 -> #DIV/0! | AU53: =AU52 -> 0 | AV53: =AV52 -> 0 | AW53: =AV53/E53 -> #DIV/0! | AX53: =AX52 -> 0 | AY53: =SUM(AY46:AY52) -> #DIV/0! | AZ53: =AZ52 -> 0 | BA53: =BA52 -> 0 | BB53: =BB52 -> 0 | BC53: =BC52 -> 0 | BD53: =+BC53/E53 -> #DIV/0! | BE53: =BE52 -> 0 | BF53: =BE53/R53 -> #DIV/0! | BG53: =BG52 -> 0 | BH53: =BG53/R53 -> #DIV/0!
D54: =+SUM(D51,D35,D27,D19,D11,D43,D53) -> 3029539.7 | E54: =+SUM(E51,E35,E27,E19,E11,E43,E53) -> 2404186 | F54: =+SUM(F51,F35,F27,F19,F11,F43,F53) -> 0 | G54: =IF(ISERROR(F54/E54),"",F54/E54) -> 0 | H54: =+SUM(H51,H35,H27,H19,H11,H43,H53) -> 2860385 | I54: =IF(ISERROR(E54/D54),"",E54/D54) -> 0.79358127 | J54: =IF(ISERROR(E54/H54),"",(E54/H54)) -> 0.84051133 | K54: =IF(ISERROR(F54/I54),"",(F54/I54)) -> 0 | Q54: =+SUM(Q51,Q35,Q27,Q19,Q11,Q43,Q53) -> 2292 | R54: =+SUM(R51,R35,R27,R19,R11,R43,R53) -> 1021 | S54: =+SUM(S51,S35,S27,S19,S11,S43,S53) -> 6418 | T54: =+SUM(T51,T35,T27,T19,T11,T43,T53) -> 126 | U54: =+SUM(U51,U35,U27,U19,U11,U43,U53) -> 8 | V54: =+SUM(V51,V35,V27,V19,V11,V43,V53) -> 121 | W54: =+SUM(W51,W35,W27,W19,W11,W43,W53) -> 1 | X54: =+SUM(X51,X35,X27,X19,X11,X43,X53) -> 21 | Y54: =IF(ISERROR(E54/Q54),"",E54/Q54) -> 1048.9468 | Z54: =IF(ISERROR(E54/R54),"",E54/R54) -> 2354.7365 | AA54: =IF(ISERROR(Q54/R54),"",Q54/R54) -> 2.244858 | AB54: =IF(ISERROR(R54/S54),"",R54/S54) -> 0.15908383 | AC54: =IF(ISERROR(T54/R54),"",T54/R54) -> 0.12340842 | AD54: =IF(ISERROR(U54/R54),"",U54/R54) -> 0.0078354554 | AE54: =IF(ISERROR(W54/R54),"",W54/R54) -> 0.00097943193 | AF54: =+V54/R54 -> 0.11851126 | AG54: =+X54/R54 -> 0.020568071 | AH54: =+SUM(AH51,AH35,AH27,AH19,AH11,AH43,AH53) -> 15763 | AI54: =AH54/E54 -> 0.0065564811 | AJ54: =+SUM(AJ51,AJ35,AJ27,AJ19,AJ11,AJ43,AJ53) -> 14228 | AK54: =+AJ54/E54 -> 0.0059180113 | AL54: =+SUM(AL51,AL35,AL27,AL19,AL11,AL43,AL53) -> 30 | AM54: =+SUM(AM51,AM35,AM27,AM19,AM11,AM43,AM53) -> 102517 | AN54: =AM54/E54 -> 0.042641044 | AO54: =+SUM(AO51,AO35,AO27,AO19,AO11,AO43,AO53) -> 52 | AP54: =+SUM(AP51,AP35,AP27,AP19,AP11,AP43,AP53) -> 87307 | AQ54: =AP54/E54 -> 0.036314578 | AR54: =+SUM(AR51,AR35,AR27,AR19,AR11,AR43,AR53) -> 30 | AS54: =+SUM(AS51,AS35,AS27,AS19,AS11,AS43,AS53) -> 97774 | AT54: =AS54/E54 -> 0.040668234 | AU54: =+SUM(AU51,AU35,AU27,AU19,AU11,AU43,AU53) -> 168 | AV54: =+SUM(AV51,AV35,AV27,AV19,AV11,AV43,AV53) -> 219214 | AW54: =AV54/E54 -> 0.091180133 | AX54: =+SUM(AX51,AX35,AX27,AX19,AX11,AX43,AX53) -> 542 | AY54: =AX54/R54 -> 0.53085211 | AZ54: =+SUM(AZ51,AZ35,AZ27,AZ19,AZ11,AZ43,AZ53) -> 2400 | BA54: =+SUM(BA51,BA35,BA27,BA19,BA11,BA43,BA53) -> 1500 | BB54: =+SUM(BB51,BB35,BB27,BB19,BB11,BB43,BB53) -> 6 | BC54: =+SUM(BC51,BC35,BC27,BC19,BC11,BC43,BC53) -> 46834 | BD54: =+BC54/E54 -> 0.01948019 | BE54: =+SUM(BE51,BE35,BE27,BE19,BE11,BE43,BE53) -> 3 | BF54: =BE54/R54 -> 0.0029382958 | BG54: =+SUM(BG51,BG35,BG27,BG19,BG11,BG43,BG53) -> 0 | BH54: =BG54/R54 -> 0
D55: =D54-E54 -> 625353.74 | S55: =R54/S54 -> 0.15908383
R56: =1342+32 -> 1374
AA57: =AA56+Z54 -> 2354.7365
A58: Last | B58: NA | C58: NA | D58: 575241.94 | E58: 356580 | F58: 0 | G58: 0 | H58: 539541 | I58: 0.61987831 | J58: 0.66089509 | K58: 0 | L58: 0 | M58: 0 | N58: 0 | O58: 0 | P58: 0 | Q58: 341 | R58: 161 | S58: 1126 | T58: 35 | U58: 5 | V58: 10 | W58: 0 | X58: 24 | Y58: =IF(ISERROR(E58/Q58),"",E58/Q58) -> 1045.6891 | Z58: =IF(ISERROR(E58/R58),"",E58/R58) -> 2214.7826 | AA58: =IF(ISERROR(Q58/R58),"",Q58/R58) -> 2.1180124 | AB58: =IF(ISERROR(R58/S58),"",R58/S58) -> 0.14298401 | AC58: =IF(ISERROR(T58/R58),"",T58/R58) -> 0.2173913 | AD58: =IF(ISERROR(U58/R58),"",U58/R58) -> 0.031055901 | AE58: =IF(ISERROR(W58/R58),"",W58/R58) -> 0 | AF58: =+V58/R58 -> 0.062111801 | AG58: =+X58/R58 -> 0.14906832 | AH58: 6401 | AI58: =AH58/E58 -> 0.017951091 | AJ58: 3468 | AK58: =+AJ58/E58 -> 0.0097257277 | AM58: 25893 | AN58: =AM58/E58 -> 0.072614841 | AP58: 50448 | AQ58: =AP58/E58 -> 0.14147737 | AS58: 47039 | AT58: =AS58/E58 -> 0.1319171 | AV58: 46609 | AW58: =AV58/E58 -> 0.1307112 | AX58: 81 | AY58: =AX58/R58 -> 0.50310559 | AZ58: 750 | BA58: 200 | BB58: 2 | BC58: 4443 | BD58: #DIV/0!
A59: Week1 | B59: NA | C59: NA | D59: =SUM(D9:D10)+D58 -> 575241.94 | E59: =SUM(E9:E10)+E58 -> 356580 | F59: =SUM(F9:F10)+F58 -> 0 | G59: =SUM(G9:G10)+G58 -> 0 | H59: =SUM(H9:H10)+H58 -> 539541 | I59: =SUM(I9:I10)+I58 -> 0.61987831 | J59: =SUM(J9:J10)+J58 -> #VALUE! | K59: =SUM(K9:K10)+K58 -> 0 | ... X59: =SUM(X9:X10)+X58 -> 24 | Y59: =IF(ISERROR(E59/Q59),"",E59/Q59) -> 1045.6891 | Z59: =IF(ISERROR(E59/R59),"",E59/R59) -> 2214.7826 | AA59: =IF(ISERROR(Q59/R59),"",Q59/R59) -> 2.1180124 | AB59: =IF(ISERROR(R59/S59),"",R59/S59) -> 0.14298401 | AC59: =IF(ISERROR(T59/R59),"",T59/R59) -> 0.2173913 | AD59: =IF(ISERROR(U59/R59),"",U59/R59) -> 0.031055901 | AE59: =IF(ISERROR(W59/R59),"",W59/R59) -> 0 | AF59: =+V59/R59 -> 0.062111801 | AG59: =+X59/R59 -> 0.14906832 | AH59: =SUM(AH9:AH10)+AH58 -> 6401 | AI59: =AH59/E59 -> 0.017951091 | AJ59: =SUM(AJ9:AJ10)+AJ58 -> 3468 | AK59: =+AJ59/E59 -> 0.0097257277 | AM59: =SUM(AM9:AM10)+AM58 -> 25893 | AN59: =AM59/E59 -> 0.072614841 | AP59: =SUM(AP9:AP10)+AP58 -> 50448 | AQ59: =AP59/E59 -> 0.14147737 | AS59: =SUM(AS9:AS10)+AS58 -> 47039 | AT59: =AS59/E59 -> 0.1319171 | AV59: =SUM(AV9:AV10)+AV58 -> 46609 | AW59: =AV59/E59 -> 0.1307112 | AX59: =SUM(AX9:AX10)+AX58 -> 81 | AY59: =AX59/R59 -> 0.50310559 | AZ59: =SUM(AZ9:AZ10)+AZ58 -> 750 | BA59: =SUM(BA9:BA10)+BA58 -> 200 | BB59: =SUM(BB9:BB10)+BB58 -> 2 | BC59: =SUM(BC9:BC10)+BC58 -> 4443 | BD59: =SUM(BD9:BD10)+BD58 -> #DIV/0!
A60: Week2 | B60: NA | C60: NA | D60: =D19 -> 534813.04 | E60: =E19 -> 461014 | F60: =F19 -> 0 | G60: =G19 -> 0 | H60: =H19 -> 604984 | I60: =I19 -> 0.86200964 | J60: =J19 -> -0.23797324 | K60: =K19 -> 0 | ... X60: =X19 -> 1 | Y60: =IF(ISERROR(E60/Q60),"",E60/Q60) -> 1047.7591 | Z60: =IF(ISERROR(E60/R60),"",E60/R60) -> 2388.6736 | AA60: =IF(ISERROR(Q60/R60),"",Q60/R60) -> 2.2797927 | AB60: =IF(ISERROR(R60/S60),"",R60/S60) -> 0.14926527 | AC60: =IF(ISERROR(T60/R60),"",T60/R60) -> 0.11917098 | AD60: =IF(ISERROR(U60/R60),"",U60/R60) -> 0.010362694 | AE60: =IF(ISERROR(W60/R60),"",W60/R60) -> 0 | AF60: =+V60/R60 -> 0.10880829 | AG60: =+X60/R60 -> 0.0051813472 | AH60: =AH19 -> 5197 | AI60: =AH60/E60 -> 0.011272977 | AJ60: =AJ19 -> 2438 | AK60: =+AJ60/E60 -> 0.0052883427 | AM60: =AM19 -> 34750 | AN60: =AM60/E60 -> 0.07537732 | AP60: =AP19 -> 11367 | AQ60: =AP60/E60 -> 0.024656518 | AS60: =AS19 -> 37444 | AT60: =AS60/E60 -> 0.081220961 | AV60: =AV19 -> 33636 | AW60: =AV60/E60 -> 0.072960908 | AX60: =AX19 -> 96 | AY60: =AX60/R60 -> 0.49740933 | AZ60: =AZ19 -> 500 | BA60: =BA19 -> 440 | BB60: =BB19 -> 1 | BC60: =BC19 -> 7794 | BD60: =BD19 -> 0.016906211
A61: Week3 | B61: NA | C61: NA | D61: =D27 -> 749378.75 | E61: =E27 -> 741019 | F61: =F27 -> 0 | G61: =G27 -> 0 | H61: =H27 -> 620690 | I61: =I27 -> 0.98884442 | J61: =J27 -> 0.19386328 | K61: =K27 -> 0 | ... X61: =X27 -> 0 | Y61: =IF(ISERROR(E61/Q61),"",E61/Q61) -> 1064.6825 | Z61: =IF(ISERROR(E61/R61),"",E61/R61) -> 2344.9968 | AA61: =IF(ISERROR(Q61/R61),"",Q61/R61) -> 2.2025316 | AB61: =IF(ISERROR(R61/S61),"",R61/S61) -> 0.16213443 | AC61: =IF(ISERROR(T61/R61),"",T61/R61) -> 0.094936709 | AD61: =IF(ISERROR(U61/R61),"",U61/R61) -> 0.0094936709 | AE61: =IF(ISERROR(W61/R61),"",W61/R61) -> 0 | AF61: =+V61/R61 -> 0.10443038 | AG61: =+X61/R61 -> 0 | AH61: =AH27 -> 6528 | AI61: =AH61/E61 -> 0.0088094907 | AJ61: =AJ27 -> 3614 | AK61: =+AJ61/E61 -> 0.0048770679 | AM61: =AM27 -> 41672 | AN61: =AM61/E61 -> 0.056236075 | AP61: =AP27 -> 11027 | AQ61: =AP61/E61 -> 0.01488086 | AS61: =AS27 -> 8845 | AT61: =AS61/E61 -> 0.011936266 | AV61: =AV27 -> 46811 | AW61: =AV61/E61 -> 0.06317112 | AX61: =AX27 -> 153 | AY61: =AX61/R61 -> 0.48417722 | AZ61: =AZ27 -> 700 | BA61: =BA27 -> 550 | BB61: =BB27 -> 3 | BC61: =BC27 -> 36844 | BD61: =BD27 -> 0.049720722
A62: Week4 | B62: NA | C62: NA | D62: =D35 -> 752581.23 | E62: =E35 -> 748455 | F62: =F35 -> 0 | G62: =G35 -> 0 | H62: =H35 -> 599489 | I62: =I35 -> 0.99451723 | J62: =J35 -> 0.2484883 | K62: =K35 -> 0 | ... X62: =X35 -> 13 | Y62: =IF(ISERROR(E62/Q62),"",E62/Q62) -> 1063.1463 | Z62: =IF(ISERROR(E62/R62),"",E62/R62) -> 2554.4539 | AA62: =IF(ISERROR(Q62/R62),"",Q62/R62) -> 2.4027304 | AB62: =IF(ISERROR(R62/S62),"",R62/S62) -> 0.15316257 | AC62: =IF(ISERROR(T62/R62),"",T62/R62) -> 0.11604096 | AD62: =IF(ISERROR(U62/R62),"",U62/R62) -> 0.0068259386 | AE62: =IF(ISERROR(W62/R62),"",W62/R62) -> 0.0034129693 | AF62: =+V62/R62 -> 0.16723549 | AG62: =+X62/R62 -> 0.044368601 | AH62: =AH35 -> 2539 | AI62: =AH62/E62 -> 0.0033923215 | AJ62: =AJ35 -> 3896 | AK62: =+AJ62/E62 -> 0.0052053898 | AM62: =AM35 -> 16115 | AN62: =AM62/E62 -> 0.021531021 | AP62: =AP35 -> 37790 | AQ62: =AP62/E62 -> 0.050490677 | AS62: =AS35 -> 33651 | AT62: =AS62/E62 -> 0.044960619 | AV62: =AV35 -> 87342 | AW62: =AV62/E62 -> 0.11669639 | AX62: =AX35 -> 172 | AY62: =AX62/R62 -> 0.58703072 | AZ62: =AZ35 -> 700 | BA62: =BA35 -> 360 | BB62: =BB35 -> 2 | BC62: =BC35 -> 2196 | BD62: =BD35 -> 0.0029340441
A63: Week5 | B63: NA | C63: NA | D63: =D43 -> 765391.12 | E63: =E43 -> 453698 | F63: =F43 -> 0 | G63: =G43 -> 0 | H63: =H43 -> 762481 | I63: =I43 -> 0.59276622 | J63: =J43 -> -0.4049714 | K63: =K43 -> 0 | ... X63: =X43 -> 7 | Y63: =IF(ISERROR(E63/Q63),"",E63/Q63) -> 1003.7566 | Z63: =IF(ISERROR(E63/R63),"",E63/R63) -> 2071.6804 | AA63: =IF(ISERROR(Q63/R63),"",Q63/R63) -> 2.0639269 | AB63: =IF(ISERROR(R63/S63),"",R63/S63) -> 0.17339667 | AC63: =IF(ISERROR(T63/R63),"",T63/R63) -> 0.17808219 | AD63: =IF(ISERROR(U63/R63),"",U63/R63) -> 0.00456621 | AE63: =IF(ISERROR(W63/R63),"",W63/R63) -> 0 | AF63: =+V63/R63 -> 0.082191781 | AG63: =+X63/R63 -> 0.03196347 | AH63: =AH43 -> 1499 | AI63: =AH63/E63 -> 0.0033039599 | AJ63: =AJ43 -> 4280 | AK63: =+AJ63/E63 -> 0.009433588 | AM63: =AM43 -> 9980 | AN63: =AM63/E63 -> 0.021997011 | AP63: =AP43 -> 27123 | AQ63: =AP63/E63 -> 0.059782058 | AS63: =AS43 -> 17834 | AT63: =AS63/E63 -> 0.039308086 | AV63: =AV43 -> 51425 | AW63: =AV63/E63 -> 0.11334632 | AX63: =AX43 -> 121 | AY63: =AX63/R63 -> 0.55251142 | AZ63: =AZ43 -> 500 | BA63: =BA43 -> 150 | BB63: =BB43 -> 0 | BC63: =BC43 -> 0 | BD63: =BD43 -> 0
A64: Week6 | B64: NA | C64: NA
A66: G/D | E66: =E61/E60-1 -> 0.60736767 | Q66: =Q62/Q61-1 -> 0.011494253 | R66: =R62/R61-1 -> -0.07278481 | S66: =S62/S61-1 -> -0.018471011 | T66: =T62/T61-1 -> 0.13333333 | U66: =U62/U61-1 -> -0.33333333 | V66: =V62/V61-1 -> 0.48484848 | W66: =W62/W61-1 -> #DIV/0! | X66: =X62/X61-1 -> #DIV/0! | ... AB66: =AB62/AB61-1 -> -0.05533591
H68: =E18/1.1 -> 0

Sheet MSG 
A1: Store | B1: VEGAS | I1: Date | J1: Retail | K1: Retail Accum Tgt | L1: Net Play | M1: Net play Accum Tgt
A2: Date- | B2: =TODAY()-0 -> 46291 | C2: =B2+1 -> 46292 | I2: 46266 | J2: 73656.886 | K2: =J2 -> 73656.886 | L2: 4597.4185 | M2: =L2 -> 4597.4185
A3: MONTH TRGT - | B3: =DSR!D54 -> 3029539.7 | I3: =I2+1 -> 46267 | J3: 76859.359 | K3: =K2+J3 -> 150516.25 | L3: 4760.6694 | M3: =M2+L3 -> 9358.0879
A4: TARGET- | B4: =VLOOKUP(B2,DSR!C8:D52,2,0) -> 176136.03 | I4: =I3+1 -> 46268 | J4: 89669.252 | K4: =K3+J4 -> 240185.5 | L4: 5336.5905 | M4: =M3+L4 -> 14694.678
A5: SALE- | B5: =IFERROR(VLOOKUP(B2,DSR!C9:E54,3,0),0) -> 0 | I5: =I4+1 -> 46269 | J5: 128098.93 | K5: =K4+J5 -> 368284.43 | L5: 8061.591 | M5: =M4+L5 -> 22756.269
A6: FF- | B6: =VLOOKUP(B2,DSR!C8:S52,17,0) -> 0 | I6: =I5+1 -> 46270 | J6: 166528.61 | K6: =K5+J6 -> 534813.04 | L6: 10551.494 | M6: =M5+L6 -> 33307.763
A7: BILL- | B7: =VLOOKUP(B2,DSR!C8:R52,16,0) -> 0 | I7: =I6+1 -> 46271 | J7: 166528.61 | K7: =K6+J7 -> 701341.65 | L7: 11801.484 | M7: =M6+L7 -> 45109.247
A8: UNIT- | B8: =IFERROR(VLOOKUP(B2,DSR!C9:Q54,15,0),0) -> 0 | I8: =I7+1 -> 46272 | J8: 73656.886 | K8: =K7+J8 -> 774998.54 | L8: 4504.142 | M8: =M7+L8 -> 49613.389
A9: UPT- | B9: =VLOOKUP(B2,DSR!C9:AA52,25,0) | I9: =I8+1 -> 46273 | J9: 76859.359 | K9: =K8+J9 -> 851857.9 | L9: 4713.2701 | M9: =M8+L9 -> 54326.659
A10: ATV- | B10: =VLOOKUP(B2,DSR!C9:Z52,24,0) | I10: =I9+1 -> 46274 | J10: 76859.359 | K10: =K9+J10 -> 928717.26 | L10: 4730.4354 | M10: =M9+L10 -> 59057.095
A11: AUV- | B11: =VLOOKUP(B2,DSR!C9:Y52,23,0) | I11: =I10+1 -> 46275 | J11: 86466.779 | K11: =K10+J11 -> 1015184 | L11: 5265.6039 | M11: =M10+L11 -> 64322.699
A12: CONV%- | B12: =VLOOKUP('MSG '!B2,DSR!C9:AB52,26,0) | I12: =I11+1 -> 46276 | J12: 96074.199 | K12: =K11+J12 -> 1111258.2 | L12: 6387.6675 | M12: =M11+L12 -> 70710.366
I13: =I12+1 -> 46277 | J13: 169731.09 | K13: =K12+J13 -> 1280989.3 | L13: 11555.449 | M13: =M12+L13 -> 82265.815
A14: MTD TGT- | B14: =VLOOKUP(B2,DSR!C9:K52,9,0) -> 2626028.1 | I14: =I13+1 -> 46278 | J14: 169731.09 | K14: =K13+J14 -> 1450720.4 | L14: 11783.432 | M14: =M13+L14 -> 94049.247
A15: MTD SALE- | B15: =DSR!E54 -> 2404186 | I15: =I14+1 -> 46279 | J15: 73656.886 | K15: =K14+J15 -> 1524377.3 | L15: 5196.8316 | M15: =M14+L15 -> 99246.079
A16: MTD SALE%- | B16: =B15/B14 -> 0.91552181 | I16: =I15+1 -> 46280 | J16: 76859.359 | K16: =K15+J16 -> 1601236.7 | L16: 4642.688 | M16: =M15+L16 -> 103888.77
A17: MTD FF- | B17: =DSR!S54 -> 6418 | I17: =I16+1 -> 46281 | J17: 76859.359 | K17: =K16+J17 -> 1678096 | L17: 4779.251 | M17: =M16+L17 -> 108668.02
A18: MTD BILL- | B18: =DSR!R54 -> 1021 | I18: =I17+1 -> 46282 | J18: 89669.252 | K18: =K17+J18 -> 1767765.3 | L18: 5428.7639 | M18: =M17+L18 -> 114096.78
A19: MTD QTY- | B19: =DSR!Q54 -> 2292 | I19: =I18+1 -> 46283 | J19: 96074.199 | K19: =K18+J19 -> 1863839.5 | L19: 6239.3847 | M19: =M18+L19 -> 120336.17
A20: MTD UPT- | B20: =DSR!AA54 -> 2.244858 | I20: =I19+1 -> 46284 | J20: 169731.09 | K20: =K19+J20 -> 2033570.5 | L20: 12016.311 | M20: =M19+L20 -> 132352.48
A21: MTD ATV- | B21: =DSR!Z54 -> 2354.7365 | I21: =I20+1 -> 46285 | J21: 169731.09 | K21: =K20+J21 -> 2203301.6 | L21: 11786.877 | M21: =M20+L21 -> 144139.35
A22: MTD AUV- | B22: =DSR!Y54 -> 1048.9468 | I22: =I21+1 -> 46286 | J22: 73656.886 | K22: =K21+J22 -> 2276958.5 | L22: 4504.142 | M22: =M21+L22 -> 148643.5
A23: MTD CONV%- | B23: =DSR!AB54 -> 0.15908383 | I23: =I22+1 -> 46287 | J23: 76859.359 | K23: =K22+J23 -> 2353817.9 | L23: 4713.2701 | M23: =M22+L23 -> 153356.77
I24: =I23+1 -> 46288 | J24: 76859.359 | K24: =K23+J24 -> 2430677.2 | L24: 4779.251 | M24: =M23+L24 -> 158136.02
A25: ATVD SALE- | B25: =VLOOKUP(B2,DSR!C9:AH52,32,0) -> 0 | I25: =I24+1 -> 46289 | J25: 89669.252 | K25: =K24+J25 -> 2520346.5 | L25: 5428.7639 | M25: =M24+L25 -> 163564.78
A26: ATVD QTY- | B26: =VLOOKUP(B2,DSR!C9:U52,19,0) -> 0 | I26: =I25+1 -> 46290 | J26: 96074.199 | K26: =K25+J26 -> 2616420.7 | L26: 6239.3847 | M26: =M25+L26 -> 169804.17
A27: ATVD CONTRI%- | B27: =VLOOKUP(B2,DSR!C9:AI52,33,0) -> #DIV/0! | I27: =I26+1 -> 46291 | J27: 176136.03 | K27: =K26+J27 -> 2792556.7 | L27: 11996.078 | M27: =M26+L27 -> 181800.24
A28: MTD ATVD CONTRI%- | B28: =DSR!AI54 -> 0.0065564811 | I28: =I27+1 -> 46292 | J28: 176136.03 | K28: =K27+J28 -> 2968692.8 | L28: 11530.929 | M28: =M27+L28 -> 193331.17
I29: =I28+1 -> 46293 | J29: 73656.886 | K29: =K28+J29 -> 3042349.6 | L29: 4504.142 | M29: =M28+L29 -> 197835.31
A30: HOT SPOT SALE- | B30: =VLOOKUP(B2,DSR!C9:AS52,43,0) -> 0 | I30: =I29+1 -> 46294 | J30: 76859.359 | K30: =K29+J30 -> 3119209 | L30: 4713.2701 | M30: =M29+L30 -> 202548.58
A31: HOT SPOT %- | B31: =VLOOKUP(B2,DSR!C9:AT52,44,0) -> #DIV/0! | I31: =I30+1 -> 46295 | J31: 76859.359 | K31: =K30+J31 -> 3196068.4 | L31: 4802.5022 | M31: =M30+L31 -> 207351.09
A32: MTD HOTSPOT %- | B32: =DSR!AT54 -> 0.040668234 | I32: =I31+1 -> 46296 | K32: =K31+J32 -> 3196068.4 | M32: =M31+L32 -> 207351.09
J33: =SUM(J2:J32) -> 3196068.4 | L33: =SUM(L2:L32) -> 207351.09
A34: SELF DEMO SALE- | B34: =VLOOKUP(B2,DSR!C9:AP52,40,0) -> 0 | J34: =+J33-J7 -> 3029539.7
A35: SELF DEMO %- | B35: =VLOOKUP(B2,DSR!C9:AQ52,41,0) -> #DIV/0! | J35: =+J34-B15 -> 625353.74
A36: MTD SELF DEMO %- | B36: =DSR!AQ54 -> 0.036314578
A38: CORE- | B38: =VLOOKUP(B2,DSR!C9:AM52,37,0) -> 0
A39: CORE %- | B39: =VLOOKUP(B2,DSR!C9:AN52,38,0) -> #DIV/0!
A40: MTD CORE SALE- | B40: =DSR!AM54 -> 102517
A41: MTD CORE DEMO%- | B41: =DSR!AN54 -> 0.042641044
A43: MII SALE - | B43: =VLOOKUP(B2,DSR!C9:AV52,46,0) -> 0
A44: MII SALE %- | B44: =VLOOKUP(B2,DSR!C9:AW52,47,0) -> #DIV/0!
A45: MTD MII SALE- | B45: =DSR!AV54 -> 219214
A46: MTD MII SALE %- | B46: =DSR!AW54 -> 0.091180133
A48: BATTERY- | B48: =VLOOKUP(B2,DSR!C9:T52,18,0) -> 0
A49: BATTERY ATTACH%- | B49: =VLOOKUP(B2,DSR!C9:AC52,27,0)
A50: MTD BATTERY ATTACH%- | B50: =DSR!AC54 -> 0.12340842
A52: BUBBLE STKS- | B52: =VLOOKUP(B2,DSR!C9:X52,22,0) -> 0
A53: BUBBLE STKS ATTACH%- | B53: =VLOOKUP(B2,DSR!C9:AG52,31,0) -> #DIV/0!
A54: MTD BUBBLE STKS ATTACH%- | B54: =DSR!AG54 -> 0.020568071
A56: MULTI BILL TRGT- | B56: 0.6
A57: MULTI BILL - | B57: =VLOOKUP(B2,DSR!C9:AX52,48,0) -> 0
A58: MULTI BILL %- | B58: =VLOOKUP(B2,DSR!C9:AY52,49,0) -> #DIV/0!
A60: LOYALTY- | B60: =VLOOKUP(B2,DSR!C9:V52,20,0) -> 0
A61: LOYALTY %- | B61: =VLOOKUP(B2,DSR!C8:AF52,30,0) -> #DIV/0!
A62: MTD LOYALTY- | B62: =DSR!V54 -> 121
A63: MTD LOYALTY%- | B63: =DSR!AF54 -> 0.11851126
A65: RED CARD- | B65: =VLOOKUP(B2,DSR!C9:W52,21,0) -> 0
A66: MTD RED CARD- | B66: =DSR!W54 -> 1
A68: MTD LAST YR SALE- | B68: =VLOOKUP(B2,DSR!C9:M52,11,0) -> 2425559
A69: LY SALE- | B69: =VLOOKUP(B2,DSR!C9:H52,6,0) -> 71229
A70: LFL%- | B70: =VLOOKUP(B2,DSR!C9:O52,13,0) -> -0.008811577
A72: TOMORROW TRGT- | B72: =VLOOKUP(C2,I2:J34,2,0) -> 176136.03
A73: NET PLAY TGT- | B73: =VLOOKUP(C2,I1:L33,4,0) -> 11530.929
A75: TELECALLING TRGT- | B75: =VLOOKUP(B2,DSR!C9:AZ52,50,0) -> 0
A76: NO OF CALLS- | B76: =VLOOKUP(B2,DSR!C9:BA52,51,0) -> 0
A77: TELECALLING SALE- | B77: =VLOOKUP(B2,DSR!C9:BC52,53,0) -> 0
A78: TELECALLING BILLS- | B78: =VLOOKUP(B2,DSR!C9:BB52,52,0) -> 0
A79: IN STORE SALE- | B79: 0
A80: IN STORE BILL- | B80: 0
A81: HOME DELIVERY SALE- | B81: 0
A82: HOME DELIVERY BILL- | B82: 0
A83: MTD CALL- | B83: =DSR!BA54 -> 1500
A84: MTD BILL- | B84: 0
A85: MTD SALE- | B85: =DSR!BC54 -> 46834
A87: Net Play Target- | B87: =Netplay!Q4 -> 11996.078
A88: Net Play Sale- | B88: =Netplay!R4 -> 0
A89: MTD Net Play Target- | B89: 104639
A90: MTD Net Play Sale- | B90: =Netplay!R5 -> 47200
K95: Sep@2026

Sheet Format
D1: Qty | E1: FOOTFALL | F1: Bills
A2: Sale
A3: KPI | B3: Qty | C3: SALE VALUE
A4: BUBBLE ST | B4: =SUMIF($A$17:$A$23001,"BUBBLE ST",$E$17:$E$23001) -> 0 | C4: =SUMIF($A$17:$A$23001,"BUBBLE ST",$F$17:$F$23001) -> 0 | D4: =+C4/$D$3 -> #DIV/0! | H4: =C4/B4 -> #DIV/0!
A5: ATVD | B5: =SUMIF($A$17:$A$23001,"ATVD",$E$17:$E$23001) -> 0 | C5: =SUMIF($A$17:$A$23001,"ATVD",$F$17:$F$23001) -> 0 | D5: =+C5/$D$3 -> #DIV/0! | E5: UPT | F5: =+D2/F2 -> #DIV/0! | H5: =C5/B5 -> #DIV/0!
A6: CORE DEMO | B6: =SUMIF($A$17:$A$23001,"CORE DEMO",$E$17:$E$23001) -> 2 | C6: =SUMIF($A$17:$A$23001,"CORE DEMO",$F$17:$F$23001) -> 1859.81 | D6: =+C6/$D$3 -> #DIV/0! | E6: Batteries Mix% | F6: =+B12/F2 -> #DIV/0! | H6: =C6/B6 -> 929.905
A7: HOTSPOTS | B7: =SUMIF($A$17:$A$23001,"HOTSPOTS",$E$17:$E$23001) -> 1 | C7: =SUMIF($A$17:$A$23001,"HOTSPOTS",$F$17:$F$23001) -> 1799 | D7: =+C7/$D$3 -> #DIV/0! | E7: Conv% | F7: =+F2/E2 -> #DIV/0! | H7: =C7/B7 -> 1799
A8: SELF DEMO | B8: =SUMIF($A$17:$A$23001,"SELF DEMO",$E$17:$E$23001) -> 4 | C8: =SUMIF($A$17:$A$23001,"SELF DEMO",$F$17:$F$23001) -> 5309.36 | D8: =+C8/$D$3 -> #DIV/0! | H8: =C8/B8 -> 1327.34
A9: LOYALTY | B9: =SUMIF($A$17:$A$23001,"LOYALTY",$E$17:$E$23001) -> 0 | C9: =SUMIF($A$17:$A$23001,"LOYALTY",$F$17:$F$23001) -> 0 | D9: =+C9/$D$3 -> #DIV/0! | H9: =C9/B9 -> #DIV/0!
A10: GIFT CARD | B10: =SUMIF($A$17:$A$23001,"GIFT CARD",$E$17:$E$23001) -> 0 | C10: =SUMIF($A$17:$A$23001,"GIFT CARD",$F$17:$F$23001) -> 0 | D10: =+C10/$D$3 -> #DIV/0! | H10: =C10/B10 -> #DIV/0!
A11: PASSPORT | B11: =SUMIF($A$17:$A$23001,"PASSPORT",$E$17:$E$23001) -> 0 | C11: =SUMIF($A$17:$A$23001,"PASSPORT",$F$17:$F$23001) -> 0 | D11: =+C11/$D$3 -> #DIV/0! | H11: =C11/B11 -> #DIV/0!
A12: BATTERY | B12: =SUMIF($A$17:$A$23001,"BATTERY",$E$17:$E$23001) -> 11 | C12: =SUMIF($A$17:$A$23001,"BATTERY",$F$17:$F$23001) -> 1141.93 | D12: =+C12/$D$3 -> #DIV/0! | H12: =C12/B12 -> 103.81182
A13: NON BIS | B13: =SUMIF($A$17:$A$23001,"NON BIS",$E$17:$E$23001) -> 0 | C13: =SUMIF($A$17:$A$23001,"NON BIS",$F$17:$F$23001) -> 0 | D13: =+C13/$D$3 -> #DIV/0! | H13: =C13/B13 -> #DIV/0!
A14: TOT BAGS | B14: =SUMIF($A$17:$A$23001,"TOT BAGS",$E$17:$E$23001) -> 0 | C14: =SUMIF($A$17:$A$23001,"TOT BAGS",$F$17:$F$23001) -> 0 | D14: =+C14/$D$3 -> #DIV/0! | H14: =C14/B14 -> #DIV/0!
A15: MII | B15: =SUMIF($A$17:$A$23001,"MII",$E$17:$E$23001) -> 7 | C15: =SUMIF($A$17:$A$23001,"MII",$F$17:$F$23001) -> 8580.57 | H15: =C15/B15 -> 1225.7957
A16: Level | B16: Article | C16: GTIN | D16: Article description | E16: Qty | F16: Value
A17: 0 | B17: 494230081 | C17: 8904406234392 | D17: NE YOUREKA JUMBO CRAFT JAR | E17: =IFERROR(VLOOKUP(C17,Pivot!A:B,2,0),0) -> 0 | F17: =IFERROR(VLOOKUP(C17,Pivot!A:C,3,0),0) -> 0
A18: ATVD | B18: 494229811 | C18: 8906006063846 | D18: NE YOUREKA 3IN1 CREATORS COMBO | E18: =IFERROR(VLOOKUP(C18,Pivot!A:B,2,0),0) -> 0 | F18: =IFERROR(VLOOKUP(C18,Pivot!A:C,3,0),0) -> 0
A19: ATVD | B19: 493174331 | C19: 8905450228047 | D19: NE YK GO FROGGY GOO | E19: =IFERROR(VLOOKUP(C19,Pivot!A:B,2,0),0) -> 0 | F19: =IFERROR(VLOOKUP(C19,Pivot!A:C,3,0),0) -> 0
A20: ATVD | B20: 494229839 | C20: 8905450758810 | D20: NE YK CREATE CRAZY INVENTIONS | E20: =IFERROR(VLOOKUP(C20,Pivot!A:B,2,0),0) -> 0 | F20: =IFERROR(VLOOKUP(C20,Pivot!A:C,3,0),0) -> 0
A21: ATVD | B21: 492409151 | C21: 8904391800343 | D21: NE ULTIMATE INSTA GLAM KIT | E21: =IFERROR(VLOOKUP(C21,Pivot!A:B,2,0),0) -> 0 | F21: =IFERROR(VLOOKUP(C21,Pivot!A:C,3,0),0) -> 0
A22: ATVD | B22: 493663599 | C22: 9789353769147 | D22: NE SPACE ENCYCLOPEDIA | E22: =IFERROR(VLOOKUP(C22,Pivot!A:B,2,0),0) -> 0 | F22: =IFERROR(VLOOKUP(C22,Pivot!A:C,3,0),0) -> 0
A23: ATVD | B23: 493663599 | C23: 9788119749027 | D23: NE SPACE ENCYCLOPEDIA | E23: =IFERROR(VLOOKUP(C23,Pivot!A:B,2,0),0) -> 0 | F23: =IFERROR(VLOOKUP(C23,Pivot!A:C,3,0),0) -> 0
A24: ATVD | B24: 491603944 | C24: 5015353612157 | D24: NE SOCCER RED ATV | E24: =IFERROR(VLOOKUP(C24,Pivot!A:B,2,0),0) -> 0 | F24: =IFERROR(VLOOKUP(C24,Pivot!A:C,3,0),0) -> 0
A25: ATVD | B25: 491603943 | C25: 5015353612140 | D25: NE SOCCER BLACK ATV | E25: =IFERROR(VLOOKUP(C25,Pivot!A:B,2,0),0) -> 0 | F25: =IFERROR(VLOOKUP(C25,Pivot!A:C,3,0),0) -> 0
A26: ATVD | B26: 491603991 | C26: 5015353612935 | D26: NE PVC WHITE SOCCER #5 | E26: =IFERROR(VLOOKUP(C26,Pivot!A:B,2,0),0) -> 0 | F26: =IFERROR(VLOOKUP(C26,Pivot!A:C,3,0),0) -> 0
A27: ATVD | B27: 491603984 | C27: 5015353612829 | D27: NE PVC RED SOCCER #5 | E27: =IFERROR(VLOOKUP(C27,Pivot!A:B,2,0),0) -> 0 | F27: =IFERROR(VLOOKUP(C27,Pivot!A:C,3,0),0) -> 0
A28: ATVD | B28: 491603983 | C28: 5015353612812 | D28: NE PVC BLACK SOCCER #5 | E28: =IFERROR(VLOOKUP(C28,Pivot!A:B,2,0),0) -> 0 | F28: =IFERROR(VLOOKUP(C28,Pivot!A:C,3,0),0) -> 0
A29: ATVD | B29: 492409149 | C29: 8904391800367 | D29: NE METALLIC HAIR AND NAIL STUDIO | E29: =IFERROR(VLOOKUP(C29,Pivot!A:B,2,0),0) -> 0 | F29: =IFERROR(VLOOKUP(C29,Pivot!A:C,3,0),0) -> 0
... A22241: Battery | B22241: 490843456 | C22241: 8901691008332 | D22241: EVEREADY AA 2115 ULT | E22241: =IFERROR(VLOOKUP(C22241,Pivot!A:B,2,0),0) -> 0 | F22241: =IFERROR(VLOOKUP(C22241,Pivot!A:C,3,0),0) -> 0

Sheet Pivot
A3: Row Labels | B3: Sum of QTY | C3: Sum of NET
A4: 74299018060 | B4: 3 | C4: 2472.03
A5: 195166109145 | B5: 1 | C5: 460
A6: 606314674076 | B6: 1 | C6: 899
A7: 714686709903 | B7: 1 | C7: 899
A8: 791115722870 | B8: 2 | C8: 2211.36
A9: 4501517003431 | B9: 1 | C9: 1999
A10: 5000394121171 | B10: 9 | C10: 931.93
A11: 8904279505919 | B11: 1 | C11: 1499
A12: 8904301767278 | B12: 1 | C12: 1799
A13: (blank)
A14: 791115722887 | B14: 1 | C14: 1299
A15: 8904279505902 | B15: 1 | C15: 1052.69
A16: 27084120134 | B16: 3 | C16: 537
A17: 616985378463 | B17: 2 | C17: 1548
A18: 8902491018682 | B18: 1 | C18: 1999
A19: 5010993652587 | B19: 1 | C19: 823.97
A20: 8904477700338 | B20: 1 | C20: 1615.9
A21: 8906173940988 | B21: 1 | C21: 1995
A22: 8904279504646 | B22: 1 | C22: 561
A23: 8905672238206 | B23: 1 | C23: 946.28
A24: 5702017812410 | B24: 1 | C24: 2151.72
A25: 8908013692385 | B25: 1 | C25: 499
... A81: 8904520801470 | B81: 1 | C81: 3571.02
A82: Grand Total | B82: 100 | C82: 96738.65

Sheet Sale
A1: TXNID | B1: STORENO | C1: TRANSACTIONTYPE | D1: RECEIPTNO | E1: TRANSDATE | F1: ARTICLESINRECEIPT | G1: BARCODE | H1: QTY | I1: RECEIPTPRICE | J1: PROMOTION | K1: DISCOUNT | L1: TOTALDISCOUNT | M1: NET | N1: TAX | O1: Tax% | P1: ARTICLEDESC | Q1: CASHIER | R1: STATUS | S1: SALESMANCODE | T1: Order_Type | U1: PRODUCT_TYPE
A2: 1 | B2: TLX5 | C2: SALE | D2: TLX5102000125092026 | E2: 46290.476 | F2: 3 | G2: 27084120134 | H2: 1 | I2: 179 | J2: 0 | K2: 0 | L2: 0 | M2: 179 | N2: 8.52 | O2: 5 | P2: NE HW BASIC CAR ASST | Q2: 50170981 | R2: COMPLETED | U2: GnG
A3: 1 | B3: TLX5 | C3: SALE | D3: TLX5102000125092026 | E3: 46290.476 | F3: 3 | G3: 27084120134 | H3: 1 | I3: 179 | J3: 0 | K3: 0 | L3: 0 | M3: 179 | N3: 8.52 | O3: 5 | P3: NE HW BASIC CAR ASST | Q3: 50170981 | R3: COMPLETED | U3: GnG
A4: 1 | B4: TLX5 | C4: SALE | D4: TLX5102000125092026 | E4: 46290.476 | F4: 3 | G4: 27084120134 | H4: 1 | I4: 179 | J4: 0 | K4: 0 | L4: 0 | M4: 179 | N4: 8.52 | O4: 5 | P4: NE HW BASIC CAR ASST | Q4: 50170981 | R4: COMPLETED | U4: GnG
A5: 1 | B5: TLX5 | C5: SALE | D5: TLX5102000125092026 | E5: 46290.476 | F5: 3 | G5: 3467452077306 | H5: 1 | I5: 399 | J5: 0 | K5: 0 | L5: 0 | M5: 399 | N5: 19 | O5: 5 | P5: NE MJT VOLVO CONSTRU | Q5: 50170981 | R5: COMPLETED | S5: 50195439 | U5: GnG
A6: 1 | B6: TLX5 | C6: SALE | D6: TLX5102000125092026 | E6: 46290.476 | F6: 3 | G6: 194735279272 | H6: 1 | I6: 599 | J6: 0 | K6: 0 | L6: 0 | M6: 599 | N6: 28.52 | O6: 5 | P6: NE MBX WORKING RIGS | Q6: 50170981 | R6: COMPLETED | S6: 50195439 | U6: GnG
A7: 2 | B7: TLX5 | C7: SALE | D7: TLX5102000225092026 | E7: 46290.481 | F7: 3 | G7: 5702017816289 | H7: 1 | I7: 6399 | J7: 0 | K7: 0 | L7: 0 | M7: 6399 | N7: 304.72 | O7: 5 | P7: NE 42205 CHEVROLET C | Q7: 50170981 | R7: COMPLETED | S7: 50188930 | U7: GnG
A8: 3 | B8: TLX5 | C8: SALE | D8: TLX5102000325092026 | E8: 46290.484 | F8: 3 | G8: 4501517003431 | H8: 1 | I8: 1999 | J8: 0 | K8: 0 | L8: 0 | M8: 1999 | N8: 0 | O8: 0 | P8: NE Shifu OrbootAu | Q8: 50170981 | R8: COMPLETED | U8: GnG
A9: 3 | B9: TLX5 | C9: SALE | D9: TLX5102000325092026 | E9: 46290.484 | F9: 3 | G9: 8908017463011 | H9: 1 | I9: 999 | J9: -149.85 | K9: 0 | L9: -149.85 | M9: 849.15 | N9: 40.44 | O9: 5 | P9: NE YOUREKA GALAXY GL | Q9: 50170981 | R9: COMPLETED | S9: 50195439 | U9: GnG
A10: 5 | B10: TLX5 | C10: SALE | D10: TLX5102000525092026 | E10: 46290.53 | F10: 3 | G10: 194735358748 | H10: 1 | I10: 299 | J10: 0 | K10: 0 | L10: 0 | M10: 299 | N10: 14.24 | O10: 5 | P10: NE HW AUTOMOTIVE ASS | Q10: 50157523 | R10: COMPLETED | S10: 50188930 | U10: GnG
A11: 5 | B11: TLX5 | C11: SALE | D11: TLX5102000525092026 | E11: 46290.53 | F11: 3 | G11: 194735358755 | H11: 1 | I11: 299 | J11: 0 | K11: 0 | L11: 0 | M11: 299 | N11: 14.24 | O11: 5 | P11: NE HW AUTOMOTIVE ASS | Q11: 50157523 | R11: COMPLETED | S11: 50188930 | U11: GnG
A12: 6 | B12: TLX5 | C12: SALE | D12: TLX5102000625092026 | E12: 46290.531 | F12: 3 | G12: 8905672547537 | H12: 1 | I12: 1499 | J12: 0 | K12: 0 | L12: 0 | M12: 1499 | N12: 228.66 | O12: 18 | P12: E SS DOLPHIN CONCERT | Q12: 50157523 | R12: COMPLETED | S12: 50188930 | U12: GnG
A13: 6 | B13: TLX5 | C13: SALE | D13: TLX5102000625092026 | E13: 46290.531 | F13: 3 | G13: 494500285 | H13: 1 | I13: 299 | J13: 0 | K13: 0 | L13: 0 | M13: 299 | N13: 45.62 | O13: 18 | P13: NE REDCARD TOTE BAG | Q13: 50157523 | R13: COMPLETED | U13: GnG
A14: 6 | B14: TLX5 | C14: SALE | D14: TLX5102000625092026 | E14: 46290.531 | F14: 3 | G14: 194735284931 | H14: 1 | I14: 449 | J14: 0 | K14: 0 | L14: 0 | M14: 449 | N14: 21.38 | O14: 5 | P14: NE MT MBX SKYBUSTERS | Q14: 50157523 | R14: COMPLETED | S14: 50188930 | U14: GnG
A15: 7 | B15: TLX5 | C15: SALE | D15: TLX5102000725092026 | E15: 46290.534 | F15: 3 | G15: 8902491018682 | H15: 1 | I15: 1999 | J15: 0 | K15: 0 | L15: 0 | M15: 1999 | N15: 95.2 | O15: 5 | P15: NE PICKLEBALL PADDLE | Q15: 50157523 | R15: COMPLETED | S15: 50195439 | U15: GnG
A16: 7 | B16: TLX5 | C16: SALE | D16: TLX5102000725092026 | E16: 46290.534 | F16: 3 | G16: 194735293858 | H16: 1 | I16: 2799 | J16: 0 | K16: 0 | L16: 0 | M16: 2799 | N16: 133.28 | O16: 5 | P16: NE HW THE HOT ONES C | Q16: 50157523 | R16: COMPLETED | S16: 50195439 | U16: GnG
A17: 8 | B17: TLX5 | C17: SALE | D17: TLX5102000825092026 | E17: 46290.546 | F17: 3 | G17: 761847400797 | H17: 1 | I17: 699 | J17: 0 | K17: 0 | L17: 0 | M17: 699 | N17: 106.62 | O17: 18 | P17: NE PARTY PURSE | Q17: 50157523 | R17: COMPLETED | S17: 50188930 | U17: GnG
A18: 10 | B18: TLX5 | C18: SALE | D18: TLX5102001025092026 | E18: 46290.581 | F18: 3 | G18: 616985378463 | H18: 1 | I18: 749 | J18: 0 | K18: 0 | L18: 0 | M18: 749 | N18: 35.66 | O18: 5 | P18: NE MIRADA 22CM ELEPH | Q18: 50157523 | R18: COMPLETED | S18: 50195907 | U18: GnG
A19: 11 | B19: TLX5 | C19: SALE | D19: TLX5102001125092026 | E19: 46290.587 | F19: 3 | G19: 8904279505919 | H19: 1 | I19: 1499 | J19: 0 | K19: 0 | L19: 0 | M19: 1499 | N19: 71.38 | O19: 5 | P19: NE MAGNETOPIA DESIGN | Q19: 50157523 | R19: COMPLETED | U19: GnG
A20: 12 | B20: TLX5 | C20: SALE | D20: TLX5102001225092026 | E20: 46290.606 | F20: 3 | G20: 5013317453709 | H20: 1 | I20: 750 | J20: -562.5 | K20: 0 | L20: -562.5 | M20: 187.5 | N20: 8.92 | O20: 5 | P20: NE DUNLOP NYLON SHUT | Q20: 50157523 | R20: COMPLETED | S20: 50151682 | U20: GnG
A21: 13 | B21: TLX5 | C21: SALE | D21: TLX5102001325092026 | E21: 46290.632 | F21: 3 | G21: 8904279518032 | H21: 1 | I21: 999 | J21: -250 | K21: 0 | L21: -250 | M21: 749 | N21: 35.66 | O21: 5 | P21: NE CLASSICS POP REVE | Q21: 50157523 | R21: COMPLETED | S21: 50000002 | U21: GnG
A22: 13 | B22: TLX5 | C22: SALE | D22: TLX5102001325092026 | E22: 46290.632 | F22: 3 | G22: 8904279510449 | H22: 1 | I22: 999 | J22: -250 | K22: 0 | L22: -250 | M22: 749 | N22: 35.66 | O22: 5 | P22: NE PUN INTENDED | Q22: 50157523 | R22: COMPLETED | S22: 50000002 | U22: GnG
A23: 15 | B23: TLX5 | C23: SALE | D23: TLX5102001525092026 | E23: 46290.645 | F23: 3 | G23: 491603774 | H23: 1 | I23: 649 | J23: 0 | K23: 0 | L23: 0 | M23: 649 | N23: 30.9 | O23: 5 | P23: NE WBB PANDA BEAR 20 | Q23: 50157523 | R23: COMPLETED | U23: GnG
A24: 16 | B24: TLX5 | C24: SALE | D24: TLX5102001625092026 | E24: 46290.648 | F24: 3 | G24: 761847400179 | H24: 1 | I24: 349 | J24: 0 | K24: 0 | L24: 0 | M24: 349 | N24: 16.62 | O24: 5 | P24: ORGANIC COTTON TRIPL | Q24: 50157523 | R24: COMPLETED | S24: 50000001 | U24: GnG
A25: 16 | B25: TLX5 | C25: SALE | D25: TLX5102001625092026 | E25: 46290.648 | F25: 3 | G25: 761847400551 | H25: 1 | I25: 399 | J25: 0 | K25: 0 | L25: 0 | M25: 399 | N25: 19 | O25: 5 | P25: ORGANIC COTTON TRIPL | Q25: 50157523 | R25: COMPLETED | S25: 50000003 | U25: GnG
A26: 18 | B26: TLX5 | C26: SALE | D26: TLX5102001825092026 | E26: 46290.674 | F26: 3 | G26: 74299018060 | H26: 1 | I26: 899 | J26: 0 | K26: 0 | L26: 0 | M26: 899 | N26: 42.8 | O26: 5 | P26: HW FIVECAR GIFT PACK | Q26: 50157523 | R26: COMPLETED | S26: 50000003 | U26: GnG
A27: 19 | B27: TLX5 | C27: SALE | D27: TLX5102001925092026 | E27: 46290.678 | F27: 3 | G27: 5000394121171 | H27: 1 | I27: 120 | J27: 0 | K27: 0 | L27: 0 | M27: 120 | N27: 18.3 | O27: 18 | P27: AA 2 CB | Q27: 50157523 | R27: COMPLETED | U27: GnG
A28: 19 | B28: TLX5 | C28: SALE | D28: TLX5102001925092026 | E28: 46290.678 | F28: 3 | G28: 8904301767278 | H28: 1 | I28: 1799 | J28: 0 | K28: 0 | L28: 0 | M28: 1799 | N28: 274.42 | O28: 18 | P28: E KS YELLOW FISHING | Q28: 50157523 | R28: COMPLETED | S28: 50188930 | U28: GnG
A29: 2 | B29: TLX5 | C29: SALE | D29: TLX5104000225092026 | E29: 46290.678 | F29: 3 | G29: 8904432234113 | H29: 1 | I29: 999 | J29: 0 | K29: 0 | L29: 0 | M29: 999 | N29: 47.58 | O29: 5 | P29: NE DISNEY BOG FOOT S | Q29: 50170981 | R29: COMPLETED | S29: 50195439 | U29: GnG
A30: 20 | B30: TLX5 | C30: SALE | D30: TLX5102002025092026 | E30: 46290.688 | F30: 3 | G30: 8904279505902 | H30: 1 | I30: 1405 | J30: -352.31 | K30: 0 | L30: -352.31 | M30: 1052.69 | N30: 50.12 | O30: 5 | P30: NE MAGNETOPIA DESIGN | Q30: 50157523 | R30: COMPLETED | U30: GnG
A31: 20 | B31: TLX5 | C31: SALE | D31: TLX5102002025092026 | E31: 46290.688 | F31: 3 | G31: 194735307708 | H31: 1 | I31: 549 | J31: -137.66 | K31: 0 | L31: -137.66 | M31: 411.34 | N31: 19.58 | O31: 5 | P31: NE HW MT GITD AST | Q31: 50157523 | R31: COMPLETED | S31: 50195907 | U31: GnG
A32: 21 | B32: TLX5 | C32: SALE | D32: TLX5102002125092026 | E32: 46290.701 | F32: 3 | G32: 494500285 | H32: 1 | I32: 1999 | J32: -462.07 | K32: 0 | L32: -462.07 | M32: 1536.93 | N32: 234.44 | O32: 18 | P32: NE REDCARD TOTE BAG | Q32: 50157523 | R32: COMPLETED | U32: GnG
A33: 21 | B33: TLX5 | C33: SALE | D33: TLX5102002125092026 | E33: 46290.701 | F33: 3 | G33: 5702017824208 | H33: 1 | I33: 6649 | J33: -1536.93 | K33: 0 | L33: -1536.93 | M33: 5112.07 | N33: 243.44 | O33: 5 | P33: NE LEGO 76327 IRON M | Q33: 50157523 | R33: COMPLETED | S33: 50000003 | U33: GnG
A34: 22 | B34: TLX5 | C34: SALE | D34: TLX5102002225092026 | E34: 46290.704 | F34: 3 | G34: 5702017879956 | H34: 1 | I34: 1799 | J34: -500 | K34: 0 | L34: -500 | M34: 1299 | N34: 61.86 | O34: 5 | P34: NE LEGO 31173 TROPIC | Q34: 50157523 | R34: COMPLETED | S34: 50000002 | U34: GnG
A35: 24 | B35: TLX5 | C35: SALE | D35: TLX5102002425092026 | E35: 46290.71 | F35: 3 | G35: 8908013692385 | H35: 1 | I35: 499 | J35: 0 | K35: 0 | L35: 0 | M35: 499 | N35: 23.76 | O35: 5 | P35: NE PLAYSHIFU SOLAR S | Q35: 50157523 | R35: COMPLETED | S35: 50000001 | U35: GnG
A36: 25 | B36: TLX5 | C36: SALE | D36: TLX5102002525092026 | E36: 46290.715 | F36: 3 | G36: 5010993652587 | H36: 1 | I36: 1099 | J36: -275.03 | K36: 0 | L36: -275.03 | M36: 823.97 | N36: 39.24 | O36: 5 | P36: MARVEL OLYMPUS 9.5IN | Q36: 50157523 | R36: COMPLETED | S36: 50201915 | U36: GnG
A37: 25 | B37: TLX5 | C37: SALE | D37: TLX5102002525092026 | E37: 46290.715 | F37: 3 | G37: 74299018060 | H37: 1 | I37: 899 | J37: -224.97 | K37: 0 | L37: -224.97 | M37: 674.03 | N37: 32.1 | O37: 5 | P37: HW FIVECAR GIFT PACK | Q37: 50157523 | R37: COMPLETED | S37: 50201915 | U37: GnG
A38: 26 | B38: TLX5 | C38: SALE | D38: TLX5102002625092026 | E38: 46290.72 | F38: 3 | G38: 5000394121263 | H38: 1 | I38: 100 | J38: 0 | K38: 0 | L38: 0 | M38: 100 | N38: 15.26 | O38: 18 | P38: AAA 2 CB | Q38: 50157523 | R38: COMPLETED | U38: GnG
A39: 26 | B39: TLX5 | C39: SALE | D39: TLX5102002625092026 | E39: 46290.72 | F39: 3 | G39: 5000394121171 | H39: 1 | I39: 110 | J39: 0 | K39: 0 | L39: 0 | M39: 110 | N39: 16.78 | O39: 18 | P39: AA 2 CB | Q39: 50157523 | R39: COMPLETED | U39: GnG
A40: 26 | B40: TLX5 | C40: SALE | D40: TLX5102002625092026 | E40: 46290.72 | F40: 3 | G40: 5000394121263 | H40: 1 | I40: 110 | J40: 0 | K40: 0 | L40: 0 | M40: 110 | N40: 16.78 | O40: 18 | P40: AAA 2 CB | Q40: 50157523 | R40: COMPLETED | U40: GnG
A41: 26 | B41: TLX5 | C41: SALE | D41: TLX5102002625092026 | E41: 46290.72 | F41: 3 | G41: 887961672039 | H41: 1 | I41: 399 | J41: 0 | K41: 0 | L41: 0 | M41: 399 | N41: 19 | O41: 5 | P41: NE MATCHBOX BASIC CA | Q41: 50157523 | R41: COMPLETED | S41: 50195439 | U41: GnG
A42: 26 | B42: TLX5 | C42: SALE | D42: TLX5102002625092026 | E42: 46290.72 | F42: 3 | G42: 887961672039 | H42: 1 | I42: 399 | J42: 0 | K42: 0 | L42: 0 | M42: 399 | N42: 19 | O42: 5 | P42: NE MATCHBOX BASIC CA | Q42: 50157523 | R42: COMPLETED | S42: 50195439 | U42: GnG
A43: 27 | B43: TLX5 | C43: SALE | D43: TLX5102002725092026 | E43: 46290.724 | F43: 3 | G43: 194735358762 | H43: 1 | I43: 299 | J43: -74.86 | K43: 0 | L43: -74.86 | M43: 224.14 | N43: 10.68 | O43: 5 | P43: NE HW AUTOMOTIVE ASS | Q43: 50157523 | R43: COMPLETED | S43: 50195439 | U43: GnG
A44: 27 | B44: TLX5 | C44: SALE | D44: TLX5102002725092026 | E44: 46290.724 | F44: 3 | G44: 8904520801227 | H44: 1 | I44: 699 | J44: -175.01 | K44: 0 | L44: -175.01 | M44: 523.99 | N44: 24.96 | O44: 5 | P44: NE 4IN FIG MVL AVN I | Q44: 50157523 | R44: COMPLETED | S44: 50195439 | U44: GnG
A45: 27 | B45: TLX5 | C45: SALE | D45: TLX5102002725092026 | E45: 46290.724 | F45: 3 | G45: 5010996295545 | H45: 1 | I45: 999 | J45: -250.13 | K45: 0 | L45: -250.13 | M45: 748.87 | N45: 35.66 | O45: 5 | P45: NE TRA GEN PROJECT S | Q45: 50157523 | R45: COMPLETED | S45: 50195439 | U45: GnG
A46: 28 | B46: TLX5 | C46: SALE | D46: TLX5102002825092026 | E46: 46290.739 | F46: 3 | G46: 8905672238206 | H46: 1 | I46: 1099 | J46: -152.72 | K46: 0 | L46: -152.72 | M46: 946.28 | N46: 45.06 | O46: 5 | P46: NE GEMSTONE DIG QUES | Q46: 50157523 | R46: COMPLETED | S46: 50201915 | U46: GnG
A47: 28 | B47: TLX5 | C47: SALE | D47: TLX5102002825092026 | E47: 46290.739 | F47: 3 | G47: 5702017812410 | H47: 1 | I47: 2499 | J47: -347.28 | K47: 0 | L47: -347.28 | M47: 2151.72 | N47: 102.46 | O47: 5 | P47: NE LEGO 60451 EMERGE | Q47: 50157523 | R47: COMPLETED | S47: 50201915 | U47: GnG
A48: 29 | B48: TLX5 | C48: SALE | D48: TLX5102002925092026 | E48: 46290.748 | F48: 3 | G48: 5000394121171 | H48: 1 | I48: 110 | J48: -21.08 | K48: 0 | L48: -21.08 | M48: 88.92 | N48: 13.56 | O48: 18 | P48: AA 2 CB | Q48: 50157523 | R48: COMPLETED | U48: GnG
A49: 29 | B49: TLX5 | C49: SALE | D49: TLX5102002925092026 | E49: 46290.748 | F49: 3 | G49: 8904477700338 | H49: 1 | I49: 1999 | J49: -383.1 | K49: 0 | L49: -383.1 | M49: 1615.9 | N49: 246.5 | O49: 18 | P49: E CLASSIC TRAIN SET | Q49: 50157523 | R49: COMPLETED | U49: GnG
A50: 32 | B50: TLX5 | C50: SALE | D50: TLX5102003225092026 | E50: 46290.775 | F50: 3 | G50: 791115722887 | H50: 1 | I50: 1299 | J50: 0 | K50: 0 | L50: 0 | M50: 1299 | N50: 198.16 | O50: 18 | P50: E HM BELLA WALKING C | Q50: 50157523 | R50: COMPLETED | U50: GnG
A51: 32 | B51: TLX5 | C51: SALE | D51: TLX5102003225092026 | E51: 46290.775 | F51: 3 | G51: 791115722870 | H51: 1 | I51: 1299 | J51: 0 | K51: 0 | L51: 0 | M51: 1299 | N51: 198.16 | O51: 18 | P51: E HM CASPER WALKING | Q51: 50157523 | R51: COMPLETED | U51: GnG
A52: 3 | B52: TLX5 | C52: SALE | D52: TLX5104000325092026 | E52: 46290.779 | F52: 3 | G52: 8906057367771 | H52: 1 | I52: 1099 | J52: -219.8 | K52: 0 | L52: -219.8 | M52: 879.2 | N52: 41.86 | O52: 5 | P52: NE MAPOLOGY WORLD CH | Q52: 50170981 | R52: COMPLETED | S52: 50000002 | U52: GnG
A53: 3 | B53: TLX5 | C53: SALE | D53: TLX5104000325092026 | E53: 46290.779 | F53: 3 | G53: 8904279509726 | H53: 1 | I53: 749 | J53: -149.8 | K53: 0 | L53: -149.8 | M53: 599.2 | N53: 28.54 | O53: 5 | P53: NE SIZZLE | Q53: 50170981 | R53: COMPLETED | S53: 50195439 | U53: GnG
A54: 3 | B54: TLX5 | C54: SALE | D54: TLX5104000325092026 | E54: 46290.779 | F54: 3 | G54: 8904279522329 | H54: 1 | I54: 999 | J54: -199.8 | K54: 0 | L54: -199.8 | M54: 799.2 | N54: 38.06 | O54: 5 | P54: NE SKM MY ARTSY STAS | Q54: 50170981 | R54: COMPLETED | S54: 50195439 | U54: GnG
A55: 33 | B55: TLX5 | C55: SALE | D55: TLX5102003325092026 | E55: 46290.805 | F55: 3 | G55: 761847400322 | H55: 1 | I55: 299 | J55: 0 | K55: 0 | L55: 0 | M55: 299 | N55: 14.24 | O55: 5 | P55: ORGANIC COTTON TRIPL | Q55: 50157523 | R55: COMPLETED | S55: 50195439 | U55: GnG
A56: 33 | B56: TLX5 | C56: SALE | D56: TLX5102003325092026 | E56: 46290.805 | F56: 3 | G56: 195166109145 | H56: 1 | I56: 460 | J56: 0 | K56: 0 | L56: 0 | M56: 460 | N56: 21.9 | O56: 5 | P56: HASBRO NERF ALPHA ST | Q56: 50157523 | R56: COMPLETED | S56: 50195439 | U56: GnG
A57: 33 | B57: TLX5 | C57: SALE | D57: TLX5102003325092026 | E57: 46290.805 | F57: 3 | G57: 4501517003455 | H57: 1 | I57: 499 | J57: 0 | K57: 0 | L57: 0 | M57: 499 | N57: 23.76 | O57: 5 | P57: NE PLAYSHIFU AQUATIC | Q57: 50157523 | R57: COMPLETED | S57: 50195439 | U57: GnG
A58: 34 | B58: TLX5 | C58: SALE | D58: TLX5102003425092026 | E58: 46290.812 | F58: 3 | G58: 8901383140012 | H58: 1 | I58: 199 | J58: 0 | K58: 0 | L58: 0 | M58: 199 | N58: 9.48 | O58: 5 | P58: KIDDY STAR LINKS | Q58: 50157523 | R58: COMPLETED | S58: 50195439 | U58: GnG
A59: 34 | B59: TLX5 | C59: SALE | D59: TLX5102003425092026 | E59: 46290.812 | F59: 3 | G59: 714686709903 | H59: 1 | I59: 899 | J59: 0 | K59: 0 | L59: 0 | M59: 899 | N59: 42.8 | O59: 5 | P59: NE MIR 35 CM BUNNY P | Q59: 50157523 | R59: COMPLETED | S59: 50195439 | U59: GnG
A60: 4 | B60: TLX5 | C60: SALE | D60: TLX5104000425092026 | E60: 46290.83 | F60: 3 | G60: 8909409260942 | H60: 1 | I60: 1599 | J60: 0 | K60: 0 | L60: 0 | M60: 1599 | N60: 243.92 | O60: 18 | P60: E HM WIRELESS WALKIE | Q60: 50170981 | R60: COMPLETED | S60: 50000002 | U60: GnG
A61: 4 | B61: TLX5 | C61: SALE | D61: TLX5104000425092026 | E61: 46290.83 | F61: 3 | G61: 8904279504660 | H61: 1 | I61: 561 | J61: 0 | K61: 0 | L61: 0 | M61: 561 | N61: 26.72 | O61: 5 | P61: NE MAGICAL SCRATCH A | Q61: 50170981 | R61: COMPLETED | U61: GnG
A62: 4 | B62: TLX5 | C62: SALE | D62: TLX5104000425092026 | E62: 46290.83 | F62: 3 | G62: 8904279504646 | H62: 1 | I62: 561 | J62: 0 | K62: 0 | L62: 0 | M62: 561 | N62: 26.72 | O62: 5 | P62: NE MAGICAL SCRATCH D | Q62: 50170981 | R62: COMPLETED | U62: GnG
A63: 36 | B63: TLX5 | C63: SALE | D63: TLX5102003625092026 | E63: 46290.834 | F63: 3 | G63: 606314674076 | H63: 1 | I63: 899 | J63: 0 | K63: 0 | L63: 0 | M63: 899 | N63: 42.8 | O63: 5 | P63: NE MIR 32CM SITTING | Q63: 50157523 | R63: COMPLETED | S63: 50151682 | U63: GnG
A64: 5 | B64: TLX5 | C64: REFUND | D64: TLX5104000525092026 | E64: 46290.835 | F64: 3 | G64: 8904520800701 | H64: -1 | I64: -1199 | J64: 0 | K64: 0 | L64: 0 | M64: -1199 | N64: -57.1 | O64: 5 | P64: NE MVL ROLE PLAY MAS | Q64: 50170981 | R64: COMPLETED | S64: 50000000 | U64: GnG
A65: 6 | B65: TLX5 | C65: SALE | D65: TLX5104000625092026 | E65: 46290.838 | F65: 3 | G65: 5000394121171 | H65: 1 | I65: 110 | J65: 0 | K65: 0 | L65: 0 | M65: 110 | N65: 16.78 | O65: 18 | P65: AA 2 CB | Q65: 50170981 | R65: COMPLETED | U65: GnG
A66: 6 | B66: TLX5 | C66: SALE | D66: TLX5104000625092026 | E66: 46290.838 | F66: 3 | G66: 5000394121171 | H66: 1 | I66: 110 | J66: 0 | K66: 0 | L66: 0 | M66: 110 | N66: 16.78 | O66: 18 | P66: AA 2 CB | Q66: 50170981 | R66: COMPLETED | U66: GnG
A67: 6 | B67: TLX5 | C67: SALE | D67: TLX5104000625092026 | E67: 46290.838 | F67: 3 | G67: 5292982076288 | H67: 1 | I67: 1499 | J67: 0 | K67: 0 | L67: 0 | M67: 1499 | N67: 71.38 | O67: 5 | P67: NE FIFA FB WHT S5 PP | Q67: 50170981 | R67: COMPLETED | S67: 50201915 | U67: GnG
A68: 6 | B68: TLX5 | C68: SALE | D68: TLX5104000625092026 | E68: 46290.838 | F68: 3 | G68: 8906173940988 | H68: 1 | I68: 1995 | J68: 0 | K68: 0 | L68: 0 | M68: 1995 | N68: 304.32 | O68: 18 | P68: E PIANO BLACK XL 49K | Q68: 50170981 | R68: COMPLETED | S68: 50201915 | U68: GnG
A69: 6 | B69: TLX5 | C69: SALE | D69: TLX5104000625092026 | E69: 46290.838 | F69: 3 | G69: 8905672501942 | H69: 1 | I69: 899 | J69: 0 | K69: 0 | L69: 0 | M69: 899 | N69: 42.8 | O69: 5 | P69: NE FOAM 24 IN CRICKE | Q69: 50170981 | R69: COMPLETED | S69: 50201915 | U69: GnG
A70: 38 | B70: TLX5 | C70: SALE | D70: TLX5102003825092026 | E70: 46290.841 | F70: 3 | G70: 8909409263455 | H70: 1 | I70: 1799 | J70: -391.26 | K70: 0 | L70: -391.26 | M70: 1407.74 | N70: 67.04 | O70: 5 | P70: NE FB AVT BIG BOW BE | Q70: 50157523 | R70: COMPLETED | S70: 50000003 | U70: GnG
A71: 40 | B71: TLX5 | C71: SALE | D71: TLX5102004025092026 | E71: 46290.845 | F71: 3 | G71: 8904520800169 | H71: 1 | I71: 1699 | J71: 0 | K71: 0 | L71: 0 | M71: 1699 | N71: 80.9 | O71: 5 | P71: NE MVL AF 7 INCH BAS | Q71: 50157523 | R71: COMPLETED | S71: 50000003 | U71: GnG
A72: 40 | B72: TLX5 | C72: SALE | D72: TLX5102004025092026 | E72: 46290.845 | F72: 3 | G72: 74299018060 | H72: 1 | I72: 899 | J72: 0 | K72: 0 | L72: 0 | M72: 899 | N72: 42.8 | O72: 5 | P72: HW FIVECAR GIFT PACK | Q72: 50157523 | R72: COMPLETED | S72: 50000003 | U72: GnG
A73: 7 | B73: TLX5 | C73: SALE | D73: TLX5104000725092026 | E73: 46290.852 | F73: 3 | G73: 8905450862715 | H73: 1 | I73: 1099 | J73: 0 | K73: 0 | L73: 0 | M73: 1099 | N73: 52.34 | O73: 5 | P73: NE HM BOOMA SONIC | Q73: 50170981 | R73: COMPLETED | U73: GnG
A74: 7 | B74: TLX5 | C74: SALE | D74: TLX5104000725092026 | E74: 46290.852 | F74: 3 | G74: 8905672336254 | H74: 1 | I74: 249 | J74: 0 | K74: 0 | L74: 0 | M74: 249 | N74: 11.86 | O74: 5 | P74: NE DINO RING TOSS GA | Q74: 50170981 | R74: COMPLETED | S74: 50000001 | U74: GnG
A75: 8 | B75: TLX5 | C75: SALE | D75: TLX5104000825092026 | E75: 46290.854 | F75: 3 | G75: 194735293858 | H75: 1 | I75: 2799 | J75: 0 | K75: 0 | L75: 0 | M75: 2799 | N75: 133.28 | O75: 5 | P75: NE HW THE HOT ONES C | Q75: 50170981 | R75: COMPLETED | S75: 50000001 | U75: GnG
A76: 9 | B76: TLX5 | C76: SALE | D76: TLX5104000925092026 | E76: 46290.858 | F76: 3 | G76: 5000394121171 | H76: 1 | I76: 100 | J76: -31.27 | K76: 0 | L76: -31.27 | M76: 68.73 | N76: 10.48 | O76: 18 | P76: AA 2 CB | Q76: 50170981 | R76: COMPLETED | U76: GnG
A77: 9 | B77: TLX5 | C77: SALE | D77: TLX5104000925092026 | E77: 46290.858 | F77: 3 | G77: 194735255528 | H77: 1 | I77: 1499 | J77: -468.73 | K77: 0 | L77: -468.73 | M77: 1030.27 | N77: 49.06 | O77: 5 | P77: NE HOT WHEELS SPEED | Q77: 50170981 | R77: COMPLETED | S77: 50000001 | U77: GnG
A78: 11 | B78: TLX5 | C78: SALE | D78: TLX5104001125092026 | E78: 46290.864 | F78: 3 | G78: 887961705393 | H78: 1 | I78: 549 | J78: 0 | K78: 0 | L78: 0 | M78: 549 | N78: 26.14 | O78: 5 | P78: NE MT 164 BASIC ASST | Q78: 50170981 | R78: COMPLETED | S78: 50151682 | U78: GnG
A79: 11 | B79: TLX5 | C79: SALE | D79: TLX5104001125092026 | E79: 46290.864 | F79: 3 | G79: 8904432223902 | H79: 1 | I79: 799 | J79: 0 | K79: 0 | L79: 0 | M79: 799 | N79: 38.04 | O79: 5 | P79: NE FP DOG DALMATION | Q79: 50170981 | R79: COMPLETED | S79: 50000001 | U79: GnG
A80: 12 | B80: TLX5 | C80: SALE | D80: TLX5104001225092026 | E80: 46290.868 | F80: 3 | G80: 8904027127257 | H80: 1 | I80: 99 | J80: -6.19 | K80: 0 | L80: -6.19 | M80: 92.81 | N80: 4.42 | O80: 5 | P80: NE ZOOZI BUBBLE TUBE | Q80: 50170981 | R80: COMPLETED | S80: 50000000 | U80: GnG
A81: 13 | B81: TLX5 | C81: SALE | D81: TLX5104001325092026 | E81: 46290.869 | F81: 3 | G81: 5000394121171 | H81: 1 | I81: 120 | J81: -35.72 | K81: 0 | L81: -35.72 | M81: 84.28 | N81: 12.86 | O81: 18 | P81: AA 2 CB | Q81: 50170981 | R81: COMPLETED | U81: GnG
A82: 13 | B82: TLX5 | C82: SALE | D82: TLX5104001325092026 | E82: 46290.869 | F82: 3 | G82: 791115722870 | H82: 1 | I82: 1299 | J82: -386.64 | K82: 0 | L82: -386.64 | M82: 912.36 | N82: 139.18 | O82: 18 | P82: E HM CASPER WALKING | Q82: 50170981 | R82: COMPLETED | U82: GnG
A83: 13 | B83: TLX5 | C83: SALE | D83: TLX5104001325092026 | E83: 46290.869 | F83: 3 | G83: 8905450027114 | H83: 1 | I83: 1599 | J83: -475.94 | K83: 0 | L83: -475.94 | M83: 1123.06 | N83: 53.48 | O83: 5 | P83: NE SS LG BEADS ABACU | Q83: 50170981 | R83: COMPLETED | S83: 50195907 | U83: GnG
A84: 13 | B84: TLX5 | C84: SALE | D84: TLX5104001325092026 | E84: 46290.869 | F84: 3 | G84: 8904520800176 | H84: 1 | I84: 1699 | J84: -505.7 | K84: 0 | L84: -505.7 | M84: 1193.3 | N84: 56.82 | O84: 5 | P84: NE MVL AF 7 INCH BAS | Q84: 50170981 | R84: COMPLETED | S84: 50195907 | U84: GnG
A85: 13 | B85: TLX5 | C85: SALE | D85: TLX5104001325092026 | E85: 46290.869 | F85: 3 | G85: 494500285 | H85: 1 | I85: 1999 | J85: -595 | K85: 0 | L85: -595 | M85: 1404 | N85: 214.16 | O85: 18 | P85: NE REDCARD TOTE BAG | Q85: 50170981 | R85: COMPLETED | U85: GnG
A86: 14 | B86: TLX5 | C86: SALE | D86: TLX5104001425092026 | E86: 46290.873 | F86: 3 | G86: 8904520800121 | H86: 1 | I86: 1699 | J86: -629.29 | K86: 0 | L86: -629.29 | M86: 1069.71 | N86: 50.94 | O86: 5 | P86: NE MVL AF 7 INCH BAS | Q86: 50170981 | R86: COMPLETED | S86: 50195907 | U86: GnG
A87: 14 | B87: TLX5 | C87: SALE | D87: TLX5104001425092026 | E87: 46290.873 | F87: 3 | G87: 8904520800183 | H87: 1 | I87: 1699 | J87: -629.29 | K87: 0 | L87: -629.29 | M87: 1069.71 | N87: 50.94 | O87: 5 | P87: NE MVL AF 7 INCH BAS | Q87: 50170981 | R87: COMPLETED | S87: 50195907 | U87: GnG
A88: 14 | B88: TLX5 | C88: SALE | D88: TLX5104001425092026 | E88: 46290.873 | F88: 3 | G88: 494500285 | H88: 1 | I88: 1999 | J88: -740.42 | K88: 0 | L88: -740.42 | M88: 1258.58 | N88: 191.98 | O88: 18 | P88: NE REDCARD TOTE BAG | Q88: 50170981 | R88: COMPLETED | U88: GnG
A89: 41 | B89: TLX5 | C89: SALE | D89: TLX5102004125092026 | E89: 46290.874 | F89: 3 | G89: 616985378463 | H89: 1 | I89: 799 | J89: 0 | K89: 0 | L89: 0 | M89: 799 | N89: 38.04 | O89: 5 | P89: NE MIRADA 22CM ELEPH | Q89: 50157523 | R89: COMPLETED | S89: 50105787 | U89: GnG
A90: 42 | B90: TLX5 | C90: SALE | D90: TLX5102004225092026 | E90: 46290.878 | F90: 3 | G90: 8905450862715 | H90: 1 | I90: 1099 | J90: -338.19 | K90: 0 | L90: -338.19 | M90: 760.81 | N90: 36.22 | O90: 5 | P90: NE HM BOOMA SONIC | Q90: 50157523 | R90: COMPLETED | U90: GnG
A91: 42 | B91: TLX5 | C91: SALE | D91: TLX5102004225092026 | E91: 46290.878 | F91: 3 | G91: 8904520800138 | H91: 1 | I91: 1699 | J91: -522.83 | K91: 0 | L91: -522.83 | M91: 1176.17 | N91: 56 | O91: 5 | P91: NE MVL AF 7 INCH BAS | Q91: 50157523 | R91: COMPLETED | S91: 50195907 | U91: GnG
A92: 42 | B92: TLX5 | C92: SALE | D92: TLX5102004225092026 | E92: 46290.878 | F92: 3 | G92: 8904520800169 | H92: 1 | I92: 1699 | J92: -522.83 | K92: 0 | L92: -522.83 | M92: 1176.17 | N92: 56 | O92: 5 | P92: NE MVL AF 7 INCH BAS | Q92: 50157523 | R92: COMPLETED | S92: 50195907 | U92: GnG
A93: 42 | B93: TLX5 | C93: SALE | D93: TLX5102004225092026 | E93: 46290.878 | F93: 3 | G93: 494500285 | H93: 1 | I93: 1999 | J93: -615.15 | K93: 0 | L93: -615.15 | M93: 1383.85 | N93: 211.1 | O93: 18 | P93: NE REDCARD TOTE BAG | Q93: 50157523 | R93: COMPLETED | U93: GnG
A94: 15 | B94: TLX5 | C94: SALE | D94: TLX5104001525092026 | E94: 46290.879 | F94: 3 | G94: 494500285 | H94: 1 | I94: 1999 | J94: -571.02 | K94: 0 | L94: -571.02 | M94: 1427.98 | N94: 217.82 | O94: 18 | P94: NE REDCARD TOTE BAG | Q94: 50170981 | R94: COMPLETED | U94: GnG
A95: 15 | B95: TLX5 | C95: SALE | D95: TLX5104001525092026 | E95: 46290.879 | F95: 3 | G95: 8904520801470 | H95: 1 | I95: 4999 | J95: -1427.98 | K95: 0 | L95: -1427.98 | M95: 3571.02 | N95: 170.04 | O95: 5 | P95: NE IRON MAN MK 11 | Q95: 50170981 | R95: COMPLETED | S95: 50195907 | U95: GnG
A96: 16 | B96: TLX5 | C96: SALE | D96: TLX5104001625092026 | E96: 46290.884 | F96: 3 | G96: 5000394121171 | H96: 1 | I96: 120 | J96: 0 | K96: 0 | L96: 0 | M96: 120 | N96: 18.3 | O96: 18 | P96: AA 2 CB | Q96: 50170981 | R96: COMPLETED | U96: GnG
A97: 16 | B97: TLX5 | C97: SALE | D97: TLX5104001625092026 | E97: 46290.884 | F97: 3 | G97: 5000394121171 | H97: 1 | I97: 120 | J97: 0 | K97: 0 | L97: 0 | M97: 120 | N97: 18.3 | O97: 18 | P97: AA 2 CB | Q97: 50170981 | R97: COMPLETED | U97: GnG
A98: 16 | B98: TLX5 | C98: SALE | D98: TLX5104001625092026 | E98: 46290.884 | F98: 3 | G98: 8905672547537 | H98: 1 | I98: 1499 | J98: 0 | K98: 0 | L98: 0 | M98: 1499 | N98: 228.66 | O98: 18 | P98: E SS DOLPHIN CONCERT | Q98: 50170981 | R98: COMPLETED | S98: 50201915 | U98: GnG
A99: 16 | B99: TLX5 | C99: SALE | D99: TLX5104001625092026 | E99: 46290.884 | F99: 3 | G99: 8904279507470 | H99: 1 | I99: 936 | J99: 0 | K99: 0 | L99: 0 | M99: 936 | N99: 44.58 | O99: 5 | P99: NE SKM SANDTASTIC UN | Q99: 50170981 | R99: COMPLETED | S99: 50201915 | U99: GnG
A100: 43 | B100: TLX5 | C100: SALE | D100: TLX5102004325092026 | E100: 46290.893 | F100: 3 | G100: 8901691010670 | H100: 1 | I100: 100 | J100: 0 | K100: 0 | L100: 0 | M100: 100 | N100: 15.26 | O100: 18 | P100: EVEREADY BATT AAA 21 | Q100: 50157523 | R100: COMPLETED | U100: GnG
...

Sheet Loyalty
A1: Store | B1: Last | C1: Today | D1: Today NOB | E1: Att%
A2: TLX5 | B2: 4 | C2: 2 | D2: 78 | E2: =+C2/D2 -> 0.025641026

Sheet CT
K1: 0.3 | L1: 0.04 | M1: 0.3 | N1: 0.085 | O1: 0.015 | P1: 0.035 | Q1: 0.05 | U1: Targte | V1: Qty | W1: Store Bills | X1: Store Qty | Y1: Today Ach
A2: Date | B2: Total Bill | C2: Total Qty | D2: Battery | E2: ATVD | F2: Bubble wand | G2: Loyalty | H2: Red Card | I2: Non BIS/Liq/Dev | J2: Tote Bag | K2: Battery | L2: ATVD | M2: Bubble wand | N2: Loyalty | O2: Red Card | P2: Non BIS/Liq/Dev | Q2: Tote Bag | T2: Battery | U2: 0.3 | V2: =VLOOKUP($V$9,A3:D34,4,0) -> #N/A | W2: =VLOOKUP($V$9,A3:B33,2,0) -> #N/A | X2: =VLOOKUP($V$9,A3:C33,3,0) -> #N/A | Y2: =V2/W2 -> #N/A
A3: 46174 | B3: =IFERROR(VLOOKUP(A3,DSR!C9:R54,16,0),0) -> 0 | C3: =IFERROR(VLOOKUP(A3,DSR!C9:Q54,15,0),0) -> 0 | D3: =IFERROR(VLOOKUP(A3,DSR!C9:T54,18,0),0) -> 0 | E3: =IFERROR(VLOOKUP(A3,DSR!C9:U54,19,0),0) -> 0 | F3: =IFERROR(VLOOKUP(A3,DSR!C9:X54,22,0),0) -> 0 | G3: =IFERROR(VLOOKUP(A3,DSR!C9:V54,20,0),0) -> 0 | H3: =IFERROR(VLOOKUP(A3,DSR!C9:W54,21,0),0) -> 0 | I3: =IFERROR(VLOOKUP(A3,DSR!C9:BE54,55,0),0) -> 0 | J3: =IFERROR(VLOOKUP(A3,DSR!C9:BG54,57,0),0) -> 0 | K3: =D3/B3 -> #DIV/0! | L3: =E3/B3 -> #DIV/0! | M3: =F3/B3 -> #DIV/0! | N3: =G3/B3 -> #DIV/0! | O3: =H3/B3 -> #DIV/0! | P3: =I3/C3 -> #DIV/0! | Q3: =J3/B3 -> #DIV/0! | T3: ATVD | U3: 0.04 | V3: =VLOOKUP($V$9,A3:E34,5,0) -> #N/A | W3: =VLOOKUP($V$9,A4:B34,2,0) -> #N/A | X3: =VLOOKUP($V$9,A4:C34,3,0) -> #N/A | Y3: =V3/W3 -> #N/A
A4: =A3+1 -> 46175 | B4: =IFERROR(VLOOKUP(A4,DSR!C10:R55,16,0),0) -> 0 | C4: =IFERROR(VLOOKUP(A4,DSR!C10:Q55,15,0),0) -> 0 | D4: =IFERROR(VLOOKUP(A4,DSR!C10:T55,18,0),0) -> 0 | E4: =IFERROR(VLOOKUP(A4,DSR!C10:U55,19,0),0) -> 0 | F4: =IFERROR(VLOOKUP(A4,DSR!C10:X55,22,0),0) -> 0 | G4: =IFERROR(VLOOKUP(A4,DSR!C10:V55,20,0),0) -> 0 | H4: =IFERROR(VLOOKUP(A4,DSR!C10:W55,21,0),0) -> 0 | I4: =IFERROR(VLOOKUP(A4,DSR!C10:BE55,55,0),0) -> 0 | J4: =IFERROR(VLOOKUP(A4,DSR!C10:BG55,57,0),0) -> 0 | K4: =D4/B4 -> #DIV/0! | L4: =E4/B4 -> #DIV/0! | M4: =F4/B4 -> #DIV/0! | N4: =G4/B4 -> #DIV/0! | O4: =H4/B4 -> #DIV/0! | P4: =I4/C4 -> #DIV/0! | Q4: =J4/B4 -> #DIV/0! | T4: Bubble wand | U4: 0.3 | V4: =VLOOKUP($V$9,A3:F34,6,0) -> #N/A | W4: =VLOOKUP($V$9,A5:B35,2,0) -> #N/A | X4: =VLOOKUP($V$9,A5:C35,3,0) -> #N/A | Y4: =V4/W4 -> #N/A
A5: =A4+1 -> 46176 | B5: =IFERROR(VLOOKUP(A5,DSR!C11:R56,16,0),0) -> 0 | C5: =IFERROR(VLOOKUP(A5,DSR!C11:Q56,15,0),0) -> 0 | D5: =IFERROR(VLOOKUP(A5,DSR!C11:T56,18,0),0) -> 0 | E5: =IFERROR(VLOOKUP(A5,DSR!C11:U56,19,0),0) -> 0 | F5: =IFERROR(VLOOKUP(A5,DSR!C11:X56,22,0),0) -> 0 | G5: =IFERROR(VLOOKUP(A5,DSR!C11:V56,20,0),0) -> 0 | H5: =IFERROR(VLOOKUP(A5,DSR!C11:W56,21,0),0) -> 0 | I5: =IFERROR(VLOOKUP(A5,DSR!C11:BE56,55,0),0) -> 0 | J5: =IFERROR(VLOOKUP(A5,DSR!C11:BG56,57,0),0) -> 0 | K5: =D5/B5 -> #DIV/0! | L5: =E5/B5 -> #DIV/0! | M5: =F5/B5 -> #DIV/0! | N5: =G5/B5 -> #DIV/0! | O5: =H5/B5 -> #DIV/0! | P5: =I5/C5 -> #DIV/0! | Q5: =J5/B5 -> #DIV/0! | T5: Loyalty | U5: 0.085 | V5: =VLOOKUP($V$9,A3:G34,7,0) -> #N/A | W5: =VLOOKUP($V$9,A6:B36,2,0) -> #N/A | X5: =VLOOKUP($V$9,A6:C36,3,0) -> #N/A | Y5: =V5/W5 -> #N/A
A6: =A5+1 -> 46177 | B6: =IFERROR(VLOOKUP(A6,DSR!C12:R57,16,0),0) -> 0 | C6: =IFERROR(VLOOKUP(A6,DSR!C12:Q57,15,0),0) -> 0 | D6: =IFERROR(VLOOKUP(A6,DSR!C12:T57,18,0),0) -> 0 | E6: =IFERROR(VLOOKUP(A6,DSR!C12:U57,19,0),0) -> 0 | F6: =IFERROR(VLOOKUP(A6,DSR!C12:X57,22,0),0) -> 0 | G6: =IFERROR(VLOOKUP(A6,DSR!C12:V57,20,0),0) -> 0 | H6: =IFERROR(VLOOKUP(A6,DSR!C12:W57,21,0),0) -> 0 | I6: =IFERROR(VLOOKUP(A6,DSR!C12:BE57,55,0),0) -> 0 | J6: =IFERROR(VLOOKUP(A6,DSR!C12:BG57,57,0),0) -> 0 | K6: =D6/B6 -> #DIV/0! | L6: =E6/B6 -> #DIV/0! | M6: =F6/B6 -> #DIV/0! | N6: =G6/B6 -> #DIV/0! | O6: =H6/B6 -> #DIV/0! | P6: =I6/C6 -> #DIV/0! | Q6: =J6/B6 -> #DIV/0! | T6: Red Card | U6: 0.015 | V6: =VLOOKUP(V9,A3:H34,8,0) -> #N/A | W6: =VLOOKUP($V$9,A7:B37,2,0) -> #N/A | X6: =VLOOKUP($V$9,A7:C37,3,0) -> #N/A | Y6: =V6/W6 -> #N/A
A7: =A6+1 -> 46178 | B7: =IFERROR(VLOOKUP(A7,DSR!C13:R58,16,0),0) -> 0 | C7: =IFERROR(VLOOKUP(A7,DSR!C13:Q58,15,0),0) -> 0 | D7: =IFERROR(VLOOKUP(A7,DSR!C13:T58,18,0),0) -> 0 | E7: =IFERROR(VLOOKUP(A7,DSR!C13:U58,19,0),0) -> 0 | F7: =IFERROR(VLOOKUP(A7,DSR!C13:X58,22,0),0) -> 0 | G7: =IFERROR(VLOOKUP(A7,DSR!C13:V58,20,0),0) -> 0 | H7: =IFERROR(VLOOKUP(A7,DSR!C13:W58,21,0),0) -> 0 | I7: =IFERROR(VLOOKUP(A7,DSR!C13:BE58,55,0),0) -> 0 | J7: =IFERROR(VLOOKUP(A7,DSR!C13:BG58,57,0),0) -> 0 | K7: =D7/B7 -> #DIV/0! | L7: =E7/B7 -> #DIV/0! | M7: =F7/B7 -> #DIV/0! | N7: =G7/B7 -> #DIV/0! | O7: =H7/B7 -> #DIV/0! | P7: =I7/C7 -> #DIV/0! | Q7: =J7/B7 -> #DIV/0! | T7: Non BIS/Liq/Dev | U7: 0.035 | V7: =VLOOKUP(V9,A3:I34,9,0) -> #N/A | W7: =VLOOKUP($V$9,A8:B38,2,0) -> #N/A | X7: =VLOOKUP($V$9,A8:C38,3,0) -> #N/A | Y7: =V7/X7 -> #N/A
A8: =A7+1 -> 46179 | B8: =IFERROR(VLOOKUP(A8,DSR!C14:R59,16,0),0) -> 0 | C8: =IFERROR(VLOOKUP(A8,DSR!C14:Q59,15,0),0) -> 0 | D8: =IFERROR(VLOOKUP(A8,DSR!C14:T59,18,0),0) -> 0 | E8: =IFERROR(VLOOKUP(A8,DSR!C14:U59,19,0),0) -> 0 | F8: =IFERROR(VLOOKUP(A8,DSR!C14:X59,22,0),0) -> 0 | G8: =IFERROR(VLOOKUP(A8,DSR!C14:V59,20,0),0) -> 0 | H8: =IFERROR(VLOOKUP(A8,DSR!C14:W59,21,0),0) -> 0 | I8: =IFERROR(VLOOKUP(A8,DSR!C14:BE59,55,0),0) -> 0 | J8: =IFERROR(VLOOKUP(A8,DSR!C14:BG59,57,0),0) -> 0 | K8: =D8/B8 -> #DIV/0! | L8: =E8/B8 -> #DIV/0! | M8: =F8/B8 -> #DIV/0! | N8: =G8/B8 -> #DIV/0! | O8: =H8/B8 -> #DIV/0! | P8: =I8/C8 -> #DIV/0! | Q8: =J8/B8 -> #DIV/0! | T8: Tote bag | U8: 0.05 | V8: =VLOOKUP(V9,A3:J34,10,0) -> #N/A | W8: =VLOOKUP($V$9,A9:B39,2,0) -> #N/A | X8: =VLOOKUP($V$9,A9:C39,3,0) -> #N/A | Y8: =V8/W8 -> #N/A
A9: =A8+1 -> 46180 | B9: =IFERROR(VLOOKUP(A9,DSR!C15:R60,16,0),0) -> 0 | C9: =IFERROR(VLOOKUP(A9,DSR!C15:Q60,15,0),0) -> 0 | D9: =IFERROR(VLOOKUP(A9,DSR!C15:T60,18,0),0) -> 0 | E9: =IFERROR(VLOOKUP(A9,DSR!C15:U60,19,0),0) -> 0 | F9: =IFERROR(VLOOKUP(A9,DSR!C15:X60,22,0),0) -> 0 | G9: =IFERROR(VLOOKUP(A9,DSR!C15:V60,20,0),0) -> 0 | H9: =IFERROR(VLOOKUP(A9,DSR!C15:W60,21,0),0) -> 0 | I9: =IFERROR(VLOOKUP(A9,DSR!C15:BE60,55,0),0) -> 0 | J9: =IFERROR(VLOOKUP(A9,DSR!C15:BG60,57,0),0) -> 0 | K9: =D9/B9 -> #DIV/0! | L9: =E9/B9 -> #DIV/0! | M9: =F9/B9 -> #DIV/0! | N9: =G9/B9 -> #DIV/0! | O9: =H9/B9 -> #DIV/0! | P9: =I9/C9 -> #DIV/0! | Q9: =J9/B9 -> #DIV/0! | V9: =TODAY() -> 46291
A10: =A9+1 -> 46181 | B10: =IFERROR(VLOOKUP(A10,DSR!C16:R61,16,0),0) -> 0 | C10: =IFERROR(VLOOKUP(A10,DSR!C16:Q61,15,0),0) -> 0 | D10: =IFERROR(VLOOKUP(A10,DSR!C16:T61,18,0),0) -> 0 | E10: =IFERROR(VLOOKUP(A10,DSR!C16:U61,19,0),0) -> 0 | F10: =IFERROR(VLOOKUP(A10,DSR!C16:X61,22,0),0) -> 0 | G10: =IFERROR(VLOOKUP(A10,DSR!C16:V61,20,0),0) -> 0 | H10: =IFERROR(VLOOKUP(A10,DSR!C16:W61,21,0),0) -> 0 | I10: =IFERROR(VLOOKUP(A10,DSR!C16:BE61,55,0),0) -> 0 | J10: =IFERROR(VLOOKUP(A10,DSR!C16:BG61,57,0),0) -> 0 | K10: =D10/B10 -> #DIV/0! | L10: =E10/B10 -> #DIV/0! | M10: =F10/B10 -> #DIV/0! | N10: =G10/B10 -> #DIV/0! | O10: =H10/B10 -> #DIV/0! | P10: =I10/C10 -> #DIV/0! | Q10: =J10/B10 -> #DIV/0!
A11: =A10+1 -> 46182 | B11: =IFERROR(VLOOKUP(A11,DSR!C17:R62,16,0),0) -> 0 | C11: =IFERROR(VLOOKUP(A11,DSR!C17:Q62,15,0),0) -> 0 | D11: =IFERROR(VLOOKUP(A11,DSR!C17:T62,18,0),0) -> 0 | E11: =IFERROR(VLOOKUP(A11,DSR!C17:U62,19,0),0) -> 0 | F11: =IFERROR(VLOOKUP(A11,DSR!C17:X62,22,0),0) -> 0 | G11: =IFERROR(VLOOKUP(A11,DSR!C17:V62,20,0),0) -> 0 | H11: =IFERROR(VLOOKUP(A11,DSR!C17:W62,21,0),0) -> 0 | I11: =IFERROR(VLOOKUP(A11,DSR!C17:BE62,55,0),0) -> 0 | J11: =IFERROR(VLOOKUP(A11,DSR!C17:BG62,57,0),0) -> 0 | K11: =D11/B11 -> #DIV/0! | L11: =E11/B11 -> #DIV/0! | M11: =F11/B11 -> #DIV/0! | N11: =G11/B11 -> #DIV/0! | O11: =H11/B11 -> #DIV/0! | P11: =I11/C11 -> #DIV/0! | Q11: =J11/B11 -> #DIV/0! | T11: DO NOT EDIT ANY VALUE JUST SHARE PHOTO
A12: =A11+1 -> 46183 | B12: =IFERROR(VLOOKUP(A12,DSR!C18:R63,16,0),0) -> 0 | C12: =IFERROR(VLOOKUP(A12,DSR!C18:Q63,15,0),0) -> 0 | D12: =IFERROR(VLOOKUP(A12,DSR!C18:T63,18,0),0) -> 0 | E12: =IFERROR(VLOOKUP(A12,DSR!C18:U63,19,0),0) -> 0 | F12: =IFERROR(VLOOKUP(A12,DSR!C18:X63,22,0),0) -> 0 | G12: =IFERROR(VLOOKUP(A12,DSR!C18:V63,20,0),0) -> 0 | H12: =IFERROR(VLOOKUP(A12,DSR!C18:W63,21,0),0) -> 0 | I12: =IFERROR(VLOOKUP(A12,DSR!C18:BE63,55,0),0) -> 0 | J12: =IFERROR(VLOOKUP(A12,DSR!C18:BG63,57,0),0) -> 0 | K12: =D12/B12 -> #DIV/0! | L12: =E12/B12 -> #DIV/0! | M12: =F12/B12 -> #DIV/0! | N12: =G12/B12 -> #DIV/0! | O12: =H12/B12 -> #DIV/0! | P12: =I12/C12 -> #DIV/0! | Q12: =J12/B12 -> #DIV/0!
A13: =A12+1 -> 46184 | B13: =IFERROR(VLOOKUP(A13,DSR!C19:R64,16,0),0) -> 0 | C13: =IFERROR(VLOOKUP(A13,DSR!C19:Q64,15,0),0) -> 0 | D13: =IFERROR(VLOOKUP(A13,DSR!C19:T64,18,0),0) -> 0 | E13: =IFERROR(VLOOKUP(A13,DSR!C19:U64,19,0),0) -> 0 | F13: =IFERROR(VLOOKUP(A13,DSR!C19:X64,22,0),0) -> 0 | G13: =IFERROR(VLOOKUP(A13,DSR!C19:V64,20,0),0) -> 0 | H13: =IFERROR(VLOOKUP(A13,DSR!C19:W64,21,0),0) -> 0 | I13: =IFERROR(VLOOKUP(A13,DSR!C19:BE64,55,0),0) -> 0 | J13: =IFERROR(VLOOKUP(A13,DSR!C19:BG64,57,0),0) -> 0 | K13: =D13/B13 -> #DIV/0! | L13: =E13/B13 -> #DIV/0! | M13: =F13/B13 -> #DIV/0! | N13: =G13/B13 -> #DIV/0! | O13: =H13/B13 -> #DIV/0! | P13: =I13/C13 -> #DIV/0! | Q13: =J13/B13 -> #DIV/0!
A14: =A13+1 -> 46185 | B14: =IFERROR(VLOOKUP(A14,DSR!C20:R65,16,0),0) -> 0 | C14: =IFERROR(VLOOKUP(A14,DSR!C20:Q65,15,0),0) -> 0 | D14: =IFERROR(VLOOKUP(A14,DSR!C20:T65,18,0),0) -> 0 | E14: =IFERROR(VLOOKUP(A14,DSR!C20:U65,19,0),0) -> 0 | F14: =IFERROR(VLOOKUP(A14,DSR!C20:X65,22,0),0) -> 0 | G14: =IFERROR(VLOOKUP(A14,DSR!C20:V65,20,0),0) -> 0 | H14: =IFERROR(VLOOKUP(A14,DSR!C20:W65,21,0),0) -> 0 | I14: =IFERROR(VLOOKUP(A14,DSR!C20:BE65,55,0),0) -> 0 | J14: =IFERROR(VLOOKUP(A14,DSR!C20:BG65,57,0),0) -> 0 | K14: =D14/B14 -> #DIV/0! | L14: =E14/B14 -> #DIV/0! | M14: =F14/B14 -> #DIV/0! | N14: =G14/B14 -> #DIV/0! | O14: =H14/B14 -> #DIV/0! | P14: =I14/C14 -> #DIV/0! | Q14: =J14/B14 -> #DIV/0!
A15: =A14+1 -> 46186 | B15: =IFERROR(VLOOKUP(A15,DSR!C21:R66,16,0),0) -> 0 | C15: =IFERROR(VLOOKUP(A15,DSR!C21:Q66,15,0),0) -> 0 | D15: =IFERROR(VLOOKUP(A15,DSR!C21:T66,18,0),0) -> 0 | E15: =IFERROR(VLOOKUP(A15,DSR!C21:U66,19,0),0) -> 0 | F15: =IFERROR(VLOOKUP(A15,DSR!C21:X66,22,0),0) -> 0 | G15: =IFERROR(VLOOKUP(A15,DSR!C21:V66,20,0),0) -> 0 | H15: =IFERROR(VLOOKUP(A15,DSR!C21:W66,21,0),0) -> 0 | I15: =IFERROR(VLOOKUP(A15,DSR!C21:BE66,55,0),0) -> 0 | J15: =IFERROR(VLOOKUP(A15,DSR!C21:BG66,57,0),0) -> 0 | K15: =D15/B15 -> #DIV/0! | L15: =E15/B15 -> #DIV/0! | M15: =F15/B15 -> #DIV/0! | N15: =G15/B15 -> #DIV/0! | O15: =H15/B15 -> #DIV/0! | P15: =I15/C15 -> #DIV/0! | Q15: =J15/B15 -> #DIV/0!
A16: =A15+1 -> 46187 | B16: =IFERROR(VLOOKUP(A16,DSR!C22:R67,16,0),0) -> 0 | C16: =IFERROR(VLOOKUP(A16,DSR!C22:Q67,15,0),0) -> 0 | D16: =IFERROR(VLOOKUP(A16,DSR!C22:T67,18,0),0) -> 0 | E16: =IFERROR(VLOOKUP(A16,DSR!C22:U67,19,0),0) -> 0 | F16: =IFERROR(VLOOKUP(A16,DSR!C22:X67,22,0),0) -> 0 | G16: =IFERROR(VLOOKUP(A16,DSR!C22:V67,20,0),0) -> 0 | H16: =IFERROR(VLOOKUP(A16,DSR!C22:W67,21,0),0) -> 0 | I16: =IFERROR(VLOOKUP(A16,DSR!C22:BE67,55,0),0) -> 0 | J16: =IFERROR(VLOOKUP(A16,DSR!C22:BG67,57,0),0) -> 0 | K16: =D16/B16 -> #DIV/0! | L16: =E16/B16 -> #DIV/0! | M16: =F16/B16 -> #DIV/0! | N16: =G16/B16 -> #DIV/0! | O16: =H16/B16 -> #DIV/0! | P16: =I16/C16 -> #DIV/0! | Q16: =J16/B16 -> #DIV/0!
A17: =A16+1 -> 46188 | B17: =IFERROR(VLOOKUP(A17,DSR!C23:R68,16,0),0) -> 0 | C17: =IFERROR(VLOOKUP(A17,DSR!C23:Q68,15,0),0) -> 0 | D17: =IFERROR(VLOOKUP(A17,DSR!C23:T68,18,0),0) -> 0 | E17: =IFERROR(VLOOKUP(A17,DSR!C23:U68,19,0),0) -> 0 | F17: =IFERROR(VLOOKUP(A17,DSR!C23:X68,22,0),0) -> 0 | G17: =IFERROR(VLOOKUP(A17,DSR!C23:V68,20,0),0) -> 0 | H17: =IFERROR(VLOOKUP(A17,DSR!C23:W68,21,0),0) -> 0 | I17: =IFERROR(VLOOKUP(A17,DSR!C23:BE68,55,0),0) -> 0 | J17: =IFERROR(VLOOKUP(A17,DSR!C23:BG68,57,0),0) -> 0 | K17: =D17/B17 -> #DIV/0! | L17: =E17/B17 -> #DIV/0! | M17: =F17/B17 -> #DIV/0! | N17: =G17/B17 -> #DIV/0! | O17: =H17/B17 -> #DIV/0! | P17: =I17/C17 -> #DIV/0! | Q17: =J17/B17 -> #DIV/0!
A18: =A17+1 -> 46189 | B18: =IFERROR(VLOOKUP(A18,DSR!C24:R69,16,0),0) -> 0 | C18: =IFERROR(VLOOKUP(A18,DSR!C24:Q69,15,0),0) -> 0 | D18: =IFERROR(VLOOKUP(A18,DSR!C24:T69,18,0),0) -> 0 | E18: =IFERROR(VLOOKUP(A18,DSR!C24:U69,19,0),0) -> 0 | F18: =IFERROR(VLOOKUP(A18,DSR!C24:X69,22,0),0) -> 0 | G18: =IFERROR(VLOOKUP(A18,DSR!C24:V69,20,0),0) -> 0 | H18: =IFERROR(VLOOKUP(A18,DSR!C24:W69,21,0),0) -> 0 | I18: =IFERROR(VLOOKUP(A18,DSR!C24:BE69,55,0),0) -> 0 | J18: =IFERROR(VLOOKUP(A18,DSR!C24:BG69,57,0),0) -> 0 | K18: =D18/B18 -> #DIV/0! | L18: =E18/B18 -> #DIV/0! | M18: =F18/B18 -> #DIV/0! | N18: =G18/B18 -> #DIV/0! | O18: =H18/B18 -> #DIV/0! | P18: =I18/C18 -> #DIV/0! | Q18: =J18/B18 -> #DIV/0!
A19: =A18+1 -> 46190 | B19: =IFERROR(VLOOKUP(A19,DSR!C25:R70,16,0),0) -> 0 | C19: =IFERROR(VLOOKUP(A19,DSR!C25:Q70,15,0),0) -> 0 | D19: =IFERROR(VLOOKUP(A19,DSR!C25:T70,18,0),0) -> 0 | E19: =IFERROR(VLOOKUP(A19,DSR!C25:U70,19,0),0) -> 0 | F19: =IFERROR(VLOOKUP(A19,DSR!C25:X70,22,0),0) -> 0 | G19: =IFERROR(VLOOKUP(A19,DSR!C25:V70,20,0),0) -> 0 | H19: =IFERROR(VLOOKUP(A19,DSR!C25:W70,21,0),0) -> 0 | I19: =IFERROR(VLOOKUP(A19,DSR!C25:BE70,55,0),0) -> 0 | J19: =IFERROR(VLOOKUP(A19,DSR!C25:BG70,57,0),0) -> 0 | K19: =D19/B19 -> #DIV/0! | L19: =E19/B19 -> #DIV/0! | M19: =F19/B19 -> #DIV/0! | N19: =G19/B19 -> #DIV/0! | O19: =H19/B19 -> #DIV/0! | P19: =I19/C19 -> #DIV/0! | Q19: =J19/B19 -> #DIV/0!
A20: =A19+1 -> 46191 | B20: =IFERROR(VLOOKUP(A20,DSR!C26:R71,16,0),0) -> 0 | C20: =IFERROR(VLOOKUP(A20,DSR!C26:Q71,15,0),0) -> 0 | D20: =IFERROR(VLOOKUP(A20,DSR!C26:T71,18,0),0) -> 0 | E20: =IFERROR(VLOOKUP(A20,DSR!C26:U71,19,0),0) -> 0 | F20: =IFERROR(VLOOKUP(A20,DSR!C26:X71,22,0),0) -> 0 | G20: =IFERROR(VLOOKUP(A20,DSR!C26:V71,20,0),0) -> 0 | H20: =IFERROR(VLOOKUP(A20,DSR!C26:W71,21,0),0) -> 0 | I20: =IFERROR(VLOOKUP(A20,DSR!C26:BE71,55,0),0) -> 0 | J20: =IFERROR(VLOOKUP(A20,DSR!C26:BG71,57,0),0) -> 0 | K20: =D20/B20 -> #DIV/0! | L20: =E20/B20 -> #DIV/0! | M20: =F20/B20 -> #DIV/0! | N20: =G20/B20 -> #DIV/0! | O20: =H20/B20 -> #DIV/0! | P20: =I20/C20 -> #DIV/0! | Q20: =J20/B20 -> #DIV/0!
A21: =A20+1 -> 46192 | B21: =IFERROR(VLOOKUP(A21,DSR!C27:R72,16,0),0) -> 0 | C21: =IFERROR(VLOOKUP(A21,DSR!C27:Q72,15,0),0) -> 0 | D21: =IFERROR(VLOOKUP(A21,DSR!C27:T72,18,0),0) -> 0 | E21: =IFERROR(VLOOKUP(A21,DSR!C27:U72,19,0),0) -> 0 | F21: =IFERROR(VLOOKUP(A21,DSR!C27:X72,22,0),0) -> 0 | G21: =IFERROR(VLOOKUP(A21,DSR!C27:V72,20,0),0) -> 0 | H21: =IFERROR(VLOOKUP(A21,DSR!C27:W72,21,0),0) -> 0 | I21: =IFERROR(VLOOKUP(A21,DSR!C27:BE72,55,0),0) -> 0 | J21: =IFERROR(VLOOKUP(A21,DSR!C27:BG72,57,0),0) -> 0 | K21: =D21/B21 -> #DIV/0! | L21: =E21/B21 -> #DIV/0! | M21: =F21/B21 -> #DIV/0! | N21: =G21/B21 -> #DIV/0! | O21: =H21/B21 -> #DIV/0! | P21: =I21/C21 -> #DIV/0! | Q21: =J21/B21 -> #DIV/0!
A22: =A21+1 -> 46193 | B22: =IFERROR(VLOOKUP(A22,DSR!C28:R73,16,0),0) -> 0 | C22: =IFERROR(VLOOKUP(A22,DSR!C28:Q73,15,0),0) -> 0 | D22: =IFERROR(VLOOKUP(A22,DSR!C28:T73,18,0),0) -> 0 | E22: =IFERROR(VLOOKUP(A22,DSR!C28:U73,19,0),0) -> 0 | F22: =IFERROR(VLOOKUP(A22,DSR!C28:X73,22,0),0) -> 0 | G22: =IFERROR(VLOOKUP(A22,DSR!C28:V73,20,0),0) -> 0 | H22: =IFERROR(VLOOKUP(A22,DSR!C28:W73,21,0),0) -> 0 | I22: =IFERROR(VLOOKUP(A22,DSR!C28:BE73,55,0),0) -> 0 | J22: =IFERROR(VLOOKUP(A22,DSR!C28:BG73,57,0),0) -> 0 | K22: =D22/B22 -> #DIV/0! | L22: =E22/B22 -> #DIV/0! | M22: =F22/B22 -> #DIV/0! | N22: =G22/B22 -> #DIV/0! | O22: =H22/B22 -> #DIV/0! | P22: =I22/C22 -> #DIV/0! | Q22: =J22/B22 -> #DIV/0!
A23: =A22+1 -> 46194 | B23: =IFERROR(VLOOKUP(A23,DSR!C29:R74,16,0),0) -> 0 | C23: =IFERROR(VLOOKUP(A23,DSR!C29:Q74,15,0),0) -> 0 | D23: =IFERROR(VLOOKUP(A23,DSR!C29:T74,18,0),0) -> 0 | E23: =IFERROR(VLOOKUP(A23,DSR!C29:U74,19,0),0) -> 0 | F23: =IFERROR(VLOOKUP(A23,DSR!C29:X74,22,0),0) -> 0 | G23: =IFERROR(VLOOKUP(A23,DSR!C29:V74,20,0),0) -> 0 | H23: =IFERROR(VLOOKUP(A23,DSR!C29:W74,21,0),0) -> 0 | I23: =IFERROR(VLOOKUP(A23,DSR!C29:BE74,55,0),0) -> 0 | J23: =IFERROR(VLOOKUP(A23,DSR!C29:BG74,57,0),0) -> 0 | K23: =D23/B23 -> #DIV/0! | L23: =E23/B23 -> #DIV/0! | M23: =F23/B23 -> #DIV/0! | N23: =G23/B23 -> #DIV/0! | O23: =H23/B23 -> #DIV/0! | P23: =I23/C23 -> #DIV/0! | Q23: =J23/B23 -> #DIV/0!
... A33: =A32+1 -> 46204 | B33: =IFERROR(VLOOKUP(A33,DSR!C39:R84,16,0),0) -> 0 | C33: =IFERROR(VLOOKUP(A33,DSR!C39:Q84,15,0),0) -> 0 | D33: =IFERROR(VLOOKUP(A33,DSR!C39:T84,18,0),0) -> 0 | E33: =IFERROR(VLOOKUP(A33,DSR!C39:U84,19,0),0) -> 0 | F33: =IFERROR(VLOOKUP(A33,DSR!C39:X84,22,0),0) -> 0 | G33: =IFERROR(VLOOKUP(A33,DSR!C39:V84,20,0),0) -> 0 | H33: =IFERROR(VLOOKUP(A33,DSR!C39:W84,21,0),0) -> 0 | I33: =IFERROR(VLOOKUP(A33,DSR!C39:BE84,55,0),0) -> 0 | J33: =IFERROR(VLOOKUP(A33,DSR!C39:BG84,57,0),0) -> 0 | K33: =D33/B33 -> #DIV/0! | L33: =E33/B33 -> #DIV/0! | M33: =F33/B33 -> #DIV/0! | N33: =G33/B33 -> #DIV/0! | O33: =H33/B33 -> #DIV/0! | P33: =I33/C33 -> #DIV/0! | Q33: =J33/B33 -> #DIV/0!
A34: MTD | B34: =SUM(B3:B33) -> 0 | C34: =SUM(C3:C33) -> 0 | D34: =SUM(D3:D33) -> 0 | E34: =SUM(E3:E33) -> 0 | F34: =SUM(F3:F33) -> 0 | G34: =SUM(G3:G33) -> 0 | H34: =SUM(H3:H33) -> 0 | I34: =SUM(I3:I33) -> 0 | J34: =SUM(J3:J33) -> 0 | K34: =D34/B34 -> #DIV/0! | L34: =E34/B34 -> #DIV/0! | M34: =F34/B34 -> #DIV/0! | N34: =G34/B34 -> #DIV/0! | O34: =H34/B34 -> #DIV/0! | P34: =I34/C34 -> #DIV/0! | Q34: =J34/$B$3 -> #DIV/0!

Sheet KPIs Track
A1: Date | B1: =TODAY() -> 46291 | C1: =TODAY()-7 -> 46284
A2: Store Code | B2: TLX5
A3: Store Name | B3: Vegas
A5: Today Upt | B5: =VLOOKUP(B1,DSR!C9:AA54,25,0)
A6: LWSD Upt | B6: =VLOOKUP(C1,DSR!C9:AA55,25,0) -> 2.2222222
A7: Growth | B7: =B5/B6-1 -> #VALUE!
A9: Bubble Stick | B9: =VLOOKUP(B1,DSR!C9:X54,22,0) -> 0
A10: Bubble Stick % | B10: =VLOOKUP(B1,DSR!C9:AG54,31,0) -> #DIV/0!
A12: Batteries Sold | B12: =VLOOKUP(B1,DSR!C9:T54,18,0) -> 0
A13: Batteries Sold% | B13: =VLOOKUP(B1,DSR!C9:AC54,27,0)
A15: Loyalty Sold | B15: =VLOOKUP(B1,DSR!C9:V54,20,0) -> 0
A16: Loyalty Sold% | B16: =VLOOKUP(B1,DSR!C9:AF54,30,0) -> #DIV/0!

Sheet Ds Data 
A1: Date | B1: Store Code | C1: Store Name | D1: NRGP No | E1: Bill No | F1: Bill Value | G1: Customer name | H1: Mobile No. | I1: ROM
A2: 02.09.2026 | B2: TLX5 | C2: HAMLEYS | D2: 37778 | E2: 104/24 | F2: 39996 | G2: ANWAR | H2: 9599514375 | I2: AJAY
A3: 03.09.2026 | B3: TLX5 | C3: HAMLEYS | D3: 37779 | E3: 104/01 | F3: 7794 | G3: Puneet | H3: 9893139823 | I3: AJAY
A4: 04.09.2026 | B4: TLX5 | C4: HAMLEYS | D4: =+D3+1 -> 37780 | E4: 104/8 | F4: 1999 | G4: PARUL | H4: 9711165459 | I4: AJAY
A5: 04.09.2026 | B5: TLX5 | C5: HAMLEYS | D5: =+D4+1 -> 37781 | E5: 104/28 | F5: 1098 | G5: NA | H5: NA | I5: AJAY
A6: 06.09.2026 | B6: TLX5 | C6: HAMLEYS | D6: =+D5+1 -> 37782 | E6: 104/59 | F6: 15999 | G6: MAYANK | H6: 9999832558 | I6: AJAY
A7: 09.09.2026 | B7: TLX5 | C7: HAMLEYS | D7: =+D6+1 -> 37783 | E7: 102/1 | F7: 32360 | G7: NEETU | H7: 8950069643 | I7: AJAY
A8: 11.09.2026 | B8: TLX5 | C8: HAMLEYS | D8: =+D7+1 -> 37784 | E8: 104/54 | F8: 2341 | G8: NEHA | H8: 8700733896 | I8: AJAY
A9: 12.09.2026 | B9: TLX5 | C9: HAMLEYS | D9: =+D8+1 -> 37785 | E9: 102/70 | F9: 1499 | G9: SUPRIYA | H9: 8881323969 | I9: AJAY
A10: 12.09.2026 | B10: TLX5 | C10: HAMLEYS | D10: =+D9+1 -> 37786 | E10: 104/23 | F10: 62930 | G10: SWATI | H10: 8076557926 | I10: AJAY
A11: 17.09.2026 | B11: TLX5 | C11: HAMLEYS | D11: =+D10+1 -> 37787 | E11: 102/18 | F11: 2492 | G11: PROMILA | H11: 7503751947 | I11: AJAY
A12: 17.09.2026 | B12: TLX5 | C12: HAMLEYS | D12: =+D11+1 -> 37788 | E12: 102/13 | F12: 5651 | G12: GARGI | H12: 9971363473 | I12: AJAY
A13: 18.09.2026 | B13: TLX5 | C13: HAMLEYS | D13: =+D12+1 -> 37789 | E13: 102/45 | F13: 991 | G13: Pranav | H13: 9971959113 | I13: AJAY
A14: 18.09.2026 | B14: TLX5 | C14: HAMLEYS | D14: =+D13+1 -> 37790 | E14: 104/6 | F14: 1205 | G14: Navaldeep | H14: 7340698625 | I14: AJAY
A15: 19.09.02026 | B15: TLX5 | C15: HAMLEYS | D15: =+D14+1 -> 37791 | E15: 102/35 | F15: 17032 | G15: ASHISH | H15: 9560049004 | I15: AJAY
A16: 22.09.2026 | B16: TLX5 | C16: HAMLEYS | D16: =+D15+1 -> 37792 | E16: 102/2 | F16: 9099 | G16: NISHA | H16: 9873823660 | I16: AJAY
A17: 23.09.2026 | B17: TLX5 | C17: HAMLEYS | D17: =+D16+1 -> 37793 | E17: 102/16 | F17: 12497 | G17: MARICA | H17: 8587859413 | I17: AJAY
A18: 25.09.2026 | B18: TLX5 | C18: HAMLEYS | D18: =+D17+1 -> 37794 | E18: 102/21 | F18: 5112 | G18: GUNJAN | H18: 9958155368 | I18: AJAY
